Workbook

Sheet MATRIZ INGRESO MES-PAIS
A1: MES | B1: El Salvador | C1: Chile | D1: Ecuador | E1: México | F1: Colombia | G1: República Dominicana | H1: Perú | I1: Paraguay | J1: Honduras | K1: Bolivia | L1: Argentina | M1: Guatemala | N1: Venezuela | O1: Uruguay | P1: Nicaragua | Q1: TOTAL MES
A2: 45658 | B2: =IFERROR(SUMIFS(INGRESOS!$J:$J,INGRESOS!$T:$T,B$1,INGRESOS!$A:$A,">="&$A2,INGRESOS!$A:$A,"<="&EOMONTH($A2,0)),0) -> 5970 | C2: =IFERROR(SUMIFS(INGRESOS!$J:$J,INGRESOS!$T:$T,C$1,INGRESOS!$A:$A,">="&$A2,INGRESOS!$A:$A,"<="&EOMONTH($A2,0)),0) -> 4983.5963 | D2: =IFERROR(SUMIFS(INGRESOS!$J:$J,INGRESOS!$T:$T,D$1,INGRESOS!$A:$A,">="&$A2,INGRESOS!$A:$A,"<="&EOMONTH($A2,0)),0) -> 0 | E2: =IFERROR(SUMIFS(INGRESOS!$J:$J,INGRESOS!$T:$T,E$1,INGRESOS!$A:$A,">="&$A2,INGRESOS!$A:$A,"<="&EOMONTH($A2,0)),0) -> 0 | F2: =IFERROR(SUMIFS(INGRESOS!$J:$J,INGRESOS!$T:$T,F$1,INGRESOS!$A:$A,">="&$A2,INGRESOS!$A:$A,"<="&EOMONTH($A2,0)),0) -> 0 | G2: =IFERROR(SUMIFS(INGRESOS!$J:$J,INGRESOS!$T:$T,G$1,INGRESOS!$A:$A,">="&$A2,INGRESOS!$A:$A,"<="&EOMONTH($A2,0)),0) -> 0 | H2: =IFERROR(SUMIFS(INGRESOS!$J:$J,INGRESOS!$T:$T,H$1,INGRESOS!$A:$A,">="&$A2,INGRESOS!$A:$A,"<="&EOMONTH($A2,0)),0) -> 0 | I2: =IFERROR(SUMIFS(INGRESOS!$J:$J,INGRESOS!$T:$T,I$1,INGRESOS!$A:$A,">="&$A2,INGRESOS!$A:$A,"<="&EOMONTH($A2,0)),0) -> 0 | ... P2: =IFERROR(SUMIFS(INGRESOS!$J:$J,INGRESOS!$T:$T,P$1,INGRESOS!$A:$A,">="&$A2,INGRESOS!$A:$A,"<="&EOMONTH($A2,0)),0) -> 0 | Q2: =+SUM(Tabla8[[#This Row],[El Salvador]:[Nicaragua]]) -> 10953.596
A3: 45689 | B3: =IFERROR(SUMIFS(INGRESOS!$J:$J,INGRESOS!$T:$T,B$1,INGRESOS!$A:$A,">="&$A3,INGRESOS!$A:$A,"<="&EOMONTH($A3,0)),0) -> 0 | C3: =IFERROR(SUMIFS(INGRESOS!$J:$J,INGRESOS!$T:$T,C$1,INGRESOS!$A:$A,">="&$A3,INGRESOS!$A:$A,"<="&EOMONTH($A3,0)),0) -> 10194.846 | D3: =IFERROR(SUMIFS(INGRESOS!$J:$J,INGRESOS!$T:$T,D$1,INGRESOS!$A:$A,">="&$A3,INGRESOS!$A:$A,"<="&EOMONTH($A3,0)),0) -> 0 | E3: =IFERROR(SUMIFS(INGRESOS!$J:$J,INGRESOS!$T:$T,E$1,INGRESOS!$A:$A,">="&$A3,INGRESOS!$A:$A,"<="&EOMONTH($A3,0)),0) -> 0 | F3: =IFERROR(SUMIFS(INGRESOS!$J:$J,INGRESOS!$T:$T,F$1,INGRESOS!$A:$A,">="&$A3,INGRESOS!$A:$A,"<="&EOMONTH($A3,0)),0) -> 0 | G3: =IFERROR(SUMIFS(INGRESOS!$J:$J,INGRESOS!$T:$T,G$1,INGRESOS!$A:$A,">="&$A3,INGRESOS!$A:$A,"<="&EOMONTH($A3,0)),0) -> 0 | H3: =IFERROR(SUMIFS(INGRESOS!$J:$J,INGRESOS!$T:$T,H$1,INGRESOS!$A:$A,">="&$A3,INGRESOS!$A:$A,"<="&EOMONTH($A3,0)),0) -> 0 | I3: =IFERROR(SUMIFS(INGRESOS!$J:$J,INGRESOS!$T:$T,I$1,INGRESOS!$A:$A,">="&$A3,INGRESOS!$A:$A,"<="&EOMONTH($A3,0)),0) -> 0 | ... P3: =IFERROR(SUMIFS(INGRESOS!$J:$J,INGRESOS!$T:$T,P$1,INGRESOS!$A:$A,">="&$A3,INGRESOS!$A:$A,"<="&EOMONTH($A3,0)),0) -> 0 | Q3: =+SUM(Tabla8[[#This Row],[El Salvador]:[Nicaragua]]) -> 10194.846
A4: 45717 | B4: =IFERROR(SUMIFS(INGRESOS!$J:$J,INGRESOS!$T:$T,B$1,INGRESOS!$A:$A,">="&$A4,INGRESOS!$A:$A,"<="&EOMONTH($A4,0)),0) -> 773.5 | C4: =IFERROR(SUMIFS(INGRESOS!$J:$J,INGRESOS!$T:$T,C$1,INGRESOS!$A:$A,">="&$A4,INGRESOS!$A:$A,"<="&EOMONTH($A4,0)),0) -> 9141.7076 | D4: =IFERROR(SUMIFS(INGRESOS!$J:$J,INGRESOS!$T:$T,D$1,INGRESOS!$A:$A,">="&$A4,INGRESOS!$A:$A,"<="&EOMONTH($A4,0)),0) -> 5570.0413 | E4: =IFERROR(SUMIFS(INGRESOS!$J:$J,INGRESOS!$T:$T,E$1,INGRESOS!$A:$A,">="&$A4,INGRESOS!$A:$A,"<="&EOMONTH($A4,0)),0) -> 7651.42 | F4: =IFERROR(SUMIFS(INGRESOS!$J:$J,INGRESOS!$T:$T,F$1,INGRESOS!$A:$A,">="&$A4,INGRESOS!$A:$A,"<="&EOMONTH($A4,0)),0) -> 1451 | G4: =IFERROR(SUMIFS(INGRESOS!$J:$J,INGRESOS!$T:$T,G$1,INGRESOS!$A:$A,">="&$A4,INGRESOS!$A:$A,"<="&EOMONTH($A4,0)),0) -> 483.5 | H4: =IFERROR(SUMIFS(INGRESOS!$J:$J,INGRESOS!$T:$T,H$1,INGRESOS!$A:$A,">="&$A4,INGRESOS!$A:$A,"<="&EOMONTH($A4,0)),0) -> 0 | I4: =IFERROR(SUMIFS(INGRESOS!$J:$J,INGRESOS!$T:$T,I$1,INGRESOS!$A:$A,">="&$A4,INGRESOS!$A:$A,"<="&EOMONTH($A4,0)),0) -> 0 | ... P4: =IFERROR(SUMIFS(INGRESOS!$J:$J,INGRESOS!$T:$T,P$1,INGRESOS!$A:$A,">="&$A4,INGRESOS!$A:$A,"<="&EOMONTH($A4,0)),0) -> 0 | Q4: =+SUM(Tabla8[[#This Row],[El Salvador]:[Nicaragua]]) -> 25071.169
A5: 45748 | B5: =IFERROR(SUMIFS(INGRESOS!$J:$J,INGRESOS!$T:$T,B$1,INGRESOS!$A:$A,">="&$A5,INGRESOS!$A:$A,"<="&EOMONTH($A5,0)),0) -> 773.5 | C5: =IFERROR(SUMIFS(INGRESOS!$J:$J,INGRESOS!$T:$T,C$1,INGRESOS!$A:$A,">="&$A5,INGRESOS!$A:$A,"<="&EOMONTH($A5,0)),0) -> 31289.041 | D5: =IFERROR(SUMIFS(INGRESOS!$J:$J,INGRESOS!$T:$T,D$1,INGRESOS!$A:$A,">="&$A5,INGRESOS!$A:$A,"<="&EOMONTH($A5,0)),0) -> 241.62 | E5: =IFERROR(SUMIFS(INGRESOS!$J:$J,INGRESOS!$T:$T,E$1,INGRESOS!$A:$A,">="&$A5,INGRESOS!$A:$A,"<="&EOMONTH($A5,0)),0) -> 12871.23 | F5: =IFERROR(SUMIFS(INGRESOS!$J:$J,INGRESOS!$T:$T,F$1,INGRESOS!$A:$A,">="&$A5,INGRESOS!$A:$A,"<="&EOMONTH($A5,0)),0) -> 5200 | G5: =IFERROR(SUMIFS(INGRESOS!$J:$J,INGRESOS!$T:$T,G$1,INGRESOS!$A:$A,">="&$A5,INGRESOS!$A:$A,"<="&EOMONTH($A5,0)),0) -> 0 | H5: =IFERROR(SUMIFS(INGRESOS!$J:$J,INGRESOS!$T:$T,H$1,INGRESOS!$A:$A,">="&$A5,INGRESOS!$A:$A,"<="&EOMONTH($A5,0)),0) -> 2934.75 | I5: =IFERROR(SUMIFS(INGRESOS!$J:$J,INGRESOS!$T:$T,I$1,INGRESOS!$A:$A,">="&$A5,INGRESOS!$A:$A,"<="&EOMONTH($A5,0)),0) -> 3871.91 | ... P5: =IFERROR(SUMIFS(INGRESOS!$J:$J,INGRESOS!$T:$T,P$1,INGRESOS!$A:$A,">="&$A5,INGRESOS!$A:$A,"<="&EOMONTH($A5,0)),0) -> 0 | Q5: =+SUM(Tabla8[[#This Row],[El Salvador]:[Nicaragua]]) -> 59179.123
A6: 45778 | B6: =IFERROR(SUMIFS(INGRESOS!$J:$J,INGRESOS!$T:$T,B$1,INGRESOS!$A:$A,">="&$A6,INGRESOS!$A:$A,"<="&EOMONTH($A6,0)),0) -> 4000 | C6: =IFERROR(SUMIFS(INGRESOS!$J:$J,INGRESOS!$T:$T,C$1,INGRESOS!$A:$A,">="&$A6,INGRESOS!$A:$A,"<="&EOMONTH($A6,0)),0) -> 6253.16 | D6: =IFERROR(SUMIFS(INGRESOS!$J:$J,INGRESOS!$T:$T,D$1,INGRESOS!$A:$A,">="&$A6,INGRESOS!$A:$A,"<="&EOMONTH($A6,0)),0) -> 6288.2 | E6: =IFERROR(SUMIFS(INGRESOS!$J:$J,INGRESOS!$T:$T,E$1,INGRESOS!$A:$A,">="&$A6,INGRESOS!$A:$A,"<="&EOMONTH($A6,0)),0) -> 16864.5 | F6: =IFERROR(SUMIFS(INGRESOS!$J:$J,INGRESOS!$T:$T,F$1,INGRESOS!$A:$A,">="&$A6,INGRESOS!$A:$A,"<="&EOMONTH($A6,0)),0) -> 7515 | G6: =IFERROR(SUMIFS(INGRESOS!$J:$J,INGRESOS!$T:$T,G$1,INGRESOS!$A:$A,">="&$A6,INGRESOS!$A:$A,"<="&EOMONTH($A6,0)),0) -> 0 | H6: =IFERROR(SUMIFS(INGRESOS!$J:$J,INGRESOS!$T:$T,H$1,INGRESOS!$A:$A,">="&$A6,INGRESOS!$A:$A,"<="&EOMONTH($A6,0)),0) -> 9427.71 | I6: =IFERROR(SUMIFS(INGRESOS!$J:$J,INGRESOS!$T:$T,I$1,INGRESOS!$A:$A,">="&$A6,INGRESOS!$A:$A,"<="&EOMONTH($A6,0)),0) -> 0 | ... P6: =IFERROR(SUMIFS(INGRESOS!$J:$J,INGRESOS!$T:$T,P$1,INGRESOS!$A:$A,">="&$A6,INGRESOS!$A:$A,"<="&EOMONTH($A6,0)),0) -> 0 | Q6: =+SUM(Tabla8[[#This Row],[El Salvador]:[Nicaragua]]) -> 57208.64
A7: 45809 | B7: =IFERROR(SUMIFS(INGRESOS!$J:$J,INGRESOS!$T:$T,B$1,INGRESOS!$A:$A,">="&$A7,INGRESOS!$A:$A,"<="&EOMONTH($A7,0)),0) -> 5828.16 | C7: =IFERROR(SUMIFS(INGRESOS!$J:$J,INGRESOS!$T:$T,C$1,INGRESOS!$A:$A,">="&$A7,INGRESOS!$A:$A,"<="&EOMONTH($A7,0)),0) -> 33923.677 | D7: =IFERROR(SUMIFS(INGRESOS!$J:$J,INGRESOS!$T:$T,D$1,INGRESOS!$A:$A,">="&$A7,INGRESOS!$A:$A,"<="&EOMONTH($A7,0)),0) -> 7028.6 | E7: =IFERROR(SUMIFS(INGRESOS!$J:$J,INGRESOS!$T:$T,E$1,INGRESOS!$A:$A,">="&$A7,INGRESOS!$A:$A,"<="&EOMONTH($A7,0)),0) -> 13509.11 | F7: =IFERROR(SUMIFS(INGRESOS!$J:$J,INGRESOS!$T:$T,F$1,INGRESOS!$A:$A,">="&$A7,INGRESOS!$A:$A,"<="&EOMONTH($A7,0)),0) -> 1934.75 | G7: =IFERROR(SUMIFS(INGRESOS!$J:$J,INGRESOS!$T:$T,G$1,INGRESOS!$A:$A,">="&$A7,INGRESOS!$A:$A,"<="&EOMONTH($A7,0)),0) -> 3869.75 | H7: =IFERROR(SUMIFS(INGRESOS!$J:$J,INGRESOS!$T:$T,H$1,INGRESOS!$A:$A,">="&$A7,INGRESOS!$A:$A,"<="&EOMONTH($A7,0)),0) -> 9228.38 | I7: =IFERROR(SUMIFS(INGRESOS!$J:$J,INGRESOS!$T:$T,I$1,INGRESOS!$A:$A,">="&$A7,INGRESOS!$A:$A,"<="&EOMONTH($A7,0)),0) -> 0 | ... P7: =IFERROR(SUMIFS(INGRESOS!$J:$J,INGRESOS!$T:$T,P$1,INGRESOS!$A:$A,">="&$A7,INGRESOS!$A:$A,"<="&EOMONTH($A7,0)),0) -> 0 | Q7: =+SUM(Tabla8[[#This Row],[El Salvador]:[Nicaragua]]) -> 80492.024
A8: 45839 | B8: =IFERROR(SUMIFS(INGRESOS!$J:$J,INGRESOS!$T:$T,B$1,INGRESOS!$A:$A,">="&$A8,INGRESOS!$A:$A,"<="&EOMONTH($A8,0)),0) -> 2224 | C8: =IFERROR(SUMIFS(INGRESOS!$J:$J,INGRESOS!$T:$T,C$1,INGRESOS!$A:$A,">="&$A8,INGRESOS!$A:$A,"<="&EOMONTH($A8,0)),0) -> 33461.017 | D8: =IFERROR(SUMIFS(INGRESOS!$J:$J,INGRESOS!$T:$T,D$1,INGRESOS!$A:$A,">="&$A8,INGRESOS!$A:$A,"<="&EOMONTH($A8,0)),0) -> 18819.6 | E8: =IFERROR(SUMIFS(INGRESOS!$J:$J,INGRESOS!$T:$T,E$1,INGRESOS!$A:$A,">="&$A8,INGRESOS!$A:$A,"<="&EOMONTH($A8,0)),0) -> 27679.19 | F8: =IFERROR(SUMIFS(INGRESOS!$J:$J,INGRESOS!$T:$T,F$1,INGRESOS!$A:$A,">="&$A8,INGRESOS!$A:$A,"<="&EOMONTH($A8,0)),0) -> 15852.61 | G8: =IFERROR(SUMIFS(INGRESOS!$J:$J,INGRESOS!$T:$T,G$1,INGRESOS!$A:$A,">="&$A8,INGRESOS!$A:$A,"<="&EOMONTH($A8,0)),0) -> 1783.8 | H8: =IFERROR(SUMIFS(INGRESOS!$J:$J,INGRESOS!$T:$T,H$1,INGRESOS!$A:$A,">="&$A8,INGRESOS!$A:$A,"<="&EOMONTH($A8,0)),0) -> 13293.749 | I8: =IFERROR(SUMIFS(INGRESOS!$J:$J,INGRESOS!$T:$T,I$1,INGRESOS!$A:$A,">="&$A8,INGRESOS!$A:$A,"<="&EOMONTH($A8,0)),0) -> 0 | ... P8: =IFERROR(SUMIFS(INGRESOS!$J:$J,INGRESOS!$T:$T,P$1,INGRESOS!$A:$A,">="&$A8,INGRESOS!$A:$A,"<="&EOMONTH($A8,0)),0) -> 0 | Q8: =+SUM(Tabla8[[#This Row],[El Salvador]:[Nicaragua]]) -> 137497.24
A9: 45870 | B9: =IFERROR(SUMIFS(INGRESOS!$J:$J,INGRESOS!$T:$T,B$1,INGRESOS!$A:$A,">="&$A9,INGRESOS!$A:$A,"<="&EOMONTH($A9,0)),0) -> 2284.95 | C9: =IFERROR(SUMIFS(INGRESOS!$J:$J,INGRESOS!$T:$T,C$1,INGRESOS!$A:$A,">="&$A9,INGRESOS!$A:$A,"<="&EOMONTH($A9,0)),0) -> 20911.007 | D9: =IFERROR(SUMIFS(INGRESOS!$J:$J,INGRESOS!$T:$T,D$1,INGRESOS!$A:$A,">="&$A9,INGRESOS!$A:$A,"<="&EOMONTH($A9,0)),0) -> 18711.717 | E9: =IFERROR(SUMIFS(INGRESOS!$J:$J,INGRESOS!$T:$T,E$1,INGRESOS!$A:$A,">="&$A9,INGRESOS!$A:$A,"<="&EOMONTH($A9,0)),0) -> 25697.33 | F9: =IFERROR(SUMIFS(INGRESOS!$J:$J,INGRESOS!$T:$T,F$1,INGRESOS!$A:$A,">="&$A9,INGRESOS!$A:$A,"<="&EOMONTH($A9,0)),0) -> 24522.35 | G9: =IFERROR(SUMIFS(INGRESOS!$J:$J,INGRESOS!$T:$T,G$1,INGRESOS!$A:$A,">="&$A9,INGRESOS!$A:$A,"<="&EOMONTH($A9,0)),0) -> 1547.5 | H9: =IFERROR(SUMIFS(INGRESOS!$J:$J,INGRESOS!$T:$T,H$1,INGRESOS!$A:$A,">="&$A9,INGRESOS!$A:$A,"<="&EOMONTH($A9,0)),0) -> 13018.945 | I9: =IFERROR(SUMIFS(INGRESOS!$J:$J,INGRESOS!$T:$T,I$1,INGRESOS!$A:$A,">="&$A9,INGRESOS!$A:$A,"<="&EOMONTH($A9,0)),0) -> 241.62 | ... P9: =IFERROR(SUMIFS(INGRESOS!$J:$J,INGRESOS!$T:$T,P$1,INGRESOS!$A:$A,">="&$A9,INGRESOS!$A:$A,"<="&EOMONTH($A9,0)),0) -> 0 | Q9: =+SUM(Tabla8[[#This Row],[El Salvador]:[Nicaragua]]) -> 140640.2
A10: 45901 | B10: =IFERROR(SUMIFS(INGRESOS!$J:$J,INGRESOS!$T:$T,B$1,INGRESOS!$A:$A,">="&$A10,INGRESOS!$A:$A,"<="&EOMONTH($A10,0)),0) -> 8404.35 | C10: =IFERROR(SUMIFS(INGRESOS!$J:$J,INGRESOS!$T:$T,C$1,INGRESOS!$A:$A,">="&$A10,INGRESOS!$A:$A,"<="&EOMONTH($A10,0)),0) -> 47474.003 | D10: =IFERROR(SUMIFS(INGRESOS!$J:$J,INGRESOS!$T:$T,D$1,INGRESOS!$A:$A,">="&$A10,INGRESOS!$A:$A,"<="&EOMONTH($A10,0)),0) -> 10735.85 | E10: =IFERROR(SUMIFS(INGRESOS!$J:$J,INGRESOS!$T:$T,E$1,INGRESOS!$A:$A,">="&$A10,INGRESOS!$A:$A,"<="&EOMONTH($A10,0)),0) -> 22794.6 | F10: =IFERROR(SUMIFS(INGRESOS!$J:$J,INGRESOS!$T:$T,F$1,INGRESOS!$A:$A,">="&$A10,INGRESOS!$A:$A,"<="&EOMONTH($A10,0)),0) -> 6528.61 | G10: =IFERROR(SUMIFS(INGRESOS!$J:$J,INGRESOS!$T:$T,G$1,INGRESOS!$A:$A,">="&$A10,INGRESOS!$A:$A,"<="&EOMONTH($A10,0)),0) -> 1426.56 | H10: =IFERROR(SUMIFS(INGRESOS!$J:$J,INGRESOS!$T:$T,H$1,INGRESOS!$A:$A,">="&$A10,INGRESOS!$A:$A,"<="&EOMONTH($A10,0)),0) -> 10634.458 | I10: =IFERROR(SUMIFS(INGRESOS!$J:$J,INGRESOS!$T:$T,I$1,INGRESOS!$A:$A,">="&$A10,INGRESOS!$A:$A,"<="&EOMONTH($A10,0)),0) -> 0 | ... P10: =IFERROR(SUMIFS(INGRESOS!$J:$J,INGRESOS!$T:$T,P$1,INGRESOS!$A:$A,">="&$A10,INGRESOS!$A:$A,"<="&EOMONTH($A10,0)),0) -> 2900.74 | Q10: =+SUM(Tabla8[[#This Row],[El Salvador]:[Nicaragua]]) -> 123609.3
A11: 45931 | B11: =IFERROR(SUMIFS(INGRESOS!$J:$J,INGRESOS!$T:$T,B$1,INGRESOS!$A:$A,">="&$A11,INGRESOS!$A:$A,"<="&EOMONTH($A11,0)),0) -> 4013.37 | C11: =IFERROR(SUMIFS(INGRESOS!$J:$J,INGRESOS!$T:$T,C$1,INGRESOS!$A:$A,">="&$A11,INGRESOS!$A:$A,"<="&EOMONTH($A11,0)),0) -> 26303.996 | D11: =IFERROR(SUMIFS(INGRESOS!$J:$J,INGRESOS!$T:$T,D$1,INGRESOS!$A:$A,">="&$A11,INGRESOS!$A:$A,"<="&EOMONTH($A11,0)),0) -> 15883.216 | E11: =IFERROR(SUMIFS(INGRESOS!$J:$J,INGRESOS!$T:$T,E$1,INGRESOS!$A:$A,">="&$A11,INGRESOS!$A:$A,"<="&EOMONTH($A11,0)),0) -> 23294.36 | F11: =IFERROR(SUMIFS(INGRESOS!$J:$J,INGRESOS!$T:$T,F$1,INGRESOS!$A:$A,">="&$A11,INGRESOS!$A:$A,"<="&EOMONTH($A11,0)),0) -> 15330.87 | G11: =IFERROR(SUMIFS(INGRESOS!$J:$J,INGRESOS!$T:$T,G$1,INGRESOS!$A:$A,">="&$A11,INGRESOS!$A:$A,"<="&EOMONTH($A11,0)),0) -> 2393.57 | H11: =IFERROR(SUMIFS(INGRESOS!$J:$J,INGRESOS!$T:$T,H$1,INGRESOS!$A:$A,">="&$A11,INGRESOS!$A:$A,"<="&EOMONTH($A11,0)),0) -> 11247.575 | I11: =IFERROR(SUMIFS(INGRESOS!$J:$J,INGRESOS!$T:$T,I$1,INGRESOS!$A:$A,">="&$A11,INGRESOS!$A:$A,"<="&EOMONTH($A11,0)),0) -> 0 | ... P11: =IFERROR(SUMIFS(INGRESOS!$J:$J,INGRESOS!$T:$T,P$1,INGRESOS!$A:$A,">="&$A11,INGRESOS!$A:$A,"<="&EOMONTH($A11,0)),0) -> 3579.5 | Q11: =+SUM(Tabla8[[#This Row],[El Salvador]:[Nicaragua]]) -> 115336.26
A12: 45962 | B12: =IFERROR(SUMIFS(INGRESOS!$J:$J,INGRESOS!$T:$T,B$1,INGRESOS!$A:$A,">="&$A12,INGRESOS!$A:$A,"<="&EOMONTH($A12,0)),0) -> 3626.62 | C12: =IFERROR(SUMIFS(INGRESOS!$J:$J,INGRESOS!$T:$T,C$1,INGRESOS!$A:$A,">="&$A12,INGRESOS!$A:$A,"<="&EOMONTH($A12,0)),0) -> 34104.14 | D12: =IFERROR(SUMIFS(INGRESOS!$J:$J,INGRESOS!$T:$T,D$1,INGRESOS!$A:$A,">="&$A12,INGRESOS!$A:$A,"<="&EOMONTH($A12,0)),0) -> 35237.233 | E12: =IFERROR(SUMIFS(INGRESOS!$J:$J,INGRESOS!$T:$T,E$1,INGRESOS!$A:$A,">="&$A12,INGRESOS!$A:$A,"<="&EOMONTH($A12,0)),0) -> 17004.6 | F12: =IFERROR(SUMIFS(INGRESOS!$J:$J,INGRESOS!$T:$T,F$1,INGRESOS!$A:$A,">="&$A12,INGRESOS!$A:$A,"<="&EOMONTH($A12,0)),0) -> 11079.7 | G12: =IFERROR(SUMIFS(INGRESOS!$J:$J,INGRESOS!$T:$T,G$1,INGRESOS!$A:$A,">="&$A12,INGRESOS!$A:$A,"<="&EOMONTH($A12,0)),0) -> 2393.57 | H12: =IFERROR(SUMIFS(INGRESOS!$J:$J,INGRESOS!$T:$T,H$1,INGRESOS!$A:$A,">="&$A12,INGRESOS!$A:$A,"<="&EOMONTH($A12,0)),0) -> 8569.74 | I12: =IFERROR(SUMIFS(INGRESOS!$J:$J,INGRESOS!$T:$T,I$1,INGRESOS!$A:$A,">="&$A12,INGRESOS!$A:$A,"<="&EOMONTH($A12,0)),0) -> 0 | ... P12: =IFERROR(SUMIFS(INGRESOS!$J:$J,INGRESOS!$T:$T,P$1,INGRESOS!$A:$A,">="&$A12,INGRESOS!$A:$A,"<="&EOMONTH($A12,0)),0) -> 3578.76 | Q12: =+SUM(Tabla8[[#This Row],[El Salvador]:[Nicaragua]]) -> 130999.57
A13: 45992 | B13: =IFERROR(SUMIFS(INGRESOS!$J:$J,INGRESOS!$T:$T,B$1,INGRESOS!$A:$A,">="&$A13,INGRESOS!$A:$A,"<="&EOMONTH($A13,0)),0) -> 3529.87 | C13: =IFERROR(SUMIFS(INGRESOS!$J:$J,INGRESOS!$T:$T,C$1,INGRESOS!$A:$A,">="&$A13,INGRESOS!$A:$A,"<="&EOMONTH($A13,0)),0) -> 31175.86 | D13: =IFERROR(SUMIFS(INGRESOS!$J:$J,INGRESOS!$T:$T,D$1,INGRESOS!$A:$A,">="&$A13,INGRESOS!$A:$A,"<="&EOMONTH($A13,0)),0) -> 21465.79 | E13: =IFERROR(SUMIFS(INGRESOS!$J:$J,INGRESOS!$T:$T,E$1,INGRESOS!$A:$A,">="&$A13,INGRESOS!$A:$A,"<="&EOMONTH($A13,0)),0) -> 26188.47 | F13: =IFERROR(SUMIFS(INGRESOS!$J:$J,INGRESOS!$T:$T,F$1,INGRESOS!$A:$A,">="&$A13,INGRESOS!$A:$A,"<="&EOMONTH($A13,0)),0) -> 12817.37 | G13: =IFERROR(SUMIFS(INGRESOS!$J:$J,INGRESOS!$T:$T,G$1,INGRESOS!$A:$A,">="&$A13,INGRESOS!$A:$A,"<="&EOMONTH($A13,0)),0) -> 2393.57 | H13: =IFERROR(SUMIFS(INGRESOS!$J:$J,INGRESOS!$T:$T,H$1,INGRESOS!$A:$A,">="&$A13,INGRESOS!$A:$A,"<="&EOMONTH($A13,0)),0) -> 7743.7911 | I13: =IFERROR(SUMIFS(INGRESOS!$J:$J,INGRESOS!$T:$T,I$1,INGRESOS!$A:$A,">="&$A13,INGRESOS!$A:$A,"<="&EOMONTH($A13,0)),0) -> 0 | ... P13: =IFERROR(SUMIFS(INGRESOS!$J:$J,INGRESOS!$T:$T,P$1,INGRESOS!$A:$A,">="&$A13,INGRESOS!$A:$A,"<="&EOMONTH($A13,0)),0) -> 3578.76 | Q13: =+SUM(Tabla8[[#This Row],[El Salvador]:[Nicaragua]]) -> 118222.47
A14: 46023 | B14: =IFERROR(SUMIFS(INGRESOS!$J:$J,INGRESOS!$T:$T,B$1,INGRESOS!$A:$A,">="&$A14,INGRESOS!$A:$A,"<="&EOMONTH($A14,0)),0) -> 2949.62 | C14: =IFERROR(SUMIFS(INGRESOS!$J:$J,INGRESOS!$T:$T,C$1,INGRESOS!$A:$A,">="&$A14,INGRESOS!$A:$A,"<="&EOMONTH($A14,0)),0) -> 25315.133 | D14: =IFERROR(SUMIFS(INGRESOS!$J:$J,INGRESOS!$T:$T,D$1,INGRESOS!$A:$A,">="&$A14,INGRESOS!$A:$A,"<="&EOMONTH($A14,0)),0) -> 22004.309 | E14: =IFERROR(SUMIFS(INGRESOS!$J:$J,INGRESOS!$T:$T,E$1,INGRESOS!$A:$A,">="&$A14,INGRESOS!$A:$A,"<="&EOMONTH($A14,0)),0) -> 24673.73 | F14: =IFERROR(SUMIFS(INGRESOS!$J:$J,INGRESOS!$T:$T,F$1,INGRESOS!$A:$A,">="&$A14,INGRESOS!$A:$A,"<="&EOMONTH($A14,0)),0) -> 27620.28 | G14: =IFERROR(SUMIFS(INGRESOS!$J:$J,INGRESOS!$T:$T,G$1,INGRESOS!$A:$A,">="&$A14,INGRESOS!$A:$A,"<="&EOMONTH($A14,0)),0) -> 3118.94 | H14: =IFERROR(SUMIFS(INGRESOS!$J:$J,INGRESOS!$T:$T,H$1,INGRESOS!$A:$A,">="&$A14,INGRESOS!$A:$A,"<="&EOMONTH($A14,0)),0) -> 12047.527 | I14: =IFERROR(SUMIFS(INGRESOS!$J:$J,INGRESOS!$T:$T,I$1,INGRESOS!$A:$A,">="&$A14,INGRESOS!$A:$A,"<="&EOMONTH($A14,0)),0) -> 0 | ... P14: =IFERROR(SUMIFS(INGRESOS!$J:$J,INGRESOS!$T:$T,P$1,INGRESOS!$A:$A,">="&$A14,INGRESOS!$A:$A,"<="&EOMONTH($A14,0)),0) -> 0 | Q14: =+SUM(Tabla8[[#This Row],[El Salvador]:[Nicaragua]]) -> 136271.11
A15: CASH IN PROM PAIS | B15: =+AVERAGE(B9:B14) -> 4134.7967 | C15: =+AVERAGE(C9:C14) -> 30880.69 | D15: =+AVERAGE(D9:D14) -> 20673.019 | E15: =+AVERAGE(E9:E14) -> 23275.515 | F15: =+AVERAGE(F9:F14) -> 16316.53 | G15: =+AVERAGE(G9:G14) -> 2212.285 | H15: =+AVERAGE(H9:H14) -> 10543.673 | I15: =+AVERAGE(I9:I14) -> 40.27 | ... P15: =+AVERAGE(P9:P14) -> 2272.96
A17: INGRESO PROGRAMADO
A18: MES | B18: El Salvador | C18: Chile | D18: Ecuador | E18: México | F18: Colombia | G18: República Dominicana | H18: Perú | I18: Paraguay | J18: Honduras | K18: Bolivia | L18: Argentina | M18: Guatemala | N18: Venezuela | O18: Uruguay | P18: Nicaragua | Q18: TOTAL MES
A19: 46054 | B19: =IFERROR(SUMIFS('CALENDARIO INGRESOS'!$I:$I,'CALENDARIO INGRESOS'!$C:$C,Tabla814[[#Headers],[El Salvador]],'CALENDARIO INGRESOS'!$G:$G,">="&$A19,'CALENDARIO INGRESOS'!$G:$G,"<="&EOMONTH($A19,0)),0) -> 2650 | C19: =IFERROR(SUMIFS('CALENDARIO INGRESOS'!$I:$I,'CALENDARIO INGRESOS'!$C:$C,Tabla814[[#Headers],[Chile]],'CALENDARIO INGRESOS'!$G:$G,">="&$A19,'CALENDARIO INGRESOS'!$G:$G,"<="&EOMONTH($A19,0)),0) -> 34354.54 | D19: =IFERROR(SUMIFS('CALENDARIO INGRESOS'!$I:$I,'CALENDARIO INGRESOS'!$C:$C,Tabla814[[#Headers],[Ecuador]],'CALENDARIO INGRESOS'!$G:$G,">="&$A19,'CALENDARIO INGRESOS'!$G:$G,"<="&EOMONTH($A19,0)),0) -> 25524 | E19: =IFERROR(SUMIFS('CALENDARIO INGRESOS'!$I:$I,'CALENDARIO INGRESOS'!$C:$C,Tabla814[[#Headers],[México]],'CALENDARIO INGRESOS'!$G:$G,">="&$A19,'CALENDARIO INGRESOS'!$G:$G,"<="&EOMONTH($A19,0)),0) -> 25039.63 | F19: =IFERROR(SUMIFS('CALENDARIO INGRESOS'!$I:$I,'CALENDARIO INGRESOS'!$C:$C,Tabla814[[#Headers],[Colombia]],'CALENDARIO INGRESOS'!$G:$G,">="&$A19,'CALENDARIO INGRESOS'!$G:$G,"<="&EOMONTH($A19,0)),0) -> 8350 | G19: =IFERROR(SUMIFS('CALENDARIO INGRESOS'!$I:$I,'CALENDARIO INGRESOS'!$C:$C,Tabla814[[#Headers],[República Dominicana]],'CALENDARIO INGRESOS'!$G:$G,">="&$A19,'CALENDARIO INGRESOS'!$G:$G,"<="&EOMONTH($A19,0)),0) -> 3475 | H19: =IFERROR(SUMIFS('CALENDARIO INGRESOS'!$I:$I,'CALENDARIO INGRESOS'!$C:$C,Tabla814[[#Headers],[Perú]],'CALENDARIO INGRESOS'!$G:$G,">="&$A19,'CALENDARIO INGRESOS'!$G:$G,"<="&EOMONTH($A19,0)),0) -> 9600 | I19: =IFERROR(SUMIFS('CALENDARIO INGRESOS'!$I:$I,'CALENDARIO INGRESOS'!$C:$C,Tabla814[[#Headers],[Paraguay]],'CALENDARIO INGRESOS'!$G:$G,">="&$A19,'CALENDARIO INGRESOS'!$G:$G,"<="&EOMONTH($A19,0)),0) -> 0 | J19: =IFERROR(SUMIFS('CALENDARIO INGRESOS'!$I:$I,'CALENDARIO INGRESOS'!$C:$C,Tabla814[[#Headers],[Honduras]],'CALENDARIO INGRESOS'!$G:$G,">="&$A19,'CALENDARIO INGRESOS'!$G:$G,"<="&EOMONTH($A19,0)),0) -> 1560 | K19: =IFERROR(SUMIFS('CALENDARIO INGRESOS'!$I:$I,'CALENDARIO INGRESOS'!$C:$C,Tabla814[[#Headers],[Bolivia]],'CALENDARIO INGRESOS'!$G:$G,">="&$A19,'CALENDARIO INGRESOS'!$G:$G,"<="&EOMONTH($A19,0)),0) -> 500 | L19: =IFERROR(SUMIFS('CALENDARIO INGRESOS'!$I:$I,'CALENDARIO INGRESOS'!$C:$C,Tabla814[[#Headers],[Argentina]],'CALENDARIO INGRESOS'!$G:$G,">="&$A19,'CALENDARIO INGRESOS'!$G:$G,"<="&EOMONTH($A19,0)),0) -> 2200 | M19: =IFERROR(SUMIFS('CALENDARIO INGRESOS'!$I:$I,'CALENDARIO INGRESOS'!$C:$C,Tabla814[[#Headers],[Guatemala]],'CALENDARIO INGRESOS'!$G:$G,">="&$A19,'CALENDARIO INGRESOS'!$G:$G,"<="&EOMONTH($A19,0)),0) -> 3450 | N19: =IFERROR(SUMIFS('CALENDARIO INGRESOS'!$I:$I,'CALENDARIO INGRESOS'!$C:$C,Tabla814[[#Headers],[Venezuela]],'CALENDARIO INGRESOS'!$G:$G,">="&$A19,'CALENDARIO INGRESOS'!$G:$G,"<="&EOMONTH($A19,0)),0) -> 12500 | O19: =IFERROR(SUMIFS('CALENDARIO INGRESOS'!$I:$I,'CALENDARIO INGRESOS'!$C:$C,Tabla814[[#Headers],[Uruguay]],'CALENDARIO INGRESOS'!$G:$G,">="&$A19,'CALENDARIO INGRESOS'!$G:$G,"<="&EOMONTH($A19,0)),0) -> 0 | P19: =IFERROR(SUMIFS('CALENDARIO INGRESOS'!$I:$I,'CALENDARIO INGRESOS'!$C:$C,Tabla814[[#Headers],[Nicaragua]],'CALENDARIO INGRESOS'!$G:$G,">="&$A19,'CALENDARIO INGRESOS'!$G:$G,"<="&EOMONTH($A19,0)),0) -> 0 | Q19: =+SUM(Tabla814[[#This Row],[El Salvador]:[Nicaragua]]) -> 129203.17
A20: 46082 | B20: =IFERROR(SUMIFS('CALENDARIO INGRESOS'!$I:$I,'CALENDARIO INGRESOS'!$C:$C,Tabla814[[#Headers],[El Salvador]],'CALENDARIO INGRESOS'!$G:$G,">="&$A20,'CALENDARIO INGRESOS'!$G:$G,"<="&EOMONTH($A20,0)),0) -> 2522 | C20: =IFERROR(SUMIFS('CALENDARIO INGRESOS'!$I:$I,'CALENDARIO INGRESOS'!$C:$C,Tabla814[[#Headers],[Chile]],'CALENDARIO INGRESOS'!$G:$G,">="&$A20,'CALENDARIO INGRESOS'!$G:$G,"<="&EOMONTH($A20,0)),0) -> 15515 | D20: =IFERROR(SUMIFS('CALENDARIO INGRESOS'!$I:$I,'CALENDARIO INGRESOS'!$C:$C,Tabla814[[#Headers],[Ecuador]],'CALENDARIO INGRESOS'!$G:$G,">="&$A20,'CALENDARIO INGRESOS'!$G:$G,"<="&EOMONTH($A20,0)),0) -> 17245 | E20: =IFERROR(SUMIFS('CALENDARIO INGRESOS'!$I:$I,'CALENDARIO INGRESOS'!$C:$C,Tabla814[[#Headers],[México]],'CALENDARIO INGRESOS'!$G:$G,">="&$A20,'CALENDARIO INGRESOS'!$G:$G,"<="&EOMONTH($A20,0)),0) -> 26888.63 | F20: =IFERROR(SUMIFS('CALENDARIO INGRESOS'!$I:$I,'CALENDARIO INGRESOS'!$C:$C,Tabla814[[#Headers],[Colombia]],'CALENDARIO INGRESOS'!$G:$G,">="&$A20,'CALENDARIO INGRESOS'!$G:$G,"<="&EOMONTH($A20,0)),0) -> 8350 | G20: =IFERROR(SUMIFS('CALENDARIO INGRESOS'!$I:$I,'CALENDARIO INGRESOS'!$C:$C,Tabla814[[#Headers],[República Dominicana]],'CALENDARIO INGRESOS'!$G:$G,">="&$A20,'CALENDARIO INGRESOS'!$G:$G,"<="&EOMONTH($A20,0)),0) -> 3475 | H20: =IFERROR(SUMIFS('CALENDARIO INGRESOS'!$I:$I,'CALENDARIO INGRESOS'!$C:$C,Tabla814[[#Headers],[Perú]],'CALENDARIO INGRESOS'!$G:$G,">="&$A20,'CALENDARIO INGRESOS'!$G:$G,"<="&EOMONTH($A20,0)),0) -> 13487 | I20: =IFERROR(SUMIFS('CALENDARIO INGRESOS'!$I:$I,'CALENDARIO INGRESOS'!$C:$C,Tabla814[[#Headers],[Paraguay]],'CALENDARIO INGRESOS'!$G:$G,">="&$A20,'CALENDARIO INGRESOS'!$G:$G,"<="&EOMONTH($A20,0)),0) -> 0 | J20: =IFERROR(SUMIFS('CALENDARIO INGRESOS'!$I:$I,'CALENDARIO INGRESOS'!$C:$C,Tabla814[[#Headers],[Honduras]],'CALENDARIO INGRESOS'!$G:$G,">="&$A20,'CALENDARIO INGRESOS'!$G:$G,"<="&EOMONTH($A20,0)),0) -> 1560 | K20: =IFERROR(SUMIFS('CALENDARIO INGRESOS'!$I:$I,'CALENDARIO INGRESOS'!$C:$C,Tabla814[[#Headers],[Bolivia]],'CALENDARIO INGRESOS'!$G:$G,">="&$A20,'CALENDARIO INGRESOS'!$G:$G,"<="&EOMONTH($A20,0)),0) -> 500 | L20: =IFERROR(SUMIFS('CALENDARIO INGRESOS'!$I:$I,'CALENDARIO INGRESOS'!$C:$C,Tabla814[[#Headers],[Argentina]],'CALENDARIO INGRESOS'!$G:$G,">="&$A20,'CALENDARIO INGRESOS'!$G:$G,"<="&EOMONTH($A20,0)),0) -> 2200 | M20: =IFERROR(SUMIFS('CALENDARIO INGRESOS'!$I:$I,'CALENDARIO INGRESOS'!$C:$C,Tabla814[[#Headers],[Guatemala]],'CALENDARIO INGRESOS'!$G:$G,">="&$A20,'CALENDARIO INGRESOS'!$G:$G,"<="&EOMONTH($A20,0)),0) -> 700 | N20: =IFERROR(SUMIFS('CALENDARIO INGRESOS'!$I:$I,'CALENDARIO INGRESOS'!$C:$C,Tabla814[[#Headers],[Venezuela]],'CALENDARIO INGRESOS'!$G:$G,">="&$A20,'CALENDARIO INGRESOS'!$G:$G,"<="&EOMONTH($A20,0)),0) -> 2000 | O20: =IFERROR(SUMIFS('CALENDARIO INGRESOS'!$I:$I,'CALENDARIO INGRESOS'!$C:$C,Tabla814[[#Headers],[Uruguay]],'CALENDARIO INGRESOS'!$G:$G,">="&$A20,'CALENDARIO INGRESOS'!$G:$G,"<="&EOMONTH($A20,0)),0) -> 0 | P20: =IFERROR(SUMIFS('CALENDARIO INGRESOS'!$I:$I,'CALENDARIO INGRESOS'!$C:$C,Tabla814[[#Headers],[Nicaragua]],'CALENDARIO INGRESOS'!$G:$G,">="&$A20,'CALENDARIO INGRESOS'!$G:$G,"<="&EOMONTH($A20,0)),0) -> 0 | Q20: =+SUM(Tabla814[[#This Row],[El Salvador]:[Nicaragua]]) -> 94442.63
A21: 46113 | B21: =IFERROR(SUMIFS('CALENDARIO INGRESOS'!$I:$I,'CALENDARIO INGRESOS'!$C:$C,Tabla814[[#Headers],[El Salvador]],'CALENDARIO INGRESOS'!$G:$G,">="&$A21,'CALENDARIO INGRESOS'!$G:$G,"<="&EOMONTH($A21,0)),0) -> 7850 | C21: =IFERROR(SUMIFS('CALENDARIO INGRESOS'!$I:$I,'CALENDARIO INGRESOS'!$C:$C,Tabla814[[#Headers],[Chile]],'CALENDARIO INGRESOS'!$G:$G,">="&$A21,'CALENDARIO INGRESOS'!$G:$G,"<="&EOMONTH($A21,0)),0) -> 16245 | D21: =IFERROR(SUMIFS('CALENDARIO INGRESOS'!$I:$I,'CALENDARIO INGRESOS'!$C:$C,Tabla814[[#Headers],[Ecuador]],'CALENDARIO INGRESOS'!$G:$G,">="&$A21,'CALENDARIO INGRESOS'!$G:$G,"<="&EOMONTH($A21,0)),0) -> 30404 | E21: =IFERROR(SUMIFS('CALENDARIO INGRESOS'!$I:$I,'CALENDARIO INGRESOS'!$C:$C,Tabla814[[#Headers],[México]],'CALENDARIO INGRESOS'!$G:$G,">="&$A21,'CALENDARIO INGRESOS'!$G:$G,"<="&EOMONTH($A21,0)),0) -> 25420.63 | F21: =IFERROR(SUMIFS('CALENDARIO INGRESOS'!$I:$I,'CALENDARIO INGRESOS'!$C:$C,Tabla814[[#Headers],[Colombia]],'CALENDARIO INGRESOS'!$G:$G,">="&$A21,'CALENDARIO INGRESOS'!$G:$G,"<="&EOMONTH($A21,0)),0) -> 14934 | G21: =IFERROR(SUMIFS('CALENDARIO INGRESOS'!$I:$I,'CALENDARIO INGRESOS'!$C:$C,Tabla814[[#Headers],[República Dominicana]],'CALENDARIO INGRESOS'!$G:$G,">="&$A21,'CALENDARIO INGRESOS'!$G:$G,"<="&EOMONTH($A21,0)),0) -> 2475 | H21: =IFERROR(SUMIFS('CALENDARIO INGRESOS'!$I:$I,'CALENDARIO INGRESOS'!$C:$C,Tabla814[[#Headers],[Perú]],'CALENDARIO INGRESOS'!$G:$G,">="&$A21,'CALENDARIO INGRESOS'!$G:$G,"<="&EOMONTH($A21,0)),0) -> 12200 | I21: =IFERROR(SUMIFS('CALENDARIO INGRESOS'!$I:$I,'CALENDARIO INGRESOS'!$C:$C,Tabla814[[#Headers],[Paraguay]],'CALENDARIO INGRESOS'!$G:$G,">="&$A21,'CALENDARIO INGRESOS'!$G:$G,"<="&EOMONTH($A21,0)),0) -> 0 | J21: =IFERROR(SUMIFS('CALENDARIO INGRESOS'!$I:$I,'CALENDARIO INGRESOS'!$C:$C,Tabla814[[#Headers],[Honduras]],'CALENDARIO INGRESOS'!$G:$G,">="&$A21,'CALENDARIO INGRESOS'!$G:$G,"<="&EOMONTH($A21,0)),0) -> 1560 | K21: =IFERROR(SUMIFS('CALENDARIO INGRESOS'!$I:$I,'CALENDARIO INGRESOS'!$C:$C,Tabla814[[#Headers],[Bolivia]],'CALENDARIO INGRESOS'!$G:$G,">="&$A21,'CALENDARIO INGRESOS'!$G:$G,"<="&EOMONTH($A21,0)),0) -> 500 | L21: =IFERROR(SUMIFS('CALENDARIO INGRESOS'!$I:$I,'CALENDARIO INGRESOS'!$C:$C,Tabla814[[#Headers],[Argentina]],'CALENDARIO INGRESOS'!$G:$G,">="&$A21,'CALENDARIO INGRESOS'!$G:$G,"<="&EOMONTH($A21,0)),0) -> 2200 | M21: =IFERROR(SUMIFS('CALENDARIO INGRESOS'!$I:$I,'CALENDARIO INGRESOS'!$C:$C,Tabla814[[#Headers],[Guatemala]],'CALENDARIO INGRESOS'!$G:$G,">="&$A21,'CALENDARIO INGRESOS'!$G:$G,"<="&EOMONTH($A21,0)),0) -> 700 | N21: =IFERROR(SUMIFS('CALENDARIO INGRESOS'!$I:$I,'CALENDARIO INGRESOS'!$C:$C,Tabla814[[#Headers],[Venezuela]],'CALENDARIO INGRESOS'!$G:$G,">="&$A21,'CALENDARIO INGRESOS'!$G:$G,"<="&EOMONTH($A21,0)),0) -> 2000 | O21: =IFERROR(SUMIFS('CALENDARIO INGRESOS'!$I:$I,'CALENDARIO INGRESOS'!$C:$C,Tabla814[[#Headers],[Uruguay]],'CALENDARIO INGRESOS'!$G:$G,">="&$A21,'CALENDARIO INGRESOS'!$G:$G,"<="&EOMONTH($A21,0)),0) -> 0 | P21: =IFERROR(SUMIFS('CALENDARIO INGRESOS'!$I:$I,'CALENDARIO INGRESOS'!$C:$C,Tabla814[[#Headers],[Nicaragua]],'CALENDARIO INGRESOS'!$G:$G,">="&$A21,'CALENDARIO INGRESOS'!$G:$G,"<="&EOMONTH($A21,0)),0) -> 0 | Q21: =+SUM(Tabla814[[#This Row],[El Salvador]:[Nicaragua]]) -> 116488.63
A22: 46143 | B22: =IFERROR(SUMIFS('CALENDARIO INGRESOS'!$I:$I,'CALENDARIO INGRESOS'!$C:$C,Tabla814[[#Headers],[El Salvador]],'CALENDARIO INGRESOS'!$G:$G,">="&$A22,'CALENDARIO INGRESOS'!$G:$G,"<="&EOMONTH($A22,0)),0) -> 1850 | C22: =IFERROR(SUMIFS('CALENDARIO INGRESOS'!$I:$I,'CALENDARIO INGRESOS'!$C:$C,Tabla814[[#Headers],[Chile]],'CALENDARIO INGRESOS'!$G:$G,">="&$A22,'CALENDARIO INGRESOS'!$G:$G,"<="&EOMONTH($A22,0)),0) -> 14750 | D22: =IFERROR(SUMIFS('CALENDARIO INGRESOS'!$I:$I,'CALENDARIO INGRESOS'!$C:$C,Tabla814[[#Headers],[Ecuador]],'CALENDARIO INGRESOS'!$G:$G,">="&$A22,'CALENDARIO INGRESOS'!$G:$G,"<="&EOMONTH($A22,0)),0) -> 15225 | E22: =IFERROR(SUMIFS('CALENDARIO INGRESOS'!$I:$I,'CALENDARIO INGRESOS'!$C:$C,Tabla814[[#Headers],[México]],'CALENDARIO INGRESOS'!$G:$G,">="&$A22,'CALENDARIO INGRESOS'!$G:$G,"<="&EOMONTH($A22,0)),0) -> 24720.63 | F22: =IFERROR(SUMIFS('CALENDARIO INGRESOS'!$I:$I,'CALENDARIO INGRESOS'!$C:$C,Tabla814[[#Headers],[Colombia]],'CALENDARIO INGRESOS'!$G:$G,">="&$A22,'CALENDARIO INGRESOS'!$G:$G,"<="&EOMONTH($A22,0)),0) -> 23061 | G22: =IFERROR(SUMIFS('CALENDARIO INGRESOS'!$I:$I,'CALENDARIO INGRESOS'!$C:$C,Tabla814[[#Headers],[República Dominicana]],'CALENDARIO INGRESOS'!$G:$G,">="&$A22,'CALENDARIO INGRESOS'!$G:$G,"<="&EOMONTH($A22,0)),0) -> 2600 | H22: =IFERROR(SUMIFS('CALENDARIO INGRESOS'!$I:$I,'CALENDARIO INGRESOS'!$C:$C,Tabla814[[#Headers],[Perú]],'CALENDARIO INGRESOS'!$G:$G,">="&$A22,'CALENDARIO INGRESOS'!$G:$G,"<="&EOMONTH($A22,0)),0) -> 12600 | I22: =IFERROR(SUMIFS('CALENDARIO INGRESOS'!$I:$I,'CALENDARIO INGRESOS'!$C:$C,Tabla814[[#Headers],[Paraguay]],'CALENDARIO INGRESOS'!$G:$G,">="&$A22,'CALENDARIO INGRESOS'!$G:$G,"<="&EOMONTH($A22,0)),0) -> 0 | J22: =IFERROR(SUMIFS('CALENDARIO INGRESOS'!$I:$I,'CALENDARIO INGRESOS'!$C:$C,Tabla814[[#Headers],[Honduras]],'CALENDARIO INGRESOS'!$G:$G,">="&$A22,'CALENDARIO INGRESOS'!$G:$G,"<="&EOMONTH($A22,0)),0) -> 1570 | K22: =IFERROR(SUMIFS('CALENDARIO INGRESOS'!$I:$I,'CALENDARIO INGRESOS'!$C:$C,Tabla814[[#Headers],[Bolivia]],'CALENDARIO INGRESOS'!$G:$G,">="&$A22,'CALENDARIO INGRESOS'!$G:$G,"<="&EOMONTH($A22,0)),0) -> 500 | L22: =IFERROR(SUMIFS('CALENDARIO INGRESOS'!$I:$I,'CALENDARIO INGRESOS'!$C:$C,Tabla814[[#Headers],[Argentina]],'CALENDARIO INGRESOS'!$G:$G,">="&$A22,'CALENDARIO INGRESOS'!$G:$G,"<="&EOMONTH($A22,0)),0) -> 2200 | M22: =IFERROR(SUMIFS('CALENDARIO INGRESOS'!$I:$I,'CALENDARIO INGRESOS'!$C:$C,Tabla814[[#Headers],[Guatemala]],'CALENDARIO INGRESOS'!$G:$G,">="&$A22,'CALENDARIO INGRESOS'!$G:$G,"<="&EOMONTH($A22,0)),0) -> 700 | N22: =IFERROR(SUMIFS('CALENDARIO INGRESOS'!$I:$I,'CALENDARIO INGRESOS'!$C:$C,Tabla814[[#Headers],[Venezuela]],'CALENDARIO INGRESOS'!$G:$G,">="&$A22,'CALENDARIO INGRESOS'!$G:$G,"<="&EOMONTH($A22,0)),0) -> 2000 | O22: =IFERROR(SUMIFS('CALENDARIO INGRESOS'!$I:$I,'CALENDARIO INGRESOS'!$C:$C,Tabla814[[#Headers],[Uruguay]],'CALENDARIO INGRESOS'!$G:$G,">="&$A22,'CALENDARIO INGRESOS'!$G:$G,"<="&EOMONTH($A22,0)),0) -> 0 | P22: =IFERROR(SUMIFS('CALENDARIO INGRESOS'!$I:$I,'CALENDARIO INGRESOS'!$C:$C,Tabla814[[#Headers],[Nicaragua]],'CALENDARIO INGRESOS'!$G:$G,">="&$A22,'CALENDARIO INGRESOS'!$G:$G,"<="&EOMONTH($A22,0)),0) -> 0 | Q22: =+SUM(Tabla814[[#This Row],[El Salvador]:[Nicaragua]]) -> 101776.63
A23: 46174 | B23: =IFERROR(SUMIFS('CALENDARIO INGRESOS'!$I:$I,'CALENDARIO INGRESOS'!$C:$C,Tabla814[[#Headers],[El Salvador]],'CALENDARIO INGRESOS'!$G:$G,">="&$A23,'CALENDARIO INGRESOS'!$G:$G,"<="&EOMONTH($A23,0)),0) -> 16850 | C23: =IFERROR(SUMIFS('CALENDARIO INGRESOS'!$I:$I,'CALENDARIO INGRESOS'!$C:$C,Tabla814[[#Headers],[Chile]],'CALENDARIO INGRESOS'!$G:$G,">="&$A23,'CALENDARIO INGRESOS'!$G:$G,"<="&EOMONTH($A23,0)),0) -> 14700 | D23: =IFERROR(SUMIFS('CALENDARIO INGRESOS'!$I:$I,'CALENDARIO INGRESOS'!$C:$C,Tabla814[[#Headers],[Ecuador]],'CALENDARIO INGRESOS'!$G:$G,">="&$A23,'CALENDARIO INGRESOS'!$G:$G,"<="&EOMONTH($A23,0)),0) -> 21245 | E23: =IFERROR(SUMIFS('CALENDARIO INGRESOS'!$I:$I,'CALENDARIO INGRESOS'!$C:$C,Tabla814[[#Headers],[México]],'CALENDARIO INGRESOS'!$G:$G,">="&$A23,'CALENDARIO INGRESOS'!$G:$G,"<="&EOMONTH($A23,0)),0) -> 30970.63 | F23: =IFERROR(SUMIFS('CALENDARIO INGRESOS'!$I:$I,'CALENDARIO INGRESOS'!$C:$C,Tabla814[[#Headers],[Colombia]],'CALENDARIO INGRESOS'!$G:$G,">="&$A23,'CALENDARIO INGRESOS'!$G:$G,"<="&EOMONTH($A23,0)),0) -> 9061 | G23: =IFERROR(SUMIFS('CALENDARIO INGRESOS'!$I:$I,'CALENDARIO INGRESOS'!$C:$C,Tabla814[[#Headers],[República Dominicana]],'CALENDARIO INGRESOS'!$G:$G,">="&$A23,'CALENDARIO INGRESOS'!$G:$G,"<="&EOMONTH($A23,0)),0) -> 1600 | H23: =IFERROR(SUMIFS('CALENDARIO INGRESOS'!$I:$I,'CALENDARIO INGRESOS'!$C:$C,Tabla814[[#Headers],[Perú]],'CALENDARIO INGRESOS'!$G:$G,">="&$A23,'CALENDARIO INGRESOS'!$G:$G,"<="&EOMONTH($A23,0)),0) -> 8600 | I23: =IFERROR(SUMIFS('CALENDARIO INGRESOS'!$I:$I,'CALENDARIO INGRESOS'!$C:$C,Tabla814[[#Headers],[Paraguay]],'CALENDARIO INGRESOS'!$G:$G,">="&$A23,'CALENDARIO INGRESOS'!$G:$G,"<="&EOMONTH($A23,0)),0) -> 0 | J23: =IFERROR(SUMIFS('CALENDARIO INGRESOS'!$I:$I,'CALENDARIO INGRESOS'!$C:$C,Tabla814[[#Headers],[Honduras]],'CALENDARIO INGRESOS'!$G:$G,">="&$A23,'CALENDARIO INGRESOS'!$G:$G,"<="&EOMONTH($A23,0)),0) -> 0 | K23: =IFERROR(SUMIFS('CALENDARIO INGRESOS'!$I:$I,'CALENDARIO INGRESOS'!$C:$C,Tabla814[[#Headers],[Bolivia]],'CALENDARIO INGRESOS'!$G:$G,">="&$A23,'CALENDARIO INGRESOS'!$G:$G,"<="&EOMONTH($A23,0)),0) -> 500 | L23: =IFERROR(SUMIFS('CALENDARIO INGRESOS'!$I:$I,'CALENDARIO INGRESOS'!$C:$C,Tabla814[[#Headers],[Argentina]],'CALENDARIO INGRESOS'!$G:$G,">="&$A23,'CALENDARIO INGRESOS'!$G:$G,"<="&EOMONTH($A23,0)),0) -> 2200 | M23: =IFERROR(SUMIFS('CALENDARIO INGRESOS'!$I:$I,'CALENDARIO INGRESOS'!$C:$C,Tabla814[[#Headers],[Guatemala]],'CALENDARIO INGRESOS'!$G:$G,">="&$A23,'CALENDARIO INGRESOS'!$G:$G,"<="&EOMONTH($A23,0)),0) -> 700 | N23: =IFERROR(SUMIFS('CALENDARIO INGRESOS'!$I:$I,'CALENDARIO INGRESOS'!$C:$C,Tabla814[[#Headers],[Venezuela]],'CALENDARIO INGRESOS'!$G:$G,">="&$A23,'CALENDARIO INGRESOS'!$G:$G,"<="&EOMONTH($A23,0)),0) -> 2000 | O23: =IFERROR(SUMIFS('CALENDARIO INGRESOS'!$I:$I,'CALENDARIO INGRESOS'!$C:$C,Tabla814[[#Headers],[Uruguay]],'CALENDARIO INGRESOS'!$G:$G,">="&$A23,'CALENDARIO INGRESOS'!$G:$G,"<="&EOMONTH($A23,0)),0) -> 0 | P23: =IFERROR(SUMIFS('CALENDARIO INGRESOS'!$I:$I,'CALENDARIO INGRESOS'!$C:$C,Tabla814[[#Headers],[Nicaragua]],'CALENDARIO INGRESOS'!$G:$G,">="&$A23,'CALENDARIO INGRESOS'!$G:$G,"<="&EOMONTH($A23,0)),0) -> 0 | Q23: =+SUM(Tabla814[[#This Row],[El Salvador]:[Nicaragua]]) -> 108426.63
A24: 46204 | B24: =IFERROR(SUMIFS('CALENDARIO INGRESOS'!$I:$I,'CALENDARIO INGRESOS'!$C:$C,Tabla814[[#Headers],[El Salvador]],'CALENDARIO INGRESOS'!$G:$G,">="&$A24,'CALENDARIO INGRESOS'!$G:$G,"<="&EOMONTH($A24,0)),0) -> 850 | C24: =IFERROR(SUMIFS('CALENDARIO INGRESOS'!$I:$I,'CALENDARIO INGRESOS'!$C:$C,Tabla814[[#Headers],[Chile]],'CALENDARIO INGRESOS'!$G:$G,">="&$A24,'CALENDARIO INGRESOS'!$G:$G,"<="&EOMONTH($A24,0)),0) -> 17700 | D24: =IFERROR(SUMIFS('CALENDARIO INGRESOS'!$I:$I,'CALENDARIO INGRESOS'!$C:$C,Tabla814[[#Headers],[Ecuador]],'CALENDARIO INGRESOS'!$G:$G,">="&$A24,'CALENDARIO INGRESOS'!$G:$G,"<="&EOMONTH($A24,0)),0) -> 23475 | E24: =IFERROR(SUMIFS('CALENDARIO INGRESOS'!$I:$I,'CALENDARIO INGRESOS'!$C:$C,Tabla814[[#Headers],[México]],'CALENDARIO INGRESOS'!$G:$G,">="&$A24,'CALENDARIO INGRESOS'!$G:$G,"<="&EOMONTH($A24,0)),0) -> 20534 | F24: =IFERROR(SUMIFS('CALENDARIO INGRESOS'!$I:$I,'CALENDARIO INGRESOS'!$C:$C,Tabla814[[#Headers],[Colombia]],'CALENDARIO INGRESOS'!$G:$G,">="&$A24,'CALENDARIO INGRESOS'!$G:$G,"<="&EOMONTH($A24,0)),0) -> 8261 | G24: =IFERROR(SUMIFS('CALENDARIO INGRESOS'!$I:$I,'CALENDARIO INGRESOS'!$C:$C,Tabla814[[#Headers],[República Dominicana]],'CALENDARIO INGRESOS'!$G:$G,">="&$A24,'CALENDARIO INGRESOS'!$G:$G,"<="&EOMONTH($A24,0)),0) -> 5800 | H24: =IFERROR(SUMIFS('CALENDARIO INGRESOS'!$I:$I,'CALENDARIO INGRESOS'!$C:$C,Tabla814[[#Headers],[Perú]],'CALENDARIO INGRESOS'!$G:$G,">="&$A24,'CALENDARIO INGRESOS'!$G:$G,"<="&EOMONTH($A24,0)),0) -> 8250 | I24: =IFERROR(SUMIFS('CALENDARIO INGRESOS'!$I:$I,'CALENDARIO INGRESOS'!$C:$C,Tabla814[[#Headers],[Paraguay]],'CALENDARIO INGRESOS'!$G:$G,">="&$A24,'CALENDARIO INGRESOS'!$G:$G,"<="&EOMONTH($A24,0)),0) -> 0 | J24: =IFERROR(SUMIFS('CALENDARIO INGRESOS'!$I:$I,'CALENDARIO INGRESOS'!$C:$C,Tabla814[[#Headers],[Honduras]],'CALENDARIO INGRESOS'!$G:$G,">="&$A24,'CALENDARIO INGRESOS'!$G:$G,"<="&EOMONTH($A24,0)),0) -> 0 | K24: =IFERROR(SUMIFS('CALENDARIO INGRESOS'!$I:$I,'CALENDARIO INGRESOS'!$C:$C,Tabla814[[#Headers],[Bolivia]],'CALENDARIO INGRESOS'!$G:$G,">="&$A24,'CALENDARIO INGRESOS'!$G:$G,"<="&EOMONTH($A24,0)),0) -> 500 | L24: =IFERROR(SUMIFS('CALENDARIO INGRESOS'!$I:$I,'CALENDARIO INGRESOS'!$C:$C,Tabla814[[#Headers],[Argentina]],'CALENDARIO INGRESOS'!$G:$G,">="&$A24,'CALENDARIO INGRESOS'!$G:$G,"<="&EOMONTH($A24,0)),0) -> 2200 | M24: =IFERROR(SUMIFS('CALENDARIO INGRESOS'!$I:$I,'CALENDARIO INGRESOS'!$C:$C,Tabla814[[#Headers],[Guatemala]],'CALENDARIO INGRESOS'!$G:$G,">="&$A24,'CALENDARIO INGRESOS'!$G:$G,"<="&EOMONTH($A24,0)),0) -> 700 | N24: =IFERROR(SUMIFS('CALENDARIO INGRESOS'!$I:$I,'CALENDARIO INGRESOS'!$C:$C,Tabla814[[#Headers],[Venezuela]],'CALENDARIO INGRESOS'!$G:$G,">="&$A24,'CALENDARIO INGRESOS'!$G:$G,"<="&EOMONTH($A24,0)),0) -> 2000 | O24: =IFERROR(SUMIFS('CALENDARIO INGRESOS'!$I:$I,'CALENDARIO INGRESOS'!$C:$C,Tabla814[[#Headers],[Uruguay]],'CALENDARIO INGRESOS'!$G:$G,">="&$A24,'CALENDARIO INGRESOS'!$G:$G,"<="&EOMONTH($A24,0)),0) -> 0 | P24: =IFERROR(SUMIFS('CALENDARIO INGRESOS'!$I:$I,'CALENDARIO INGRESOS'!$C:$C,Tabla814[[#Headers],[Nicaragua]],'CALENDARIO INGRESOS'!$G:$G,">="&$A24,'CALENDARIO INGRESOS'!$G:$G,"<="&EOMONTH($A24,0)),0) -> 0 | Q24: =+SUM(Tabla814[[#This Row],[El Salvador]:[Nicaragua]]) -> 90270
A25: 46235 | B25: =IFERROR(SUMIFS('CALENDARIO INGRESOS'!$I:$I,'CALENDARIO INGRESOS'!$C:$C,Tabla814[[#Headers],[El Salvador]],'CALENDARIO INGRESOS'!$G:$G,">="&$A25,'CALENDARIO INGRESOS'!$G:$G,"<="&EOMONTH($A25,0)),0) -> 850 | C25: =IFERROR(SUMIFS('CALENDARIO INGRESOS'!$I:$I,'CALENDARIO INGRESOS'!$C:$C,Tabla814[[#Headers],[Chile]],'CALENDARIO INGRESOS'!$G:$G,">="&$A25,'CALENDARIO INGRESOS'!$G:$G,"<="&EOMONTH($A25,0)),0) -> 12100 | D25: =IFERROR(SUMIFS('CALENDARIO INGRESOS'!$I:$I,'CALENDARIO INGRESOS'!$C:$C,Tabla814[[#Headers],[Ecuador]],'CALENDARIO INGRESOS'!$G:$G,">="&$A25,'CALENDARIO INGRESOS'!$G:$G,"<="&EOMONTH($A25,0)),0) -> 13100 | E25: =IFERROR(SUMIFS('CALENDARIO INGRESOS'!$I:$I,'CALENDARIO INGRESOS'!$C:$C,Tabla814[[#Headers],[México]],'CALENDARIO INGRESOS'!$G:$G,">="&$A25,'CALENDARIO INGRESOS'!$G:$G,"<="&EOMONTH($A25,0)),0) -> 18534 | F25: =IFERROR(SUMIFS('CALENDARIO INGRESOS'!$I:$I,'CALENDARIO INGRESOS'!$C:$C,Tabla814[[#Headers],[Colombia]],'CALENDARIO INGRESOS'!$G:$G,">="&$A25,'CALENDARIO INGRESOS'!$G:$G,"<="&EOMONTH($A25,0)),0) -> 10511 | G25: =IFERROR(SUMIFS('CALENDARIO INGRESOS'!$I:$I,'CALENDARIO INGRESOS'!$C:$C,Tabla814[[#Headers],[República Dominicana]],'CALENDARIO INGRESOS'!$G:$G,">="&$A25,'CALENDARIO INGRESOS'!$G:$G,"<="&EOMONTH($A25,0)),0) -> 1000 | H25: =IFERROR(SUMIFS('CALENDARIO INGRESOS'!$I:$I,'CALENDARIO INGRESOS'!$C:$C,Tabla814[[#Headers],[Perú]],'CALENDARIO INGRESOS'!$G:$G,">="&$A25,'CALENDARIO INGRESOS'!$G:$G,"<="&EOMONTH($A25,0)),0) -> 10216 | I25: =IFERROR(SUMIFS('CALENDARIO INGRESOS'!$I:$I,'CALENDARIO INGRESOS'!$C:$C,Tabla814[[#Headers],[Paraguay]],'CALENDARIO INGRESOS'!$G:$G,">="&$A25,'CALENDARIO INGRESOS'!$G:$G,"<="&EOMONTH($A25,0)),0) -> 0 | J25: =IFERROR(SUMIFS('CALENDARIO INGRESOS'!$I:$I,'CALENDARIO INGRESOS'!$C:$C,Tabla814[[#Headers],[Honduras]],'CALENDARIO INGRESOS'!$G:$G,">="&$A25,'CALENDARIO INGRESOS'!$G:$G,"<="&EOMONTH($A25,0)),0) -> 0 | K25: =IFERROR(SUMIFS('CALENDARIO INGRESOS'!$I:$I,'CALENDARIO INGRESOS'!$C:$C,Tabla814[[#Headers],[Bolivia]],'CALENDARIO INGRESOS'!$G:$G,">="&$A25,'CALENDARIO INGRESOS'!$G:$G,"<="&EOMONTH($A25,0)),0) -> 500 | L25: =IFERROR(SUMIFS('CALENDARIO INGRESOS'!$I:$I,'CALENDARIO INGRESOS'!$C:$C,Tabla814[[#Headers],[Argentina]],'CALENDARIO INGRESOS'!$G:$G,">="&$A25,'CALENDARIO INGRESOS'!$G:$G,"<="&EOMONTH($A25,0)),0) -> 2200 | M25: =IFERROR(SUMIFS('CALENDARIO INGRESOS'!$I:$I,'CALENDARIO INGRESOS'!$C:$C,Tabla814[[#Headers],[Guatemala]],'CALENDARIO INGRESOS'!$G:$G,">="&$A25,'CALENDARIO INGRESOS'!$G:$G,"<="&EOMONTH($A25,0)),0) -> 700 | N25: =IFERROR(SUMIFS('CALENDARIO INGRESOS'!$I:$I,'CALENDARIO INGRESOS'!$C:$C,Tabla814[[#Headers],[Venezuela]],'CALENDARIO INGRESOS'!$G:$G,">="&$A25,'CALENDARIO INGRESOS'!$G:$G,"<="&EOMONTH($A25,0)),0) -> 2000 | O25: =IFERROR(SUMIFS('CALENDARIO INGRESOS'!$I:$I,'CALENDARIO INGRESOS'!$C:$C,Tabla814[[#Headers],[Uruguay]],'CALENDARIO INGRESOS'!$G:$G,">="&$A25,'CALENDARIO INGRESOS'!$G:$G,"<="&EOMONTH($A25,0)),0) -> 0 | P25: =IFERROR(SUMIFS('CALENDARIO INGRESOS'!$I:$I,'CALENDARIO INGRESOS'!$C:$C,Tabla814[[#Headers],[Nicaragua]],'CALENDARIO INGRESOS'!$G:$G,">="&$A25,'CALENDARIO INGRESOS'!$G:$G,"<="&EOMONTH($A25,0)),0) -> 0 | Q25: =+SUM(Tabla814[[#This Row],[El Salvador]:[Nicaragua]]) -> 71711
A26: 46266 | B26: =IFERROR(SUMIFS('CALENDARIO INGRESOS'!$I:$I,'CALENDARIO INGRESOS'!$C:$C,Tabla814[[#Headers],[El Salvador]],'CALENDARIO INGRESOS'!$G:$G,">="&$A26,'CALENDARIO INGRESOS'!$G:$G,"<="&EOMONTH($A26,0)),0) -> 1850 | C26: =IFERROR(SUMIFS('CALENDARIO INGRESOS'!$I:$I,'CALENDARIO INGRESOS'!$C:$C,Tabla814[[#Headers],[Chile]],'CALENDARIO INGRESOS'!$G:$G,">="&$A26,'CALENDARIO INGRESOS'!$G:$G,"<="&EOMONTH($A26,0)),0) -> 12700 | D26: =IFERROR(SUMIFS('CALENDARIO INGRESOS'!$I:$I,'CALENDARIO INGRESOS'!$C:$C,Tabla814[[#Headers],[Ecuador]],'CALENDARIO INGRESOS'!$G:$G,">="&$A26,'CALENDARIO INGRESOS'!$G:$G,"<="&EOMONTH($A26,0)),0) -> 12900 | E26: =IFERROR(SUMIFS('CALENDARIO INGRESOS'!$I:$I,'CALENDARIO INGRESOS'!$C:$C,Tabla814[[#Headers],[México]],'CALENDARIO INGRESOS'!$G:$G,">="&$A26,'CALENDARIO INGRESOS'!$G:$G,"<="&EOMONTH($A26,0)),0) -> 17634 | F26: =IFERROR(SUMIFS('CALENDARIO INGRESOS'!$I:$I,'CALENDARIO INGRESOS'!$C:$C,Tabla814[[#Headers],[Colombia]],'CALENDARIO INGRESOS'!$G:$G,">="&$A26,'CALENDARIO INGRESOS'!$G:$G,"<="&EOMONTH($A26,0)),0) -> 5961 | G26: =IFERROR(SUMIFS('CALENDARIO INGRESOS'!$I:$I,'CALENDARIO INGRESOS'!$C:$C,Tabla814[[#Headers],[República Dominicana]],'CALENDARIO INGRESOS'!$G:$G,">="&$A26,'CALENDARIO INGRESOS'!$G:$G,"<="&EOMONTH($A26,0)),0) -> 1000 | H26: =IFERROR(SUMIFS('CALENDARIO INGRESOS'!$I:$I,'CALENDARIO INGRESOS'!$C:$C,Tabla814[[#Headers],[Perú]],'CALENDARIO INGRESOS'!$G:$G,">="&$A26,'CALENDARIO INGRESOS'!$G:$G,"<="&EOMONTH($A26,0)),0) -> 4350 | I26: =IFERROR(SUMIFS('CALENDARIO INGRESOS'!$I:$I,'CALENDARIO INGRESOS'!$C:$C,Tabla814[[#Headers],[Paraguay]],'CALENDARIO INGRESOS'!$G:$G,">="&$A26,'CALENDARIO INGRESOS'!$G:$G,"<="&EOMONTH($A26,0)),0) -> 0 | J26: =IFERROR(SUMIFS('CALENDARIO INGRESOS'!$I:$I,'CALENDARIO INGRESOS'!$C:$C,Tabla814[[#Headers],[Honduras]],'CALENDARIO INGRESOS'!$G:$G,">="&$A26,'CALENDARIO INGRESOS'!$G:$G,"<="&EOMONTH($A26,0)),0) -> 1187 | K26: =IFERROR(SUMIFS('CALENDARIO INGRESOS'!$I:$I,'CALENDARIO INGRESOS'!$C:$C,Tabla814[[#Headers],[Bolivia]],'CALENDARIO INGRESOS'!$G:$G,">="&$A26,'CALENDARIO INGRESOS'!$G:$G,"<="&EOMONTH($A26,0)),0) -> 500 | L26: =IFERROR(SUMIFS('CALENDARIO INGRESOS'!$I:$I,'CALENDARIO INGRESOS'!$C:$C,Tabla814[[#Headers],[Argentina]],'CALENDARIO INGRESOS'!$G:$G,">="&$A26,'CALENDARIO INGRESOS'!$G:$G,"<="&EOMONTH($A26,0)),0) -> 1200 | M26: =IFERROR(SUMIFS('CALENDARIO INGRESOS'!$I:$I,'CALENDARIO INGRESOS'!$C:$C,Tabla814[[#Headers],[Guatemala]],'CALENDARIO INGRESOS'!$G:$G,">="&$A26,'CALENDARIO INGRESOS'!$G:$G,"<="&EOMONTH($A26,0)),0) -> 700 | N26: =IFERROR(SUMIFS('CALENDARIO INGRESOS'!$I:$I,'CALENDARIO INGRESOS'!$C:$C,Tabla814[[#Headers],[Venezuela]],'CALENDARIO INGRESOS'!$G:$G,">="&$A26,'CALENDARIO INGRESOS'!$G:$G,"<="&EOMONTH($A26,0)),0) -> 2000 | O26: =IFERROR(SUMIFS('CALENDARIO INGRESOS'!$I:$I,'CALENDARIO INGRESOS'!$C:$C,Tabla814[[#Headers],[Uruguay]],'CALENDARIO INGRESOS'!$G:$G,">="&$A26,'CALENDARIO INGRESOS'!$G:$G,"<="&EOMONTH($A26,0)),0) -> 0 | P26: =IFERROR(SUMIFS('CALENDARIO INGRESOS'!$I:$I,'CALENDARIO INGRESOS'!$C:$C,Tabla814[[#Headers],[Nicaragua]],'CALENDARIO INGRESOS'!$G:$G,">="&$A26,'CALENDARIO INGRESOS'!$G:$G,"<="&EOMONTH($A26,0)),0) -> 0 | Q26: =+SUM(Tabla814[[#This Row],[El Salvador]:[Nicaragua]]) -> 61982
A27: 46296 | B27: =IFERROR(SUMIFS('CALENDARIO INGRESOS'!$I:$I,'CALENDARIO INGRESOS'!$C:$C,Tabla814[[#Headers],[El Salvador]],'CALENDARIO INGRESOS'!$G:$G,">="&$A27,'CALENDARIO INGRESOS'!$G:$G,"<="&EOMONTH($A27,0)),0) -> 1850 | C27: =IFERROR(SUMIFS('CALENDARIO INGRESOS'!$I:$I,'CALENDARIO INGRESOS'!$C:$C,Tabla814[[#Headers],[Chile]],'CALENDARIO INGRESOS'!$G:$G,">="&$A27,'CALENDARIO INGRESOS'!$G:$G,"<="&EOMONTH($A27,0)),0) -> 11850 | D27: =IFERROR(SUMIFS('CALENDARIO INGRESOS'!$I:$I,'CALENDARIO INGRESOS'!$C:$C,Tabla814[[#Headers],[Ecuador]],'CALENDARIO INGRESOS'!$G:$G,">="&$A27,'CALENDARIO INGRESOS'!$G:$G,"<="&EOMONTH($A27,0)),0) -> 16150 | E27: =IFERROR(SUMIFS('CALENDARIO INGRESOS'!$I:$I,'CALENDARIO INGRESOS'!$C:$C,Tabla814[[#Headers],[México]],'CALENDARIO INGRESOS'!$G:$G,">="&$A27,'CALENDARIO INGRESOS'!$G:$G,"<="&EOMONTH($A27,0)),0) -> 16634 | F27: =IFERROR(SUMIFS('CALENDARIO INGRESOS'!$I:$I,'CALENDARIO INGRESOS'!$C:$C,Tabla814[[#Headers],[Colombia]],'CALENDARIO INGRESOS'!$G:$G,">="&$A27,'CALENDARIO INGRESOS'!$G:$G,"<="&EOMONTH($A27,0)),0) -> 5461 | G27: =IFERROR(SUMIFS('CALENDARIO INGRESOS'!$I:$I,'CALENDARIO INGRESOS'!$C:$C,Tabla814[[#Headers],[República Dominicana]],'CALENDARIO INGRESOS'!$G:$G,">="&$A27,'CALENDARIO INGRESOS'!$G:$G,"<="&EOMONTH($A27,0)),0) -> 1000 | H27: =IFERROR(SUMIFS('CALENDARIO INGRESOS'!$I:$I,'CALENDARIO INGRESOS'!$C:$C,Tabla814[[#Headers],[Perú]],'CALENDARIO INGRESOS'!$G:$G,">="&$A27,'CALENDARIO INGRESOS'!$G:$G,"<="&EOMONTH($A27,0)),0) -> 5350 | I27: =IFERROR(SUMIFS('CALENDARIO INGRESOS'!$I:$I,'CALENDARIO INGRESOS'!$C:$C,Tabla814[[#Headers],[Paraguay]],'CALENDARIO INGRESOS'!$G:$G,">="&$A27,'CALENDARIO INGRESOS'!$G:$G,"<="&EOMONTH($A27,0)),0) -> 0 | J27: =IFERROR(SUMIFS('CALENDARIO INGRESOS'!$I:$I,'CALENDARIO INGRESOS'!$C:$C,Tabla814[[#Headers],[Honduras]],'CALENDARIO INGRESOS'!$G:$G,">="&$A27,'CALENDARIO INGRESOS'!$G:$G,"<="&EOMONTH($A27,0)),0) -> 2187 | K27: =IFERROR(SUMIFS('CALENDARIO INGRESOS'!$I:$I,'CALENDARIO INGRESOS'!$C:$C,Tabla814[[#Headers],[Bolivia]],'CALENDARIO INGRESOS'!$G:$G,">="&$A27,'CALENDARIO INGRESOS'!$G:$G,"<="&EOMONTH($A27,0)),0) -> 500 | L27: =IFERROR(SUMIFS('CALENDARIO INGRESOS'!$I:$I,'CALENDARIO INGRESOS'!$C:$C,Tabla814[[#Headers],[Argentina]],'CALENDARIO INGRESOS'!$G:$G,">="&$A27,'CALENDARIO INGRESOS'!$G:$G,"<="&EOMONTH($A27,0)),0) -> 1200 | M27: =IFERROR(SUMIFS('CALENDARIO INGRESOS'!$I:$I,'CALENDARIO INGRESOS'!$C:$C,Tabla814[[#Headers],[Guatemala]],'CALENDARIO INGRESOS'!$G:$G,">="&$A27,'CALENDARIO INGRESOS'!$G:$G,"<="&EOMONTH($A27,0)),0) -> 1576 | N27: =IFERROR(SUMIFS('CALENDARIO INGRESOS'!$I:$I,'CALENDARIO INGRESOS'!$C:$C,Tabla814[[#Headers],[Venezuela]],'CALENDARIO INGRESOS'!$G:$G,">="&$A27,'CALENDARIO INGRESOS'!$G:$G,"<="&EOMONTH($A27,0)),0) -> 6000 | O27: =IFERROR(SUMIFS('CALENDARIO INGRESOS'!$I:$I,'CALENDARIO INGRESOS'!$C:$C,Tabla814[[#Headers],[Uruguay]],'CALENDARIO INGRESOS'!$G:$G,">="&$A27,'CALENDARIO INGRESOS'!$G:$G,"<="&EOMONTH($A27,0)),0) -> 0 | P27: =IFERROR(SUMIFS('CALENDARIO INGRESOS'!$I:$I,'CALENDARIO INGRESOS'!$C:$C,Tabla814[[#Headers],[Nicaragua]],'CALENDARIO INGRESOS'!$G:$G,">="&$A27,'CALENDARIO INGRESOS'!$G:$G,"<="&EOMONTH($A27,0)),0) -> 0 | Q27: =+SUM(Tabla814[[#This Row],[El Salvador]:[Nicaragua]]) -> 69758
A28: 46327 | B28: =IFERROR(SUMIFS('CALENDARIO INGRESOS'!$I:$I,'CALENDARIO INGRESOS'!$C:$C,Tabla814[[#Headers],[El Salvador]],'CALENDARIO INGRESOS'!$G:$G,">="&$A28,'CALENDARIO INGRESOS'!$G:$G,"<="&EOMONTH($A28,0)),0) -> 2950 | C28: =IFERROR(SUMIFS('CALENDARIO INGRESOS'!$I:$I,'CALENDARIO INGRESOS'!$C:$C,Tabla814[[#Headers],[Chile]],'CALENDARIO INGRESOS'!$G:$G,">="&$A28,'CALENDARIO INGRESOS'!$G:$G,"<="&EOMONTH($A28,0)),0) -> 16079 | D28: =IFERROR(SUMIFS('CALENDARIO INGRESOS'!$I:$I,'CALENDARIO INGRESOS'!$C:$C,Tabla814[[#Headers],[Ecuador]],'CALENDARIO INGRESOS'!$G:$G,">="&$A28,'CALENDARIO INGRESOS'!$G:$G,"<="&EOMONTH($A28,0)),0) -> 17400 | E28: =IFERROR(SUMIFS('CALENDARIO INGRESOS'!$I:$I,'CALENDARIO INGRESOS'!$C:$C,Tabla814[[#Headers],[México]],'CALENDARIO INGRESOS'!$G:$G,">="&$A28,'CALENDARIO INGRESOS'!$G:$G,"<="&EOMONTH($A28,0)),0) -> 15434 | F28: =IFERROR(SUMIFS('CALENDARIO INGRESOS'!$I:$I,'CALENDARIO INGRESOS'!$C:$C,Tabla814[[#Headers],[Colombia]],'CALENDARIO INGRESOS'!$G:$G,">="&$A28,'CALENDARIO INGRESOS'!$G:$G,"<="&EOMONTH($A28,0)),0) -> 5200 | G28: =IFERROR(SUMIFS('CALENDARIO INGRESOS'!$I:$I,'CALENDARIO INGRESOS'!$C:$C,Tabla814[[#Headers],[República Dominicana]],'CALENDARIO INGRESOS'!$G:$G,">="&$A28,'CALENDARIO INGRESOS'!$G:$G,"<="&EOMONTH($A28,0)),0) -> 2000 | H28: =IFERROR(SUMIFS('CALENDARIO INGRESOS'!$I:$I,'CALENDARIO INGRESOS'!$C:$C,Tabla814[[#Headers],[Perú]],'CALENDARIO INGRESOS'!$G:$G,">="&$A28,'CALENDARIO INGRESOS'!$G:$G,"<="&EOMONTH($A28,0)),0) -> 6350 | I28: =IFERROR(SUMIFS('CALENDARIO INGRESOS'!$I:$I,'CALENDARIO INGRESOS'!$C:$C,Tabla814[[#Headers],[Paraguay]],'CALENDARIO INGRESOS'!$G:$G,">="&$A28,'CALENDARIO INGRESOS'!$G:$G,"<="&EOMONTH($A28,0)),0) -> 0 | J28: =IFERROR(SUMIFS('CALENDARIO INGRESOS'!$I:$I,'CALENDARIO INGRESOS'!$C:$C,Tabla814[[#Headers],[Honduras]],'CALENDARIO INGRESOS'!$G:$G,">="&$A28,'CALENDARIO INGRESOS'!$G:$G,"<="&EOMONTH($A28,0)),0) -> 2187 | K28: =IFERROR(SUMIFS('CALENDARIO INGRESOS'!$I:$I,'CALENDARIO INGRESOS'!$C:$C,Tabla814[[#Headers],[Bolivia]],'CALENDARIO INGRESOS'!$G:$G,">="&$A28,'CALENDARIO INGRESOS'!$G:$G,"<="&EOMONTH($A28,0)),0) -> 500 | L28: =IFERROR(SUMIFS('CALENDARIO INGRESOS'!$I:$I,'CALENDARIO INGRESOS'!$C:$C,Tabla814[[#Headers],[Argentina]],'CALENDARIO INGRESOS'!$G:$G,">="&$A28,'CALENDARIO INGRESOS'!$G:$G,"<="&EOMONTH($A28,0)),0) -> 1200 | M28: =IFERROR(SUMIFS('CALENDARIO INGRESOS'!$I:$I,'CALENDARIO INGRESOS'!$C:$C,Tabla814[[#Headers],[Guatemala]],'CALENDARIO INGRESOS'!$G:$G,">="&$A28,'CALENDARIO INGRESOS'!$G:$G,"<="&EOMONTH($A28,0)),0) -> 1600 | N28: =IFERROR(SUMIFS('CALENDARIO INGRESOS'!$I:$I,'CALENDARIO INGRESOS'!$C:$C,Tabla814[[#Headers],[Venezuela]],'CALENDARIO INGRESOS'!$G:$G,">="&$A28,'CALENDARIO INGRESOS'!$G:$G,"<="&EOMONTH($A28,0)),0) -> 1000 | O28: =IFERROR(SUMIFS('CALENDARIO INGRESOS'!$I:$I,'CALENDARIO INGRESOS'!$C:$C,Tabla814[[#Headers],[Uruguay]],'CALENDARIO INGRESOS'!$G:$G,">="&$A28,'CALENDARIO INGRESOS'!$G:$G,"<="&EOMONTH($A28,0)),0) -> 0 | P28: =IFERROR(SUMIFS('CALENDARIO INGRESOS'!$I:$I,'CALENDARIO INGRESOS'!$C:$C,Tabla814[[#Headers],[Nicaragua]],'CALENDARIO INGRESOS'!$G:$G,">="&$A28,'CALENDARIO INGRESOS'!$G:$G,"<="&EOMONTH($A28,0)),0) -> 0 | Q28: =+SUM(Tabla814[[#This Row],[El Salvador]:[Nicaragua]]) -> 71900
A29: 46357 | B29: =IFERROR(SUMIFS('CALENDARIO INGRESOS'!$I:$I,'CALENDARIO INGRESOS'!$C:$C,Tabla814[[#Headers],[El Salvador]],'CALENDARIO INGRESOS'!$G:$G,">="&$A29,'CALENDARIO INGRESOS'!$G:$G,"<="&EOMONTH($A29,0)),0) -> 2950 | C29: =IFERROR(SUMIFS('CALENDARIO INGRESOS'!$I:$I,'CALENDARIO INGRESOS'!$C:$C,Tabla814[[#Headers],[Chile]],'CALENDARIO INGRESOS'!$G:$G,">="&$A29,'CALENDARIO INGRESOS'!$G:$G,"<="&EOMONTH($A29,0)),0) -> 27038 | D29: =IFERROR(SUMIFS('CALENDARIO INGRESOS'!$I:$I,'CALENDARIO INGRESOS'!$C:$C,Tabla814[[#Headers],[Ecuador]],'CALENDARIO INGRESOS'!$G:$G,">="&$A29,'CALENDARIO INGRESOS'!$G:$G,"<="&EOMONTH($A29,0)),0) -> 11800 | E29: =IFERROR(SUMIFS('CALENDARIO INGRESOS'!$I:$I,'CALENDARIO INGRESOS'!$C:$C,Tabla814[[#Headers],[México]],'CALENDARIO INGRESOS'!$G:$G,">="&$A29,'CALENDARIO INGRESOS'!$G:$G,"<="&EOMONTH($A29,0)),0) -> 12804 | F29: =IFERROR(SUMIFS('CALENDARIO INGRESOS'!$I:$I,'CALENDARIO INGRESOS'!$C:$C,Tabla814[[#Headers],[Colombia]],'CALENDARIO INGRESOS'!$G:$G,">="&$A29,'CALENDARIO INGRESOS'!$G:$G,"<="&EOMONTH($A29,0)),0) -> 5200 | G29: =IFERROR(SUMIFS('CALENDARIO INGRESOS'!$I:$I,'CALENDARIO INGRESOS'!$C:$C,Tabla814[[#Headers],[República Dominicana]],'CALENDARIO INGRESOS'!$G:$G,">="&$A29,'CALENDARIO INGRESOS'!$G:$G,"<="&EOMONTH($A29,0)),0) -> 2000 | H29: =IFERROR(SUMIFS('CALENDARIO INGRESOS'!$I:$I,'CALENDARIO INGRESOS'!$C:$C,Tabla814[[#Headers],[Perú]],'CALENDARIO INGRESOS'!$G:$G,">="&$A29,'CALENDARIO INGRESOS'!$G:$G,"<="&EOMONTH($A29,0)),0) -> 8350 | I29: =IFERROR(SUMIFS('CALENDARIO INGRESOS'!$I:$I,'CALENDARIO INGRESOS'!$C:$C,Tabla814[[#Headers],[Paraguay]],'CALENDARIO INGRESOS'!$G:$G,">="&$A29,'CALENDARIO INGRESOS'!$G:$G,"<="&EOMONTH($A29,0)),0) -> 0 | J29: =IFERROR(SUMIFS('CALENDARIO INGRESOS'!$I:$I,'CALENDARIO INGRESOS'!$C:$C,Tabla814[[#Headers],[Honduras]],'CALENDARIO INGRESOS'!$G:$G,">="&$A29,'CALENDARIO INGRESOS'!$G:$G,"<="&EOMONTH($A29,0)),0) -> 2187 | K29: =IFERROR(SUMIFS('CALENDARIO INGRESOS'!$I:$I,'CALENDARIO INGRESOS'!$C:$C,Tabla814[[#Headers],[Bolivia]],'CALENDARIO INGRESOS'!$G:$G,">="&$A29,'CALENDARIO INGRESOS'!$G:$G,"<="&EOMONTH($A29,0)),0) -> 2741 | L29: =IFERROR(SUMIFS('CALENDARIO INGRESOS'!$I:$I,'CALENDARIO INGRESOS'!$C:$C,Tabla814[[#Headers],[Argentina]],'CALENDARIO INGRESOS'!$G:$G,">="&$A29,'CALENDARIO INGRESOS'!$G:$G,"<="&EOMONTH($A29,0)),0) -> 1200 | M29: =IFERROR(SUMIFS('CALENDARIO INGRESOS'!$I:$I,'CALENDARIO INGRESOS'!$C:$C,Tabla814[[#Headers],[Guatemala]],'CALENDARIO INGRESOS'!$G:$G,">="&$A29,'CALENDARIO INGRESOS'!$G:$G,"<="&EOMONTH($A29,0)),0) -> 1600 | N29: =IFERROR(SUMIFS('CALENDARIO INGRESOS'!$I:$I,'CALENDARIO INGRESOS'!$C:$C,Tabla814[[#Headers],[Venezuela]],'CALENDARIO INGRESOS'!$G:$G,">="&$A29,'CALENDARIO INGRESOS'!$G:$G,"<="&EOMONTH($A29,0)),0) -> 0 | O29: =IFERROR(SUMIFS('CALENDARIO INGRESOS'!$I:$I,'CALENDARIO INGRESOS'!$C:$C,Tabla814[[#Headers],[Uruguay]],'CALENDARIO INGRESOS'!$G:$G,">="&$A29,'CALENDARIO INGRESOS'!$G:$G,"<="&EOMONTH($A29,0)),0) -> 0 | P29: =IFERROR(SUMIFS('CALENDARIO INGRESOS'!$I:$I,'CALENDARIO INGRESOS'!$C:$C,Tabla814[[#Headers],[Nicaragua]],'CALENDARIO INGRESOS'!$G:$G,">="&$A29,'CALENDARIO INGRESOS'!$G:$G,"<="&EOMONTH($A29,0)),0) -> 0 | Q29: =+SUM(Tabla814[[#This Row],[El Salvador]:[Nicaragua]]) -> 77870
A30: 46388 | B30: =IFERROR(SUMIFS('CALENDARIO INGRESOS'!$I:$I,'CALENDARIO INGRESOS'!$C:$C,Tabla814[[#Headers],[El Salvador]],'CALENDARIO INGRESOS'!$G:$G,">="&$A30,'CALENDARIO INGRESOS'!$G:$G,"<="&EOMONTH($A30,0)),0) -> 2100 | C30: =IFERROR(SUMIFS('CALENDARIO INGRESOS'!$I:$I,'CALENDARIO INGRESOS'!$C:$C,Tabla814[[#Headers],[Chile]],'CALENDARIO INGRESOS'!$G:$G,">="&$A30,'CALENDARIO INGRESOS'!$G:$G,"<="&EOMONTH($A30,0)),0) -> 23638 | D30: =IFERROR(SUMIFS('CALENDARIO INGRESOS'!$I:$I,'CALENDARIO INGRESOS'!$C:$C,Tabla814[[#Headers],[Ecuador]],'CALENDARIO INGRESOS'!$G:$G,">="&$A30,'CALENDARIO INGRESOS'!$G:$G,"<="&EOMONTH($A30,0)),0) -> 9800 | E30: =IFERROR(SUMIFS('CALENDARIO INGRESOS'!$I:$I,'CALENDARIO INGRESOS'!$C:$C,Tabla814[[#Headers],[México]],'CALENDARIO INGRESOS'!$G:$G,">="&$A30,'CALENDARIO INGRESOS'!$G:$G,"<="&EOMONTH($A30,0)),0) -> 12154 | F30: =IFERROR(SUMIFS('CALENDARIO INGRESOS'!$I:$I,'CALENDARIO INGRESOS'!$C:$C,Tabla814[[#Headers],[Colombia]],'CALENDARIO INGRESOS'!$G:$G,">="&$A30,'CALENDARIO INGRESOS'!$G:$G,"<="&EOMONTH($A30,0)),0) -> 6200 | G30: =IFERROR(SUMIFS('CALENDARIO INGRESOS'!$I:$I,'CALENDARIO INGRESOS'!$C:$C,Tabla814[[#Headers],[República Dominicana]],'CALENDARIO INGRESOS'!$G:$G,">="&$A30,'CALENDARIO INGRESOS'!$G:$G,"<="&EOMONTH($A30,0)),0) -> 2000 | H30: =IFERROR(SUMIFS('CALENDARIO INGRESOS'!$I:$I,'CALENDARIO INGRESOS'!$C:$C,Tabla814[[#Headers],[Perú]],'CALENDARIO INGRESOS'!$G:$G,">="&$A30,'CALENDARIO INGRESOS'!$G:$G,"<="&EOMONTH($A30,0)),0) -> 5850 | I30: =IFERROR(SUMIFS('CALENDARIO INGRESOS'!$I:$I,'CALENDARIO INGRESOS'!$C:$C,Tabla814[[#Headers],[Paraguay]],'CALENDARIO INGRESOS'!$G:$G,">="&$A30,'CALENDARIO INGRESOS'!$G:$G,"<="&EOMONTH($A30,0)),0) -> 0 | J30: =IFERROR(SUMIFS('CALENDARIO INGRESOS'!$I:$I,'CALENDARIO INGRESOS'!$C:$C,Tabla814[[#Headers],[Honduras]],'CALENDARIO INGRESOS'!$G:$G,">="&$A30,'CALENDARIO INGRESOS'!$G:$G,"<="&EOMONTH($A30,0)),0) -> 2000 | K30: =IFERROR(SUMIFS('CALENDARIO INGRESOS'!$I:$I,'CALENDARIO INGRESOS'!$C:$C,Tabla814[[#Headers],[Bolivia]],'CALENDARIO INGRESOS'!$G:$G,">="&$A30,'CALENDARIO INGRESOS'!$G:$G,"<="&EOMONTH($A30,0)),0) -> 0 | L30: =IFERROR(SUMIFS('CALENDARIO INGRESOS'!$I:$I,'CALENDARIO INGRESOS'!$C:$C,Tabla814[[#Headers],[Argentina]],'CALENDARIO INGRESOS'!$G:$G,">="&$A30,'CALENDARIO INGRESOS'!$G:$G,"<="&EOMONTH($A30,0)),0) -> 1200 | M30: =IFERROR(SUMIFS('CALENDARIO INGRESOS'!$I:$I,'CALENDARIO INGRESOS'!$C:$C,Tabla814[[#Headers],[Guatemala]],'CALENDARIO INGRESOS'!$G:$G,">="&$A30,'CALENDARIO INGRESOS'!$G:$G,"<="&EOMONTH($A30,0)),0) -> 1600 | N30: =IFERROR(SUMIFS('CALENDARIO INGRESOS'!$I:$I,'CALENDARIO INGRESOS'!$C:$C,Tabla814[[#Headers],[Venezuela]],'CALENDARIO INGRESOS'!$G:$G,">="&$A30,'CALENDARIO INGRESOS'!$G:$G,"<="&EOMONTH($A30,0)),0) -> 0 | O30: =IFERROR(SUMIFS('CALENDARIO INGRESOS'!$I:$I,'CALENDARIO INGRESOS'!$C:$C,Tabla814[[#Headers],[Uruguay]],'CALENDARIO INGRESOS'!$G:$G,">="&$A30,'CALENDARIO INGRESOS'!$G:$G,"<="&EOMONTH($A30,0)),0) -> 0 | P30: =IFERROR(SUMIFS('CALENDARIO INGRESOS'!$I:$I,'CALENDARIO INGRESOS'!$C:$C,Tabla814[[#Headers],[Nicaragua]],'CALENDARIO INGRESOS'!$G:$G,">="&$A30,'CALENDARIO INGRESOS'!$G:$G,"<="&EOMONTH($A30,0)),0) -> 0 | Q30: =+SUM(Tabla814[[#This Row],[El Salvador]:[Nicaragua]]) -> 66542
... A41: 46722 | B41: =IFERROR(SUMIFS('CALENDARIO INGRESOS'!$I:$I,'CALENDARIO INGRESOS'!$C:$C,Tabla814[[#Headers],[El Salvador]],'CALENDARIO INGRESOS'!$G:$G,">="&$A41,'CALENDARIO INGRESOS'!$G:$G,"<="&EOMONTH($A41,0)),0) -> 800 | C41: =IFERROR(SUMIFS('CALENDARIO INGRESOS'!$I:$I,'CALENDARIO INGRESOS'!$C:$C,Tabla814[[#Headers],[Chile]],'CALENDARIO INGRESOS'!$G:$G,">="&$A41,'CALENDARIO INGRESOS'!$G:$G,"<="&EOMONTH($A41,0)),0) -> 6908 | D41: =IFERROR(SUMIFS('CALENDARIO INGRESOS'!$I:$I,'CALENDARIO INGRESOS'!$C:$C,Tabla814[[#Headers],[Ecuador]],'CALENDARIO INGRESOS'!$G:$G,">="&$A41,'CALENDARIO INGRESOS'!$G:$G,"<="&EOMONTH($A41,0)),0) -> 8950 | E41: =IFERROR(SUMIFS('CALENDARIO INGRESOS'!$I:$I,'CALENDARIO INGRESOS'!$C:$C,Tabla814[[#Headers],[México]],'CALENDARIO INGRESOS'!$G:$G,">="&$A41,'CALENDARIO INGRESOS'!$G:$G,"<="&EOMONTH($A41,0)),0) -> 6750 | F41: =IFERROR(SUMIFS('CALENDARIO INGRESOS'!$I:$I,'CALENDARIO INGRESOS'!$C:$C,Tabla814[[#Headers],[Colombia]],'CALENDARIO INGRESOS'!$G:$G,">="&$A41,'CALENDARIO INGRESOS'!$G:$G,"<="&EOMONTH($A41,0)),0) -> 3450 | G41: =IFERROR(SUMIFS('CALENDARIO INGRESOS'!$I:$I,'CALENDARIO INGRESOS'!$C:$C,Tabla814[[#Headers],[República Dominicana]],'CALENDARIO INGRESOS'!$G:$G,">="&$A41,'CALENDARIO INGRESOS'!$G:$G,"<="&EOMONTH($A41,0)),0) -> 1000 | H41: =IFERROR(SUMIFS('CALENDARIO INGRESOS'!$I:$I,'CALENDARIO INGRESOS'!$C:$C,Tabla814[[#Headers],[Perú]],'CALENDARIO INGRESOS'!$G:$G,">="&$A41,'CALENDARIO INGRESOS'!$G:$G,"<="&EOMONTH($A41,0)),0) -> 3800 | I41: =IFERROR(SUMIFS('CALENDARIO INGRESOS'!$I:$I,'CALENDARIO INGRESOS'!$C:$C,Tabla814[[#Headers],[Paraguay]],'CALENDARIO INGRESOS'!$G:$G,">="&$A41,'CALENDARIO INGRESOS'!$G:$G,"<="&EOMONTH($A41,0)),0) -> 0 | J41: =IFERROR(SUMIFS('CALENDARIO INGRESOS'!$I:$I,'CALENDARIO INGRESOS'!$C:$C,Tabla814[[#Headers],[Honduras]],'CALENDARIO INGRESOS'!$G:$G,">="&$A41,'CALENDARIO INGRESOS'!$G:$G,"<="&EOMONTH($A41,0)),0) -> 0 | K41: =IFERROR(SUMIFS('CALENDARIO INGRESOS'!$I:$I,'CALENDARIO INGRESOS'!$C:$C,Tabla814[[#Headers],[Bolivia]],'CALENDARIO INGRESOS'!$G:$G,">="&$A41,'CALENDARIO INGRESOS'!$G:$G,"<="&EOMONTH($A41,0)),0) -> 0 | L41: =IFERROR(SUMIFS('CALENDARIO INGRESOS'!$I:$I,'CALENDARIO INGRESOS'!$C:$C,Tabla814[[#Headers],[Argentina]],'CALENDARIO INGRESOS'!$G:$G,">="&$A41,'CALENDARIO INGRESOS'!$G:$G,"<="&EOMONTH($A41,0)),0) -> 2000 | M41: =IFERROR(SUMIFS('CALENDARIO INGRESOS'!$I:$I,'CALENDARIO INGRESOS'!$C:$C,Tabla814[[#Headers],[Guatemala]],'CALENDARIO INGRESOS'!$G:$G,">="&$A41,'CALENDARIO INGRESOS'!$G:$G,"<="&EOMONTH($A41,0)),0) -> 0 | N41: =IFERROR(SUMIFS('CALENDARIO INGRESOS'!$I:$I,'CALENDARIO INGRESOS'!$C:$C,Tabla814[[#Headers],[Venezuela]],'CALENDARIO INGRESOS'!$G:$G,">="&$A41,'CALENDARIO INGRESOS'!$G:$G,"<="&EOMONTH($A41,0)),0) -> 1000 | O41: =IFERROR(SUMIFS('CALENDARIO INGRESOS'!$I:$I,'CALENDARIO INGRESOS'!$C:$C,Tabla814[[#Headers],[Uruguay]],'CALENDARIO INGRESOS'!$G:$G,">="&$A41,'CALENDARIO INGRESOS'!$G:$G,"<="&EOMONTH($A41,0)),0) -> 0 | P41: =IFERROR(SUMIFS('CALENDARIO INGRESOS'!$I:$I,'CALENDARIO INGRESOS'!$C:$C,Tabla814[[#Headers],[Nicaragua]],'CALENDARIO INGRESOS'!$G:$G,">="&$A41,'CALENDARIO INGRESOS'!$G:$G,"<="&EOMONTH($A41,0)),0) -> 0 | Q41: =+SUM(Tabla814[[#This Row],[El Salvador]:[Nicaragua]]) -> 34658
A42: TOTAL | B42: =+SUM(B19:B41) -> 71909 | C42: =+SUM(C19:C41) -> 340344.54 | D42: =+SUM(D19:D41) -> 312218 | E42: =+SUM(E19:E41) -> 348930.15 | F42: =+SUM(F19:F41) -> 170150 | G42: =+SUM(G19:G41) -> 41425 | H42: =+SUM(H19:H41) -> 163103 | I42: =+SUM(I19:I41) -> 0 | ... P42: =+SUM(P19:P41) -> 0 | Q42: =+SUM(Tabla814[[#This Row],[El Salvador]:[Nicaragua]]) -> 1607499.7

Sheet UNIT ECONOMICS
A1: General | D1: Ingreso | F1: COR/Dr (Costo Directo) | J1: Adquisición | K1: OPEX/Dr (Prorrateado) | N1: Resumen/Dr
A2: Month | B2: Drs. Activos | C2: Drs. Nuevos | D2: Ingreso Neto (EUR) | E2: Ingreso/Dr (EUR) | F2: Idioma/Dr (EUR) | G2: Form. Médica/Dr (EUR) | H2: Legal-Otros/Dr (EUR) | I2: COR TOTAL/Dr (EUR) | J2: CAC/Dr Nuevo (EUR) | K2: G&A/Dr (EUR) | L2: CS/Dr (EUR) | M2: R&D/Dr (EUR) | N2: Costo Total/Dr (EUR) | O2: Margen Neto/Dr (EUR) | P2: Margen Contribucion/Dr (EUR)
A3: =EERR!A4 -> 45658 | B3: ='COHORTES INGRESO'!E4 -> 3 | C3: ='COHORTES INGRESO'!C4 -> 3 | D3: =EERR!Q4 -> 10953.596 | E3: =IFERROR(D3/B3,0) -> 3651.1988 | F3: {=IFERROR((SUMPRODUCT((YEAR(SALIDAS!$A$2:$A$1498)=YEAR(A3))*(MONTH(SALIDAS!$A$2:$A$1498)=MONTH(A3))*(SALIDAS!$G$2:$G$1498="Lingoda")*(SALIDAS!$U$2:$U$1498="COR")*SALIDAS!$F$2:$F$1498)+SUMPRODUCT((YEAR(SALIDAS!$A$2:$A$1498)=YEAR(A3))*(MONTH(SALIDAS!$A$2:$A$1498)=MONTH(A3))*(SALIDAS!$G$2:$G$1498="Lingoking")*(SALIDAS!$U$2:$U$1498="COR")*SALIDAS!$F$2:$F$1498)+SUMPRODUCT((YEAR(SALIDAS!$A$2:$A$1498)=YEAR(A3))*(MONTH(SALIDAS!$A$2:$A$1498)=MONTH(A3))*(ISNUMBER(SEARCH("Schwark",SALIDAS!$H$2:$H$1498)))*(SALIDAS!$U$2:$U$1498="COR")*SALIDAS!$F$2:$F$1498))/B3,0)} -> -166.66667 | G3: {=IFERROR(SUMPRODUCT((YEAR(SALIDAS!$A$2:$A$1498)=YEAR(A3))*(MONTH(SALIDAS!$A$2:$A$1498)=MONTH(A3))*(SALIDAS!$G$2:$G$1498="Lecturio")*(SALIDAS!$U$2:$U$1498="COR")*SALIDAS!$F$2:$F$1498)/B3,0)} -> 0 | H3: =I3-F3-G3 -> -142.8 | I3: =IFERROR(EERR!S4/B3,0) -> -309.46667 | J3: =IFERROR(EERR!V4/C3,0) -> -2741.4685 | K3: =IFERROR(EERR!X4/B3,0) -> -1906.0921 | L3: =IFERROR(EERR!Y4/B3,0) -> -515.66667 | M3: =IFERROR(EERR!W4/B3,0) -> -449.07333 | N3: =I3+K3+L3+M3 -> -3180.2987 | O3: =E3+N3 -> 470.90002 | P3: =+EERR!AG4/Table15[[#This Row],[Drs. Activos]] -> 3013.0754
A4: =EERR!A5 -> 45689 | B4: ='COHORTES INGRESO'!E5 -> 4 | C4: ='COHORTES INGRESO'!C5 -> 1 | D4: =EERR!Q5 -> 10194.846 | E4: =IFERROR(D4/B4,0) -> 2548.7114 | F4: {=IFERROR((SUMPRODUCT((YEAR(SALIDAS!$A$2:$A$1498)=YEAR(A4))*(MONTH(SALIDAS!$A$2:$A$1498)=MONTH(A4))*(SALIDAS!$G$2:$G$1498="Lingoda")*(SALIDAS!$U$2:$U$1498="COR")*SALIDAS!$F$2:$F$1498)+SUMPRODUCT((YEAR(SALIDAS!$A$2:$A$1498)=YEAR(A4))*(MONTH(SALIDAS!$A$2:$A$1498)=MONTH(A4))*(SALIDAS!$G$2:$G$1498="Lingoking")*(SALIDAS!$U$2:$U$1498="COR")*SALIDAS!$F$2:$F$1498)+SUMPRODUCT((YEAR(SALIDAS!$A$2:$A$1498)=YEAR(A4))*(MONTH(SALIDAS!$A$2:$A$1498)=MONTH(A4))*(ISNUMBER(SEARCH("Schwark",SALIDAS!$H$2:$H$1498)))*(SALIDAS!$U$2:$U$1498="COR")*SALIDAS!$F$2:$F$1498))/B4,0)} -> 0 | G4: {=IFERROR(SUMPRODUCT((YEAR(SALIDAS!$A$2:$A$1498)=YEAR(A4))*(MONTH(SALIDAS!$A$2:$A$1498)=MONTH(A4))*(SALIDAS!$G$2:$G$1498="Lecturio")*(SALIDAS!$U$2:$U$1498="COR")*SALIDAS!$F$2:$F$1498)/B4,0)} -> 0 | H4: =I4-F4-G4 -> 0 | I4: =IFERROR(EERR!S5/B4,0) -> 0 | J4: =IFERROR(EERR!V5/C4,0) -> -17413.583 | K4: =IFERROR(EERR!X5/B4,0) -> -1995.7603 | L4: =IFERROR(EERR!Y5/B4,0) -> -1696.0787 | M4: =IFERROR(EERR!W5/B4,0) -> -55.32 | N4: =I4+K4+L4+M4 -> -3747.1589 | O4: =E4+N4 -> -1198.4476 | P4: =+EERR!AG5/Table15[[#This Row],[Drs. Activos]] -> 1183.3164
A5: =EERR!A6 -> 45717 | B5: ='COHORTES INGRESO'!E6 -> 17 | C5: ='COHORTES INGRESO'!C6 -> 14 | D5: =EERR!Q6 -> 25071.169 | E5: =IFERROR(D5/B5,0) -> 1474.7746 | F5: {=IFERROR((SUMPRODUCT((YEAR(SALIDAS!$A$2:$A$1498)=YEAR(A5))*(MONTH(SALIDAS!$A$2:$A$1498)=MONTH(A5))*(SALIDAS!$G$2:$G$1498="Lingoda")*(SALIDAS!$U$2:$U$1498="COR")*SALIDAS!$F$2:$F$1498)+SUMPRODUCT((YEAR(SALIDAS!$A$2:$A$1498)=YEAR(A5))*(MONTH(SALIDAS!$A$2:$A$1498)=MONTH(A5))*(SALIDAS!$G$2:$G$1498="Lingoking")*(SALIDAS!$U$2:$U$1498="COR")*SALIDAS!$F$2:$F$1498)+SUMPRODUCT((YEAR(SALIDAS!$A$2:$A$1498)=YEAR(A5))*(MONTH(SALIDAS!$A$2:$A$1498)=MONTH(A5))*(ISNUMBER(SEARCH("Schwark",SALIDAS!$H$2:$H$1498)))*(SALIDAS!$U$2:$U$1498="COR")*SALIDAS!$F$2:$F$1498))/B5,0)} -> -352.94118 | G5: {=IFERROR(SUMPRODUCT((YEAR(SALIDAS!$A$2:$A$1498)=YEAR(A5))*(MONTH(SALIDAS!$A$2:$A$1498)=MONTH(A5))*(SALIDAS!$G$2:$G$1498="Lecturio")*(SALIDAS!$U$2:$U$1498="COR")*SALIDAS!$F$2:$F$1498)/B5,0)} -> -1103.6471 | H5: =I5-F5-G5 -> -7.0588235 | I5: =IFERROR(EERR!S6/B5,0) -> -1463.6471 | J5: =IFERROR(EERR!V6/C5,0) -> -1623.9067 | K5: =IFERROR(EERR!X6/B5,0) -> -216.93166 | L5: =IFERROR(EERR!Y6/B5,0) -> -217.90799 | M5: =IFERROR(EERR!W6/B5,0) -> -13.030588 | N5: =I5+K5+L5+M5 -> -1911.5173 | O5: =E5+N5 -> -436.74266 | P5: =+EERR!AG6/Table15[[#This Row],[Drs. Activos]] -> 88.712711
A6: =EERR!A7 -> 45748 | B6: ='COHORTES INGRESO'!E7 -> 34 | C6: ='COHORTES INGRESO'!C7 -> 19 | D6: =EERR!Q7 -> 59179.123 | E6: =IFERROR(D6/B6,0) -> 1740.5625 | F6: {=IFERROR((SUMPRODUCT((YEAR(SALIDAS!$A$2:$A$1498)=YEAR(A6))*(MONTH(SALIDAS!$A$2:$A$1498)=MONTH(A6))*(SALIDAS!$G$2:$G$1498="Lingoda")*(SALIDAS!$U$2:$U$1498="COR")*SALIDAS!$F$2:$F$1498)+SUMPRODUCT((YEAR(SALIDAS!$A$2:$A$1498)=YEAR(A6))*(MONTH(SALIDAS!$A$2:$A$1498)=MONTH(A6))*(SALIDAS!$G$2:$G$1498="Lingoking")*(SALIDAS!$U$2:$U$1498="COR")*SALIDAS!$F$2:$F$1498)+SUMPRODUCT((YEAR(SALIDAS!$A$2:$A$1498)=YEAR(A6))*(MONTH(SALIDAS!$A$2:$A$1498)=MONTH(A6))*(ISNUMBER(SEARCH("Schwark",SALIDAS!$H$2:$H$1498)))*(SALIDAS!$U$2:$U$1498="COR")*SALIDAS!$F$2:$F$1498))/B6,0)} -> -105.88235 | G6: {=IFERROR(SUMPRODUCT((YEAR(SALIDAS!$A$2:$A$1498)=YEAR(A6))*(MONTH(SALIDAS!$A$2:$A$1498)=MONTH(A6))*(SALIDAS!$G$2:$G$1498="Lecturio")*(SALIDAS!$U$2:$U$1498="COR")*SALIDAS!$F$2:$F$1498)/B6,0)} -> -205.88235 | H6: =I6-F6-G6 -> -6.6988235 | I6: =IFERROR(EERR!S7/B6,0) -> -318.46353 | J6: =IFERROR(EERR!V7/C6,0) -> -1240.1479 | K6: =IFERROR(EERR!X7/B6,0) -> -246.92995 | L6: =IFERROR(EERR!Y7/B6,0) -> -120.4495 | M6: =IFERROR(EERR!W7/B6,0) -> -5.2947647 | N6: =I6+K6+L6+M6 -> -691.13774 | O6: =E6+N6 -> 1049.4247 | P6: =+EERR!AG7/Table15[[#This Row],[Drs. Activos]] -> 1203.7497
A7: =EERR!A8 -> 45778 | B7: ='COHORTES INGRESO'!E8 -> 48 | C7: ='COHORTES INGRESO'!C8 -> 15 | D7: =EERR!Q8 -> 57208.64 | E7: =IFERROR(D7/B7,0) -> 1191.8467 | F7: {=IFERROR((SUMPRODUCT((YEAR(SALIDAS!$A$2:$A$1498)=YEAR(A7))*(MONTH(SALIDAS!$A$2:$A$1498)=MONTH(A7))*(SALIDAS!$G$2:$G$1498="Lingoda")*(SALIDAS!$U$2:$U$1498="COR")*SALIDAS!$F$2:$F$1498)+SUMPRODUCT((YEAR(SALIDAS!$A$2:$A$1498)=YEAR(A7))*(MONTH(SALIDAS!$A$2:$A$1498)=MONTH(A7))*(SALIDAS!$G$2:$G$1498="Lingoking")*(SALIDAS!$U$2:$U$1498="COR")*SALIDAS!$F$2:$F$1498)+SUMPRODUCT((YEAR(SALIDAS!$A$2:$A$1498)=YEAR(A7))*(MONTH(SALIDAS!$A$2:$A$1498)=MONTH(A7))*(ISNUMBER(SEARCH("Schwark",SALIDAS!$H$2:$H$1498)))*(SALIDAS!$U$2:$U$1498="COR")*SALIDAS!$F$2:$F$1498))/B7,0)} -> -37.5 | G7: {=IFERROR(SUMPRODUCT((YEAR(SALIDAS!$A$2:$A$1498)=YEAR(A7))*(MONTH(SALIDAS!$A$2:$A$1498)=MONTH(A7))*(SALIDAS!$G$2:$G$1498="Lecturio")*(SALIDAS!$U$2:$U$1498="COR")*SALIDAS!$F$2:$F$1498)/B7,0)} -> -225.63542 | H7: =I7-F7-G7 -> -8.8995833 | I7: =IFERROR(EERR!S8/B7,0) -> -272.035 | J7: =IFERROR(EERR!V8/C7,0) -> -1695.221 | K7: =IFERROR(EERR!X8/B7,0) -> -209.64094 | L7: =IFERROR(EERR!Y8/B7,0) -> -101.79593 | M7: =IFERROR(EERR!W8/B7,0) -> -9.2022917 | N7: =I7+K7+L7+M7 -> -592.67416 | O7: =E7+N7 -> 599.1725 | P7: =+EERR!AG8/Table15[[#This Row],[Drs. Activos]] -> 807.43322
A8: =EERR!A9 -> 45809 | B8: ='COHORTES INGRESO'!E9 -> 63 | C8: ='COHORTES INGRESO'!C9 -> 19 | D8: =EERR!Q9 -> 80492.024 | E8: =IFERROR(D8/B8,0) -> 1277.6512 | F8: {=IFERROR((SUMPRODUCT((YEAR(SALIDAS!$A$2:$A$1498)=YEAR(A8))*(MONTH(SALIDAS!$A$2:$A$1498)=MONTH(A8))*(SALIDAS!$G$2:$G$1498="Lingoda")*(SALIDAS!$U$2:$U$1498="COR")*SALIDAS!$F$2:$F$1498)+SUMPRODUCT((YEAR(SALIDAS!$A$2:$A$1498)=YEAR(A8))*(MONTH(SALIDAS!$A$2:$A$1498)=MONTH(A8))*(SALIDAS!$G$2:$G$1498="Lingoking")*(SALIDAS!$U$2:$U$1498="COR")*SALIDAS!$F$2:$F$1498)+SUMPRODUCT((YEAR(SALIDAS!$A$2:$A$1498)=YEAR(A8))*(MONTH(SALIDAS!$A$2:$A$1498)=MONTH(A8))*(ISNUMBER(SEARCH("Schwark",SALIDAS!$H$2:$H$1498)))*(SALIDAS!$U$2:$U$1498="COR")*SALIDAS!$F$2:$F$1498))/B8,0)} -> -161.90476 | G8: {=IFERROR(SUMPRODUCT((YEAR(SALIDAS!$A$2:$A$1498)=YEAR(A8))*(MONTH(SALIDAS!$A$2:$A$1498)=MONTH(A8))*(SALIDAS!$G$2:$G$1498="Lecturio")*(SALIDAS!$U$2:$U$1498="COR")*SALIDAS!$F$2:$F$1498)/B8,0)} -> 0 | H8: =I8-F8-G8 -> -6.7952381 | I8: =IFERROR(EERR!S9/B8,0) -> -168.7 | J8: =IFERROR(EERR!V9/C8,0) -> -1385.653 | K8: =IFERROR(EERR!X9/B8,0) -> -374.54114 | L8: =IFERROR(EERR!Y9/B8,0) -> -142.72247 | M8: =IFERROR(EERR!W9/B8,0) -> -10.988814 | N8: =I8+K8+L8+M8 -> -696.95243 | O8: =E8+N8 -> 580.69874 | P8: =+EERR!AG9/Table15[[#This Row],[Drs. Activos]] -> 866.23901
A9: =EERR!A10 -> 45839 | B9: ='COHORTES INGRESO'!E10 -> 84 | C9: ='COHORTES INGRESO'!C10 -> 31 | D9: =EERR!Q10 -> 137497.24 | E9: =IFERROR(D9/B9,0) -> 1636.8719 | F9: {=IFERROR((SUMPRODUCT((YEAR(SALIDAS!$A$2:$A$1498)=YEAR(A9))*(MONTH(SALIDAS!$A$2:$A$1498)=MONTH(A9))*(SALIDAS!$G$2:$G$1498="Lingoda")*(SALIDAS!$U$2:$U$1498="COR")*SALIDAS!$F$2:$F$1498)+SUMPRODUCT((YEAR(SALIDAS!$A$2:$A$1498)=YEAR(A9))*(MONTH(SALIDAS!$A$2:$A$1498)=MONTH(A9))*(SALIDAS!$G$2:$G$1498="Lingoking")*(SALIDAS!$U$2:$U$1498="COR")*SALIDAS!$F$2:$F$1498)+SUMPRODUCT((YEAR(SALIDAS!$A$2:$A$1498)=YEAR(A9))*(MONTH(SALIDAS!$A$2:$A$1498)=MONTH(A9))*(ISNUMBER(SEARCH("Schwark",SALIDAS!$H$2:$H$1498)))*(SALIDAS!$U$2:$U$1498="COR")*SALIDAS!$F$2:$F$1498))/B9,0)} -> -234.89524 | G9: {=IFERROR(SUMPRODUCT((YEAR(SALIDAS!$A$2:$A$1498)=YEAR(A9))*(MONTH(SALIDAS!$A$2:$A$1498)=MONTH(A9))*(SALIDAS!$G$2:$G$1498="Lecturio")*(SALIDAS!$U$2:$U$1498="COR")*SALIDAS!$F$2:$F$1498)/B9,0)} -> 0 | H9: =I9-F9-G9 -> -5.6122619 | I9: =IFERROR(EERR!S10/B9,0) -> -240.5075 | J9: =IFERROR(EERR!V10/C9,0) -> -840.99707 | K9: =IFERROR(EERR!X10/B9,0) -> -254.81291 | L9: =IFERROR(EERR!Y10/B9,0) -> -168.67675 | M9: =IFERROR(EERR!W10/B9,0) -> -9.2922053 | N9: =I9+K9+L9+M9 -> -673.28936 | O9: =E9+N9 -> 963.58255 | P9: =+EERR!AG10/Table15[[#This Row],[Drs. Activos]] -> 1208.8649
A10: =EERR!A11 -> 45870 | B10: ='COHORTES INGRESO'!E11 -> 101 | C10: ='COHORTES INGRESO'!C11 -> 26 | D10: =EERR!Q11 -> 140640.2 | E10: =IFERROR(D10/B10,0) -> 1392.4772 | F10: {=IFERROR((SUMPRODUCT((YEAR(SALIDAS!$A$2:$A$1498)=YEAR(A10))*(MONTH(SALIDAS!$A$2:$A$1498)=MONTH(A10))*(SALIDAS!$G$2:$G$1498="Lingoda")*(SALIDAS!$U$2:$U$1498="COR")*SALIDAS!$F$2:$F$1498)+SUMPRODUCT((YEAR(SALIDAS!$A$2:$A$1498)=YEAR(A10))*(MONTH(SALIDAS!$A$2:$A$1498)=MONTH(A10))*(SALIDAS!$G$2:$G$1498="Lingoking")*(SALIDAS!$U$2:$U$1498="COR")*SALIDAS!$F$2:$F$1498)+SUMPRODUCT((YEAR(SALIDAS!$A$2:$A$1498)=YEAR(A10))*(MONTH(SALIDAS!$A$2:$A$1498)=MONTH(A10))*(ISNUMBER(SEARCH("Schwark",SALIDAS!$H$2:$H$1498)))*(SALIDAS!$U$2:$U$1498="COR")*SALIDAS!$F$2:$F$1498))/B10,0)} -> -146.89584 | G10: {=IFERROR(SUMPRODUCT((YEAR(SALIDAS!$A$2:$A$1498)=YEAR(A10))*(MONTH(SALIDAS!$A$2:$A$1498)=MONTH(A10))*(SALIDAS!$G$2:$G$1498="Lecturio")*(SALIDAS!$U$2:$U$1498="COR")*SALIDAS!$F$2:$F$1498)/B10,0)} -> 0 | H10: =I10-F10-G10 -> -24.477353 | I10: =IFERROR(EERR!S11/B10,0) -> -171.37319 | J10: =IFERROR(EERR!V11/C10,0) -> -1512.392 | K10: =IFERROR(EERR!X11/B10,0) -> -526.2414 | L10: =IFERROR(EERR!Y11/B10,0) -> -135.54527 | M10: =IFERROR(EERR!W11/B10,0) -> -8.8755314 | N10: =I10+K10+L10+M10 -> -842.03539 | O10: =E10+N10 -> 550.44182 | P10: =+EERR!AG11/Table15[[#This Row],[Drs. Activos]] -> 982.63645
A11: =EERR!A12 -> 45901 | B11: ='COHORTES INGRESO'!E12 -> 111 | C11: ='COHORTES INGRESO'!C12 -> 14 | D11: =EERR!Q12 -> 123609.3 | E11: =IFERROR(D11/B11,0) -> 1113.5973 | F11: {=IFERROR((SUMPRODUCT((YEAR(SALIDAS!$A$2:$A$1498)=YEAR(A11))*(MONTH(SALIDAS!$A$2:$A$1498)=MONTH(A11))*(SALIDAS!$G$2:$G$1498="Lingoda")*(SALIDAS!$U$2:$U$1498="COR")*SALIDAS!$F$2:$F$1498)+SUMPRODUCT((YEAR(SALIDAS!$A$2:$A$1498)=YEAR(A11))*(MONTH(SALIDAS!$A$2:$A$1498)=MONTH(A11))*(SALIDAS!$G$2:$G$1498="Lingoking")*(SALIDAS!$U$2:$U$1498="COR")*SALIDAS!$F$2:$F$1498)+SUMPRODUCT((YEAR(SALIDAS!$A$2:$A$1498)=YEAR(A11))*(MONTH(SALIDAS!$A$2:$A$1498)=MONTH(A11))*(ISNUMBER(SEARCH("Schwark",SALIDAS!$H$2:$H$1498)))*(SALIDAS!$U$2:$U$1498="COR")*SALIDAS!$F$2:$F$1498))/B11,0)} -> -188.02326 | G11: {=IFERROR(SUMPRODUCT((YEAR(SALIDAS!$A$2:$A$1498)=YEAR(A11))*(MONTH(SALIDAS!$A$2:$A$1498)=MONTH(A11))*(SALIDAS!$G$2:$G$1498="Lecturio")*(SALIDAS!$U$2:$U$1498="COR")*SALIDAS!$F$2:$F$1498)/B11,0)} -> 0 | H11: =I11-F11-G11 -> -41.302706 | I11: =IFERROR(EERR!S12/B11,0) -> -229.32597 | J11: =IFERROR(EERR!V12/C11,0) -> -2162.4026 | K11: =IFERROR(EERR!X12/B11,0) -> -412.0325 | L11: =IFERROR(EERR!Y12/B11,0) -> -172.89128 | M11: =IFERROR(EERR!W12/B11,0) -> -6.9970331 | N11: =I11+K11+L11+M11 -> -821.24678 | O11: =E11+N11 -> 292.35056 | P11: =+EERR!AG12/Table15[[#This Row],[Drs. Activos]] -> 852.54961
A12: =EERR!A13 -> 45931 | B12: ='COHORTES INGRESO'!E13 -> 113 | C12: ='COHORTES INGRESO'!C13 -> 11 | D12: =EERR!Q13 -> 115336.26 | E12: =IFERROR(D12/B12,0) -> 1020.6748 | F12: {=IFERROR((SUMPRODUCT((YEAR(SALIDAS!$A$2:$A$1498)=YEAR(A12))*(MONTH(SALIDAS!$A$2:$A$1498)=MONTH(A12))*(SALIDAS!$G$2:$G$1498="Lingoda")*(SALIDAS!$U$2:$U$1498="COR")*SALIDAS!$F$2:$F$1498)+SUMPRODUCT((YEAR(SALIDAS!$A$2:$A$1498)=YEAR(A12))*(MONTH(SALIDAS!$A$2:$A$1498)=MONTH(A12))*(SALIDAS!$G$2:$G$1498="Lingoking")*(SALIDAS!$U$2:$U$1498="COR")*SALIDAS!$F$2:$F$1498)+SUMPRODUCT((YEAR(SALIDAS!$A$2:$A$1498)=YEAR(A12))*(MONTH(SALIDAS!$A$2:$A$1498)=MONTH(A12))*(ISNUMBER(SEARCH("Schwark",SALIDAS!$H$2:$H$1498)))*(SALIDAS!$U$2:$U$1498="COR")*SALIDAS!$F$2:$F$1498))/B12,0)} -> -66.563761 | G12: {=IFERROR(SUMPRODUCT((YEAR(SALIDAS!$A$2:$A$1498)=YEAR(A12))*(MONTH(SALIDAS!$A$2:$A$1498)=MONTH(A12))*(SALIDAS!$G$2:$G$1498="Lecturio")*(SALIDAS!$U$2:$U$1498="COR")*SALIDAS!$F$2:$F$1498)/B12,0)} -> 0 | H12: =I12-F12-G12 -> -21.361571 | I12: =IFERROR(EERR!S13/B12,0) -> -87.925332 | J12: =IFERROR(EERR!V13/C12,0) -> -3389.335 | K12: =IFERROR(EERR!X13/B12,0) -> -448.34299 | L12: =IFERROR(EERR!Y13/B12,0) -> -165.61553 | M12: =IFERROR(EERR!W13/B12,0) -> -7.811707 | N12: =I12+K12+L12+M12 -> -709.69556 | O12: =E12+N12 -> 310.97928 | P12: =+EERR!AG13/Table15[[#This Row],[Drs. Activos]] -> 757.61351
A13: =EERR!A14 -> 45962 | B13: ='COHORTES INGRESO'!E14 -> 119 | C13: ='COHORTES INGRESO'!C14 -> 13 | D13: =EERR!Q14 -> 130999.57 | E13: =IFERROR(D13/B13,0) -> 1100.8367 | F13: {=IFERROR((SUMPRODUCT((YEAR(SALIDAS!$A$2:$A$1498)=YEAR(A13))*(MONTH(SALIDAS!$A$2:$A$1498)=MONTH(A13))*(SALIDAS!$G$2:$G$1498="Lingoda")*(SALIDAS!$U$2:$U$1498="COR")*SALIDAS!$F$2:$F$1498)+SUMPRODUCT((YEAR(SALIDAS!$A$2:$A$1498)=YEAR(A13))*(MONTH(SALIDAS!$A$2:$A$1498)=MONTH(A13))*(SALIDAS!$G$2:$G$1498="Lingoking")*(SALIDAS!$U$2:$U$1498="COR")*SALIDAS!$F$2:$F$1498)+SUMPRODUCT((YEAR(SALIDAS!$A$2:$A$1498)=YEAR(A13))*(MONTH(SALIDAS!$A$2:$A$1498)=MONTH(A13))*(ISNUMBER(SEARCH("Schwark",SALIDAS!$H$2:$H$1498)))*(SALIDAS!$U$2:$U$1498="COR")*SALIDAS!$F$2:$F$1498))/B13,0)} -> -212.04431 | G13: {=IFERROR(SUMPRODUCT((YEAR(SALIDAS!$A$2:$A$1498)=YEAR(A13))*(MONTH(SALIDAS!$A$2:$A$1498)=MONTH(A13))*(SALIDAS!$G$2:$G$1498="Lecturio")*(SALIDAS!$U$2:$U$1498="COR")*SALIDAS!$F$2:$F$1498)/B13,0)} -> 0 | H13: =I13-F13-G13 -> -5.1602524 | I13: =IFERROR(EERR!S14/B13,0) -> -217.20456 | J13: =IFERROR(EERR!V14/C13,0) -> -3378.8996 | K13: =IFERROR(EERR!X14/B13,0) -> -422.96282 | L13: =IFERROR(EERR!Y14/B13,0) -> -143.13117 | M13: =IFERROR(EERR!W14/B13,0) -> -5.6373955 | N13: =I13+K13+L13+M13 -> -788.93595 | O13: =E13+N13 -> 311.90075 | P13: =+EERR!AG14/Table15[[#This Row],[Drs. Activos]] -> 701.65302
A14: =EERR!A15 -> 45992 | B14: ='COHORTES INGRESO'!E15 -> 126 | C14: ='COHORTES INGRESO'!C15 -> 10 | D14: =EERR!Q15 -> 118222.47 | E14: =IFERROR(D14/B14,0) -> 938.27358 | F14: {=IFERROR((SUMPRODUCT((YEAR(SALIDAS!$A$2:$A$1498)=YEAR(A14))*(MONTH(SALIDAS!$A$2:$A$1498)=MONTH(A14))*(SALIDAS!$G$2:$G$1498="Lingoda")*(SALIDAS!$U$2:$U$1498="COR")*SALIDAS!$F$2:$F$1498)+SUMPRODUCT((YEAR(SALIDAS!$A$2:$A$1498)=YEAR(A14))*(MONTH(SALIDAS!$A$2:$A$1498)=MONTH(A14))*(SALIDAS!$G$2:$G$1498="Lingoking")*(SALIDAS!$U$2:$U$1498="COR")*SALIDAS!$F$2:$F$1498)+SUMPRODUCT((YEAR(SALIDAS!$A$2:$A$1498)=YEAR(A14))*(MONTH(SALIDAS!$A$2:$A$1498)=MONTH(A14))*(ISNUMBER(SEARCH("Schwark",SALIDAS!$H$2:$H$1498)))*(SALIDAS!$U$2:$U$1498="COR")*SALIDAS!$F$2:$F$1498))/B14,0)} -> -168.37083 | G14: {=IFERROR(SUMPRODUCT((YEAR(SALIDAS!$A$2:$A$1498)=YEAR(A14))*(MONTH(SALIDAS!$A$2:$A$1498)=MONTH(A14))*(SALIDAS!$G$2:$G$1498="Lecturio")*(SALIDAS!$U$2:$U$1498="COR")*SALIDAS!$F$2:$F$1498)/B14,0)} -> 0 | H14: =I14-F14-G14 -> -34.699551 | I14: =IFERROR(EERR!S15/B14,0) -> -203.07038 | J14: =IFERROR(EERR!V15/C14,0) -> -4334.9473 | K14: =IFERROR(EERR!X15/B14,0) -> -365.04485 | L14: =IFERROR(EERR!Y15/B14,0) -> -172.7548 | M14: =IFERROR(EERR!W15/B14,0) -> -7.5199427 | N14: =I14+K14+L14+M14 -> -748.38997 | O14: =E14+N14 -> 189.88361 | P14: =+EERR!AG15/Table15[[#This Row],[Drs. Activos]] -> 600.97195
... A16: =EERR!A17 -> 46054 | B16: ='COHORTES INGRESO'!E17 -> 145 | C16: ='COHORTES INGRESO'!C17 -> 5 | D16: =EERR!Q17 -> 111993.37 | E16: =IFERROR(D16/B16,0) -> 772.36807 | F16: {=IFERROR((SUMPRODUCT((YEAR(SALIDAS!$A$2:$A$1498)=YEAR(A16))*(MONTH(SALIDAS!$A$2:$A$1498)=MONTH(A16))*(SALIDAS!$G$2:$G$1498="Lingoda")*(SALIDAS!$U$2:$U$1498="COR")*SALIDAS!$F$2:$F$1498)+SUMPRODUCT((YEAR(SALIDAS!$A$2:$A$1498)=YEAR(A16))*(MONTH(SALIDAS!$A$2:$A$1498)=MONTH(A16))*(SALIDAS!$G$2:$G$1498="Lingoking")*(SALIDAS!$U$2:$U$1498="COR")*SALIDAS!$F$2:$F$1498)+SUMPRODUCT((YEAR(SALIDAS!$A$2:$A$1498)=YEAR(A16))*(MONTH(SALIDAS!$A$2:$A$1498)=MONTH(A16))*(ISNUMBER(SEARCH("Schwark",SALIDAS!$H$2:$H$1498)))*(SALIDAS!$U$2:$U$1498="COR")*SALIDAS!$F$2:$F$1498))/B16,0)} -> -36.567645 | G16: {=IFERROR(SUMPRODUCT((YEAR(SALIDAS!$A$2:$A$1498)=YEAR(A16))*(MONTH(SALIDAS!$A$2:$A$1498)=MONTH(A16))*(SALIDAS!$G$2:$G$1498="Lecturio")*(SALIDAS!$U$2:$U$1498="COR")*SALIDAS!$F$2:$F$1498)/B16,0)} -> 0 | H16: =I16-F16-G16 -> -3.5492834 | I16: =IFERROR(EERR!S17/B16,0) -> -40.116928 | J16: =IFERROR(EERR!V17/C16,0) -> -10617.403 | K16: =IFERROR(EERR!X17/B16,0) -> -323.28687 | L16: =IFERROR(EERR!Y17/B16,0) -> -83.167172 | M16: =IFERROR(EERR!W17/B16,0) -> -6.2216682 | N16: =I16+K16+L16+M16 -> -452.79264 | O16: =E16+N16 -> 319.57543 | P16: =+EERR!AG17/Table15[[#This Row],[Drs. Activos]] -> 585.00556
A17: Promedio | B17: =AVERAGE(B3:B16) -> 79.142857 | C17: =AVERAGE(C3:C16) -> 14 | D17: =AVERAGE(D3:D16) -> 89833.494 | E17: =AVERAGE(E3:E16) -> 1488.0864 | F17: =AVERAGE(F3:F16) -> -138.98339 | G17: =AVERAGE(G3:G16) -> -109.65463 | H17: =AVERAGE(H3:H16) -> -24.847601 | I17: =AVERAGE(I3:I16) -> -273.48562 | ... P17: =AVERAGE(P3:P16) -> 970.39753

Sheet KPIs
A1: SEGUIMIENTO SEMANAL DE KPIs - ENERO 2026
A3: 1. CAJA Y COBRANZA | B3: Responsable: Sebastián Arellano
A4: KPI | B4: META | C4: SEM 1 | D4: SEM 2 | E4: SEM 3 | F4: SEM 4 | G4: ACUMULADO | H4: % AVANCE | I4: ESTADO
A5: Ratio Cobranza | B5: ≥90% | C5: =SUMIFS('CALENDARIO INGRESOS'!$I:$I,'CALENDARIO INGRESOS'!$L:$L,"PAGADA",'CALENDARIO INGRESOS'!$G:$G,">="&DATE(2026,1,1),'CALENDARIO INGRESOS'!$G:$G,"<="&DATE(2026,1,7))/SUMIFS('CALENDARIO INGRESOS'!$I:$I,'CALENDARIO INGRESOS'!$G:$G,">="&DATE(2026,1,1),'CALENDARIO INGRESOS'!$G:$G,"<="&DATE(2026,1,7)) -> 1 | D5: =SUMIFS('CALENDARIO INGRESOS'!$I:$I,'CALENDARIO INGRESOS'!$L:$L,"PAGADA",'CALENDARIO INGRESOS'!$G:$G,">="&DATE(2026,1,8),'CALENDARIO INGRESOS'!$G:$G,"<="&DATE(2026,1,14))/SUMIFS('CALENDARIO INGRESOS'!$I:$I,'CALENDARIO INGRESOS'!$G:$G,">="&DATE(2026,1,8),'CALENDARIO INGRESOS'!$G:$G,"<="&DATE(2026,1,14)) -> 1 | E5: =SUMIFS('CALENDARIO INGRESOS'!$I:$I,'CALENDARIO INGRESOS'!$L:$L,"PAGADA",'CALENDARIO INGRESOS'!$G:$G,">="&DATE(2026,1,15),'CALENDARIO INGRESOS'!$G:$G,"<="&DATE(2026,1,21))/SUMIFS('CALENDARIO INGRESOS'!$I:$I,'CALENDARIO INGRESOS'!$G:$G,">="&DATE(2026,1,15),'CALENDARIO INGRESOS'!$G:$G,"<="&DATE(2026,1,21)) -> 1 | F5: =SUMIFS('CALENDARIO INGRESOS'!$I:$I,'CALENDARIO INGRESOS'!$L:$L,"PAGADA",'CALENDARIO INGRESOS'!$G:$G,">="&DATE(2026,1,22),'CALENDARIO INGRESOS'!$G:$G,"<="&DATE(2026,1,31))/SUMIFS('CALENDARIO INGRESOS'!$I:$I,'CALENDARIO INGRESOS'!$G:$G,">="&DATE(2026,1,22),'CALENDARIO INGRESOS'!$G:$G,"<="&DATE(2026,1,31)) -> 0.96023136 | G5: =SUMIFS('CALENDARIO INGRESOS'!$I:$I,'CALENDARIO INGRESOS'!$L:$L,"PAGADA",'CALENDARIO INGRESOS'!$G:$G,">="&DATE(2026,1,1),'CALENDARIO INGRESOS'!$G:$G,"<="&DATE(2026,1,31))/SUMIFS('CALENDARIO INGRESOS'!$I:$I,'CALENDARIO INGRESOS'!$G:$G,">="&DATE(2026,1,1),'CALENDARIO INGRESOS'!$G:$G,"<="&DATE(2026,1,31)) -> 0.98148588 | H5: - | I5: =IF(G5>=0.9,"✓","✗") -> ✓
A6: Cash-In (€) | B6: ≥€120,000 | C6: =SUMIFS(INGRESOS!$G:$G,INGRESOS!$A:$A,">="&DATE(2026,1,1),INGRESOS!$A:$A,"<="&DATE(2026,1,7)) -> 35170.377 | D6: =SUMIFS(INGRESOS!$G:$G,INGRESOS!$A:$A,">="&DATE(2026,1,8),INGRESOS!$A:$A,"<="&DATE(2026,1,14)) -> 29375.225 | E6: =SUMIFS(INGRESOS!$G:$G,INGRESOS!$A:$A,">="&DATE(2026,1,15),INGRESOS!$A:$A,"<="&DATE(2026,1,21)) -> 14804 | F6: =SUMIFS(INGRESOS!$G:$G,INGRESOS!$A:$A,">="&DATE(2026,1,22),INGRESOS!$A:$A,"<="&DATE(2026,1,31)) -> 61522.375 | G6: =SUMIFS(INGRESOS!$G:$G,INGRESOS!$A:$A,">="&DATE(2026,1,1),INGRESOS!$A:$A,"<="&DATE(2026,1,31)) -> 140871.98 | H6: =G6/120000 -> 1.1739331 | I6: =IF(G6>=120000,"✓","✗") -> ✓
A7: Facturas On-Time | B7: ≥95% | C7: =COUNTIFS('CALENDARIO INGRESOS'!$L:$L,"PAGADA",'CALENDARIO INGRESOS'!$M:$M,"<=0",'CALENDARIO INGRESOS'!$G:$G,">="&DATE(2026,1,1),'CALENDARIO INGRESOS'!$G:$G,"<="&DATE(2026,1,7))/COUNTIFS('CALENDARIO INGRESOS'!$L:$L,"PAGADA",'CALENDARIO INGRESOS'!$G:$G,">="&DATE(2026,1,1),'CALENDARIO INGRESOS'!$G:$G,"<="&DATE(2026,1,7)) -> 0.72972973 | D7: =COUNTIFS('CALENDARIO INGRESOS'!$L:$L,"PAGADA",'CALENDARIO INGRESOS'!$M:$M,"<=0",'CALENDARIO INGRESOS'!$G:$G,">="&DATE(2026,1,8),'CALENDARIO INGRESOS'!$G:$G,"<="&DATE(2026,1,14))/COUNTIFS('CALENDARIO INGRESOS'!$L:$L,"PAGADA",'CALENDARIO INGRESOS'!$G:$G,">="&DATE(2026,1,8),'CALENDARIO INGRESOS'!$G:$G,"<="&DATE(2026,1,14)) -> 0.78571429 | E7: =COUNTIFS('CALENDARIO INGRESOS'!$L:$L,"PAGADA",'CALENDARIO INGRESOS'!$M:$M,"<=0",'CALENDARIO INGRESOS'!$G:$G,">="&DATE(2026,1,15),'CALENDARIO INGRESOS'!$G:$G,"<="&DATE(2026,1,21))/COUNTIFS('CALENDARIO INGRESOS'!$L:$L,"PAGADA",'CALENDARIO INGRESOS'!$G:$G,">="&DATE(2026,1,15),'CALENDARIO INGRESOS'!$G:$G,"<="&DATE(2026,1,21)) -> 0.63636364 | F7: =COUNTIFS('CALENDARIO INGRESOS'!$L:$L,"PAGADA",'CALENDARIO INGRESOS'!$M:$M,"<=0",'CALENDARIO INGRESOS'!$G:$G,">="&DATE(2026,1,22),'CALENDARIO INGRESOS'!$G:$G,"<="&DATE(2026,1,31))/COUNTIFS('CALENDARIO INGRESOS'!$L:$L,"PAGADA",'CALENDARIO INGRESOS'!$G:$G,">="&DATE(2026,1,22),'CALENDARIO INGRESOS'!$G:$G,"<="&DATE(2026,1,31)) -> 0.58 | G7: =COUNTIFS('CALENDARIO INGRESOS'!$L:$L,"PAGADA",'CALENDARIO INGRESOS'!$M:$M,"<=0",'CALENDARIO INGRESOS'!$G:$G,">="&DATE(2026,1,1),'CALENDARIO INGRESOS'!$G:$G,"<="&DATE(2026,1,31))/COUNTIFS('CALENDARIO INGRESOS'!$L:$L,"PAGADA",'CALENDARIO INGRESOS'!$G:$G,">="&DATE(2026,1,1),'CALENDARIO INGRESOS'!$G:$G,"<="&DATE(2026,1,31)) -> 0.65853659 | H7: =G7/0.95 -> 0.69319641 | I7: =IF(G7>=0.95,"✓","✗") -> ✗
A8: Dias de retraso promedio | B8: ≤2/mes | C8: =SUMIFS('CALENDARIO INGRESOS'!M:M,'CALENDARIO INGRESOS'!M:M,"<0",'CALENDARIO INGRESOS'!G:G,">="&DATE(2026,1,1),'CALENDARIO INGRESOS'!G:G,"<="&DATE(2026,1,7))/COUNTIFS('CALENDARIO INGRESOS'!M:M,"<0",'CALENDARIO INGRESOS'!G:G,">="&DATE(2026,1,1),'CALENDARIO INGRESOS'!G:G,"<="&DATE(2026,1,7)) -> -1.5454545 | D8: =SUMIFS('CALENDARIO INGRESOS'!M:M,'CALENDARIO INGRESOS'!M:M,"<0",'CALENDARIO INGRESOS'!G:G,">="&DATE(2026,1,8),'CALENDARIO INGRESOS'!G:G,"<="&DATE(2026,1,14))/COUNTIFS('CALENDARIO INGRESOS'!M:M,"<0",'CALENDARIO INGRESOS'!G:G,">="&DATE(2026,1,8),'CALENDARIO INGRESOS'!G:G,"<="&DATE(2026,1,14)) -> -6.6 | E8: =SUMIFS('CALENDARIO INGRESOS'!M:M,'CALENDARIO INGRESOS'!M:M,"<0",'CALENDARIO INGRESOS'!G:G,">="&DATE(2026,1,15),'CALENDARIO INGRESOS'!G:G,"<="&DATE(2026,1,21))/COUNTIFS('CALENDARIO INGRESOS'!M:M,"<0",'CALENDARIO INGRESOS'!G:G,">="&DATE(2026,1,15),'CALENDARIO INGRESOS'!G:G,"<="&DATE(2026,1,21)) -> -2.8333333 | F8: =SUMIFS('CALENDARIO INGRESOS'!M:M,'CALENDARIO INGRESOS'!M:M,"<0",'CALENDARIO INGRESOS'!G:G,">="&DATE(2026,1,22),'CALENDARIO INGRESOS'!G:G,"<="&DATE(2026,1,31))/COUNTIFS('CALENDARIO INGRESOS'!M:M,"<0",'CALENDARIO INGRESOS'!G:G,">="&DATE(2026,1,22),'CALENDARIO INGRESOS'!G:G,"<="&DATE(2026,1,31)) -> -2.0714286 | G8: =SUMIFS('CALENDARIO INGRESOS'!M:M,'CALENDARIO INGRESOS'!M:M,"<0",'CALENDARIO INGRESOS'!G:G,">="&DATE(2026,1,1),'CALENDARIO INGRESOS'!G:G,"<="&DATE(2026,1,31))/COUNTIFS('CALENDARIO INGRESOS'!M:M,"<0",'CALENDARIO INGRESOS'!G:G,">="&DATE(2026,1,1),'CALENDARIO INGRESOS'!G:G,"<="&DATE(2026,1,31)) -> -2.6666667 | I8: =IF(G8>=-2,"✓","✗") -> ✗
A9: AR > 15 días | B9: ≤15% | C9: =COUNTIFS('CALENDARIO INGRESOS'!$M:$M,">15",'CALENDARIO INGRESOS'!$G:$G,">="&DATE(2026,1,1),'CALENDARIO INGRESOS'!$G:$G,"<="&DATE(2026,1,7))/COUNTIFS('CALENDARIO INGRESOS'!$G:$G,">="&DATE(2026,1,1),'CALENDARIO INGRESOS'!$G:$G,"<="&DATE(2026,1,7)) -> 0.027027027 | D9: =COUNTIFS('CALENDARIO INGRESOS'!$M:$M,">15",'CALENDARIO INGRESOS'!$G:$G,">="&DATE(2026,1,8),'CALENDARIO INGRESOS'!$G:$G,"<="&DATE(2026,1,14))/COUNTIFS('CALENDARIO INGRESOS'!$G:$G,">="&DATE(2026,1,8),'CALENDARIO INGRESOS'!$G:$G,"<="&DATE(2026,1,14)) -> 0 | E9: =COUNTIFS('CALENDARIO INGRESOS'!$M:$M,">15",'CALENDARIO INGRESOS'!$G:$G,">="&DATE(2026,1,15),'CALENDARIO INGRESOS'!$G:$G,"<="&DATE(2026,1,21))/COUNTIFS('CALENDARIO INGRESOS'!$G:$G,">="&DATE(2026,1,15),'CALENDARIO INGRESOS'!$G:$G,"<="&DATE(2026,1,21)) -> 0.045454545 | F9: =COUNTIFS('CALENDARIO INGRESOS'!$M:$M,">15",'CALENDARIO INGRESOS'!$G:$G,">="&DATE(2026,1,22),'CALENDARIO INGRESOS'!$G:$G,"<="&DATE(2026,1,31))/COUNTIFS('CALENDARIO INGRESOS'!$G:$G,">="&DATE(2026,1,22),'CALENDARIO INGRESOS'!$G:$G,"<="&DATE(2026,1,31)) -> 0 | G9: =COUNTIFS('CALENDARIO INGRESOS'!$M:$M,">30",'CALENDARIO INGRESOS'!$G:$G,">="&DATE(2026,1,1),'CALENDARIO INGRESOS'!$G:$G,"<="&DATE(2026,1,31))/COUNTIFS('CALENDARIO INGRESOS'!$G:$G,">="&DATE(2026,1,1),'CALENDARIO INGRESOS'!$G:$G,"<="&DATE(2026,1,31)) -> 0.0079365079 | H9: - | I9: =IF(G9<=0.15,"✓","✗") -> ✓
A11: 2. CLIENTES | B11: Responsable: Sebastián Arellano
A12: KPI | B12: META | C12: SEM 1 | D12: SEM 2 | E12: SEM 3 | F12: SEM 4 | G12: ACUMULADO | H12: % AVANCE | I12: ESTADO
A13: Clientes Activos | B13: ≥140 | C13: =COUNTIFS('RESUMEN CLIENTES'!G:G,"<="&DATE(2026,1,7),'RESUMEN CLIENTES'!M:M,"OK")+COUNTIFS('RESUMEN CLIENTES'!G:G,"<="&DATE(2026,1,7),'RESUMEN CLIENTES'!M:M,"¡REGULARIZAR!")+COUNTIFS('RESUMEN CLIENTES'!G:G,"<="&DATE(2026,1,7),'RESUMEN CLIENTES'!M:M,"EVALUACION") -> 127 | D13: =COUNTIFS('RESUMEN CLIENTES'!G:G,"<="&DATE(2026,1,14),'RESUMEN CLIENTES'!M:M,"OK")+COUNTIFS('RESUMEN CLIENTES'!G:G,"<="&DATE(2026,1,14),'RESUMEN CLIENTES'!M:M,"¡REGULARIZAR!")+COUNTIFS('RESUMEN CLIENTES'!G:G,"<="&DATE(2026,1,14),'RESUMEN CLIENTES'!M:M,"EVALUACION") -> 130 | E13: =COUNTIFS('RESUMEN CLIENTES'!G:G,"<="&DATE(2026,1,21),'RESUMEN CLIENTES'!M:M,"OK")+COUNTIFS('RESUMEN CLIENTES'!G:G,"<="&DATE(2026,1,21),'RESUMEN CLIENTES'!M:M,"¡REGULARIZAR!")+COUNTIFS('RESUMEN CLIENTES'!G:G,"<="&DATE(2026,1,21),'RESUMEN CLIENTES'!M:M,"EVALUACION") -> 134 | F13: =COUNTIFS('RESUMEN CLIENTES'!G:G,"<="&DATE(2026,1,31),'RESUMEN CLIENTES'!M:M,"OK")+COUNTIFS('RESUMEN CLIENTES'!G:G,"<="&DATE(2026,1,31),'RESUMEN CLIENTES'!M:M,"¡REGULARIZAR!")+COUNTIFS('RESUMEN CLIENTES'!G:G,"<="&DATE(2026,1,31),'RESUMEN CLIENTES'!M:M,"EVALUACION") -> 140 | G13: =+F13 -> 140 | H13: - | I13: =IF(G13>=140,"✓","✗") -> ✓
A14: Nuevos Clientes | B14: ≥20/mes | C14: =COUNTIFS('RESUMEN CLIENTES'!$G:$G,">="&DATE(2026,1,1),'RESUMEN CLIENTES'!$G:$G,"<="&DATE(2026,1,7)) -> 1 | D14: =COUNTIFS('RESUMEN CLIENTES'!$G:$G,">="&DATE(2026,1,8),'RESUMEN CLIENTES'!$G:$G,"<="&DATE(2026,1,14)) -> 3 | E14: =COUNTIFS('RESUMEN CLIENTES'!$G:$G,">="&DATE(2026,1,15),'RESUMEN CLIENTES'!$G:$G,"<="&DATE(2026,1,21)) -> 4 | F14: =COUNTIFS('RESUMEN CLIENTES'!$G:$G,">="&DATE(2026,1,22),'RESUMEN CLIENTES'!$G:$G,"<="&DATE(2026,1,31)) -> 7 | G14: =COUNTIFS('RESUMEN CLIENTES'!$G:$G,">="&DATE(2026,1,1),'RESUMEN CLIENTES'!$G:$G,"<="&DATE(2026,1,31)) -> 15 | H14: =G14/20 -> 0.75 | I14: =IF(G14>=20,"✓","✗") -> ✗
A15: Tasa Abandono | B15: ≤5% | C15: =(COUNTIFS('RESUMEN CLIENTES'!J:J,">="&DATE(2026,1,1),'RESUMEN CLIENTES'!J:J,"<="&DATE(2026,1,7),'RESUMEN CLIENTES'!M:M,"ELIMINADO")+COUNTIFS('RESUMEN CLIENTES'!J:J,">="&DATE(2026,1,1),'RESUMEN CLIENTES'!J:J,"<="&DATE(2026,1,7),'RESUMEN CLIENTES'!M:M,"SUSPENDIDO")+COUNTIFS('RESUMEN CLIENTES'!J:J,">="&DATE(2026,1,1),'RESUMEN CLIENTES'!J:J,"<="&DATE(2026,1,7),'RESUMEN CLIENTES'!M:M,"EN PAUSA"))/C13 -> 0 | D15: =(COUNTIFS('RESUMEN CLIENTES'!J:J,">="&DATE(2026,1,8),'RESUMEN CLIENTES'!J:J,"<="&DATE(2026,1,14),'RESUMEN CLIENTES'!M:M,"ELIMINADO")+COUNTIFS('RESUMEN CLIENTES'!J:J,">="&DATE(2026,1,8),'RESUMEN CLIENTES'!J:J,"<="&DATE(2026,1,14),'RESUMEN CLIENTES'!M:M,"SUSPENDIDO")+COUNTIFS('RESUMEN CLIENTES'!J:J,">="&DATE(2026,1,8),'RESUMEN CLIENTES'!J:J,"<="&DATE(2026,1,14),'RESUMEN CLIENTES'!M:M,"EN PAUSA"))/D13 -> 0 | E15: =(COUNTIFS('RESUMEN CLIENTES'!J:J,">="&DATE(2026,1,15),'RESUMEN CLIENTES'!J:J,"<="&DATE(2026,1,21),'RESUMEN CLIENTES'!M:M,"ELIMINADO")+COUNTIFS('RESUMEN CLIENTES'!J:J,">="&DATE(2026,1,15),'RESUMEN CLIENTES'!J:J,"<="&DATE(2026,1,21),'RESUMEN CLIENTES'!M:M,"SUSPENDIDO")+COUNTIFS('RESUMEN CLIENTES'!J:J,">="&DATE(2026,1,15),'RESUMEN CLIENTES'!J:J,"<="&DATE(2026,1,21),'RESUMEN CLIENTES'!M:M,"EN PAUSA"))/E13 -> 0 | F15: =(COUNTIFS('RESUMEN CLIENTES'!J:J,">="&DATE(2026,1,22),'RESUMEN CLIENTES'!J:J,"<="&DATE(2026,1,31),'RESUMEN CLIENTES'!M:M,"ELIMINADO")+COUNTIFS('RESUMEN CLIENTES'!J:J,">="&DATE(2026,1,22),'RESUMEN CLIENTES'!J:J,"<="&DATE(2026,1,31),'RESUMEN CLIENTES'!M:M,"SUSPENDIDO")+COUNTIFS('RESUMEN CLIENTES'!J:J,">="&DATE(2026,1,22),'RESUMEN CLIENTES'!J:J,"<="&DATE(2026,1,31),'RESUMEN CLIENTES'!M:M,"EN PAUSA"))/F13 -> 0.0071428571 | G15: =(COUNTIFS('RESUMEN CLIENTES'!J:J,">="&DATE(2026,1,1),'RESUMEN CLIENTES'!J:J,"<="&DATE(2026,1,31),'RESUMEN CLIENTES'!M:M,"ELIMINADO")+COUNTIFS('RESUMEN CLIENTES'!J:J,">="&DATE(2026,1,1),'RESUMEN CLIENTES'!J:J,"<="&DATE(2026,1,31),'RESUMEN CLIENTES'!M:M,"SUSPENDIDO")+COUNTIFS('RESUMEN CLIENTES'!J:J,">="&DATE(2026,1,1),'RESUMEN CLIENTES'!J:J,"<="&DATE(2026,1,31),'RESUMEN CLIENTES'!M:M,"EN PAUSA"))/G13 -> 0.0071428571 | H15: - | I15: =IF(G15<=0.05,"✓","✗") -> ✓
A16: Clientes OK | B16: ≥90% | C16: =COUNTIFS('RESUMEN CLIENTES'!$G:$G,"<="&DATE(2026,1,7),'RESUMEN CLIENTES'!$M:$M,"OK")/C13 -> 0.93700787 | D16: =COUNTIFS('RESUMEN CLIENTES'!$G:$G,"<="&DATE(2026,1,14),'RESUMEN CLIENTES'!$M:$M,"OK")/D13 -> 0.93076923 | E16: =COUNTIFS('RESUMEN CLIENTES'!$G:$G,"<="&DATE(2026,1,21),'RESUMEN CLIENTES'!$M:$M,"OK")/E13 -> 0.92537313 | F16: =COUNTIFS('RESUMEN CLIENTES'!$G:$G,"<="&DATE(2026,1,31),'RESUMEN CLIENTES'!$M:$M,"OK")/F13 -> 0.91428571 | G16: =COUNTIFS('RESUMEN CLIENTES'!$G:$G,"<="&DATE(2026,1,31),'RESUMEN CLIENTES'!$M:$M,"OK")/G13 -> 0.91428571 | H16: =G16/0.9 -> 1.015873 | I16: =IF(G16>=0.9,"✓","✗") -> ✓
A17: % Suscripción Activa | B17: ≥70% | C17: =COUNTIFS('RESUMEN CLIENTES'!$G:$G,"<="&DATE(2026,1,7),'RESUMEN CLIENTES'!$M:$M,"OK",'RESUMEN CLIENTES'!$W:$W,1)/COUNTIFS('RESUMEN CLIENTES'!$G:$G,"<="&DATE(2026,1,7),'RESUMEN CLIENTES'!$M:$M,"OK") -> 0.5210084 | D17: =COUNTIFS('RESUMEN CLIENTES'!$G:$G,"<="&DATE(2026,1,14),'RESUMEN CLIENTES'!$M:$M,"OK",'RESUMEN CLIENTES'!$W:$W,1)/COUNTIFS('RESUMEN CLIENTES'!$G:$G,"<="&DATE(2026,1,14),'RESUMEN CLIENTES'!$M:$M,"OK") -> 0.52066116 | E17: =COUNTIFS('RESUMEN CLIENTES'!$G:$G,"<="&DATE(2026,1,21),'RESUMEN CLIENTES'!$M:$M,"OK",'RESUMEN CLIENTES'!$W:$W,1)/COUNTIFS('RESUMEN CLIENTES'!$G:$G,"<="&DATE(2026,1,21),'RESUMEN CLIENTES'!$M:$M,"OK") -> 0.51612903 | F17: =COUNTIFS('RESUMEN CLIENTES'!$G:$G,"<="&DATE(2026,1,31),'RESUMEN CLIENTES'!$M:$M,"OK",'RESUMEN CLIENTES'!$W:$W,1)/COUNTIFS('RESUMEN CLIENTES'!$G:$G,"<="&DATE(2026,1,31),'RESUMEN CLIENTES'!$M:$M,"OK") -> 0.515625 | G17: =COUNTIFS('RESUMEN CLIENTES'!$G:$G,"<="&DATE(2026,1,31),'RESUMEN CLIENTES'!$M:$M,"OK",'RESUMEN CLIENTES'!$W:$W,1)/COUNTIFS('RESUMEN CLIENTES'!$G:$G,"<="&DATE(2026,1,31),'RESUMEN CLIENTES'!$M:$M,"OK") -> 0.515625 | H17: =G17/0.7 -> 0.73660714 | I17: =IF(G17>=0.7,"✓","✗") -> ✗
A19: 3. MÉTRICAS FINANCIERAS | B19: Responsables: José I. Donoso / S. Arellano
A20: KPI | B20: META | C20: SEM 1 | D20: SEM 2 | E20: SEM 3 | F20: SEM 4 | G20: ACUMULADO | H20: % AVANCE | I20: ESTADO
A21: Ingresos Totales | B21: Monitor | C21: =SUMIFS(INGRESOS!$J:$J,INGRESOS!$A:$A,">="&DATE(2026,1,1),INGRESOS!$A:$A,"<="&MIN(TODAY(),DATE(2026,1,7))) -> 34007.379 | D21: =SUMIFS(INGRESOS!$J:$J,INGRESOS!$A:$A,">="&DATE(2026,1,8),INGRESOS!$A:$A,"<="&MIN(TODAY(),DATE(2026,1,14))) -> 28446.479 | E21: =SUMIFS(INGRESOS!$J:$J,INGRESOS!$A:$A,">="&DATE(2026,1,15),INGRESOS!$A:$A,"<="&MIN(TODAY(),DATE(2026,1,21))) -> 14351.08 | F21: =SUMIFS(INGRESOS!$J:$J,INGRESOS!$A:$A,">="&DATE(2026,1,22),INGRESOS!$A:$A,"<="&MIN(TODAY(),DATE(2026,1,31))) -> 59466.173 | G21: =SUM(C21:F21) -> 136271.11 | H21: - | I21: -
A22: EBITDA | B22: ≥€0 | C22: =SUMIFS(INGRESOS!$J:$J,INGRESOS!$A:$A,">="&DATE(2026,1,1),INGRESOS!$A:$A,"<="&MIN(TODAY(),DATE(2026,1,7)))+SUMIFS(SALIDAS!$F:$F,SALIDAS!$U:$U,"COR",SALIDAS!$A:$A,">="&DATE(2026,1,1),SALIDAS!$A:$A,"<="&MIN(TODAY(),DATE(2026,1,7)))+SUMIFS(SALIDAS!$F:$F,SALIDAS!$U:$U,"OPEX",SALIDAS!$A:$A,">="&DATE(2026,1,1),SALIDAS!$A:$A,"<="&MIN(TODAY(),DATE(2026,1,7))) -> 1966.9795 | D22: =SUMIFS(INGRESOS!$J:$J,INGRESOS!$A:$A,">="&DATE(2026,1,8),INGRESOS!$A:$A,"<="&MIN(TODAY(),DATE(2026,1,14)))+SUMIFS(SALIDAS!$F:$F,SALIDAS!$U:$U,"COR",SALIDAS!$A:$A,">="&DATE(2026,1,8),SALIDAS!$A:$A,"<="&MIN(TODAY(),DATE(2026,1,14)))+SUMIFS(SALIDAS!$F:$F,SALIDAS!$U:$U,"OPEX",SALIDAS!$A:$A,">="&DATE(2026,1,8),SALIDAS!$A:$A,"<="&MIN(TODAY(),DATE(2026,1,14))) -> 23537.41 | E22: =SUMIFS(INGRESOS!$J:$J,INGRESOS!$A:$A,">="&DATE(2026,1,15),INGRESOS!$A:$A,"<="&MIN(TODAY(),DATE(2026,1,21)))+SUMIFS(SALIDAS!$F:$F,SALIDAS!$U:$U,"COR",SALIDAS!$A:$A,">="&DATE(2026,1,15),SALIDAS!$A:$A,"<="&MIN(TODAY(),DATE(2026,1,21)))+SUMIFS(SALIDAS!$F:$F,SALIDAS!$U:$U,"OPEX",SALIDAS!$A:$A,">="&DATE(2026,1,15),SALIDAS!$A:$A,"<="&MIN(TODAY(),DATE(2026,1,21))) -> -4699.2125 | F22: =SUMIFS(INGRESOS!$J:$J,INGRESOS!$A:$A,">="&DATE(2026,1,22),INGRESOS!$A:$A,"<="&MIN(TODAY(),DATE(2026,1,31)))+SUMIFS(SALIDAS!$F:$F,SALIDAS!$U:$U,"COR",SALIDAS!$A:$A,">="&DATE(2026,1,22),SALIDAS!$A:$A,"<="&MIN(TODAY(),DATE(2026,1,31)))+SUMIFS(SALIDAS!$F:$F,SALIDAS!$U:$U,"OPEX",SALIDAS!$A:$A,">="&DATE(2026,1,22),SALIDAS!$A:$A,"<="&MIN(TODAY(),DATE(2026,1,31))) -> -15150.755 | G22: =SUM(C22:F22) -> 5654.4221 | H22: =IF(G22>=0,1,0) -> 1 | I22: =IF(G22>=0,"✓","✗") -> ✓
A23: TOTAL OPEX | B23: Control | C23: =SUMIFS(SALIDAS!$F:$F,SALIDAS!$U:$U,"OPEX",SALIDAS!$A:$A,">="&DATE(2026,1,1),SALIDAS!$A:$A,"<="&MIN(TODAY(),DATE(2026,1,7))) -> -25388.776 | D23: =SUMIFS(SALIDAS!$F:$F,SALIDAS!$U:$U,"OPEX",SALIDAS!$A:$A,">="&DATE(2026,1,8),SALIDAS!$A:$A,"<="&MIN(TODAY(),DATE(2026,1,14))) -> -4909.0693 | E23: =SUMIFS(SALIDAS!$F:$F,SALIDAS!$U:$U,"OPEX",SALIDAS!$A:$A,">="&DATE(2026,1,15),SALIDAS!$A:$A,"<="&MIN(TODAY(),DATE(2026,1,21))) -> -15758.923 | F23: =SUMIFS(SALIDAS!$F:$F,SALIDAS!$U:$U,"OPEX",SALIDAS!$A:$A,">="&DATE(2026,1,22),SALIDAS!$A:$A,"<="&MIN(TODAY(),DATE(2026,1,31))) -> -69585.163 | G23: =SUM(C23:F23) -> -115641.93 | H23: - | I23: -
A24: Sales & Marketing | C24: =SUMIFS(SALIDAS!$F:$F,SALIDAS!$U:$U,"OPEX",SALIDAS!V:V,KPIs!A24,SALIDAS!$A:$A,">="&DATE(2026,1,1),SALIDAS!$A:$A,"<="&MIN(TODAY(),DATE(2026,1,7))) -> -15929.614 | D24: =SUMIFS(SALIDAS!$F:$F,SALIDAS!$U:$U,"OPEX",SALIDAS!V:V,KPIs!A24,SALIDAS!$A:$A,">="&DATE(2026,1,8),SALIDAS!$A:$A,"<="&MIN(TODAY(),DATE(2026,1,14))) -> -812.86922 | E24: =SUMIFS(SALIDAS!$F:$F,SALIDAS!$U:$U,"OPEX",SALIDAS!V:V,KPIs!A24,SALIDAS!$A:$A,">="&DATE(2026,1,15),SALIDAS!$A:$A,"<="&MIN(TODAY(),DATE(2026,1,21))) -> -737.31 | F24: =SUMIFS(SALIDAS!$F:$F,SALIDAS!$U:$U,"OPEX",SALIDAS!V:V,KPIs!A24,SALIDAS!$A:$A,">="&DATE(2026,1,22),SALIDAS!$A:$A,"<="&MIN(TODAY(),DATE(2026,1,31))) -> -28635.208 | G24: =SUM(C24:F24) -> -46115.002
A25: Research & Development | C25: =SUMIFS(SALIDAS!$F:$F,SALIDAS!$U:$U,"OPEX",SALIDAS!V:V,A25,SALIDAS!$A:$A,">="&DATE(2026,1,1),SALIDAS!$A:$A,"<="&MIN(TODAY(),DATE(2026,1,7))) -> -158.33827 | D25: =SUMIFS(SALIDAS!$F:$F,SALIDAS!$U:$U,"OPEX",SALIDAS!V:V,KPIs!A25,SALIDAS!$A:$A,">="&DATE(2026,1,8),SALIDAS!$A:$A,"<="&MIN(TODAY(),DATE(2026,1,14))) -> -781.83 | E25: =SUMIFS(SALIDAS!$F:$F,SALIDAS!$U:$U,"OPEX",SALIDAS!V:V,KPIs!A25,SALIDAS!$A:$A,">="&DATE(2026,1,15),SALIDAS!$A:$A,"<="&MIN(TODAY(),DATE(2026,1,21))) -> -192.44 | F25: =SUMIFS(SALIDAS!$F:$F,SALIDAS!$U:$U,"OPEX",SALIDAS!V:V,KPIs!A25,SALIDAS!$A:$A,">="&DATE(2026,1,22),SALIDAS!$A:$A,"<="&MIN(TODAY(),DATE(2026,1,31))) -> -529.46273 | G25: =SUM(C25:F25) -> -1662.071
A26: General & Administrative | C26: =SUMIFS(SALIDAS!$F:$F,SALIDAS!$U:$U,"OPEX",SALIDAS!V:V,A26,SALIDAS!$A:$A,">="&DATE(2026,1,1),SALIDAS!$A:$A,"<="&MIN(TODAY(),DATE(2026,1,7))) -> -9300.8234 | D26: =SUMIFS(SALIDAS!$F:$F,SALIDAS!$U:$U,"OPEX",SALIDAS!V:V,KPIs!A26,SALIDAS!$A:$A,">="&DATE(2026,1,8),SALIDAS!$A:$A,"<="&MIN(TODAY(),DATE(2026,1,14))) -> -1560.7701 | E26: =SUMIFS(SALIDAS!$F:$F,SALIDAS!$U:$U,"OPEX",SALIDAS!V:V,KPIs!A26,SALIDAS!$A:$A,">="&DATE(2026,1,15),SALIDAS!$A:$A,"<="&MIN(TODAY(),DATE(2026,1,21))) -> -4416.6725 | F26: =SUMIFS(SALIDAS!$F:$F,SALIDAS!$U:$U,"OPEX",SALIDAS!V:V,KPIs!A26,SALIDAS!$A:$A,">="&DATE(2026,1,22),SALIDAS!$A:$A,"<="&MIN(TODAY(),DATE(2026,1,31))) -> -38038.697 | G26: =SUM(C26:F26) -> -53316.963
A27: Customer Success | C27: =SUMIFS(SALIDAS!$F:$F,SALIDAS!$U:$U,"OPEX",SALIDAS!V:V,A27,SALIDAS!$A:$A,">="&DATE(2026,1,1),SALIDAS!$A:$A,"<="&MIN(TODAY(),DATE(2026,1,7))) -> 0 | D27: =SUMIFS(SALIDAS!$F:$F,SALIDAS!$U:$U,"OPEX",SALIDAS!V:V,KPIs!A27,SALIDAS!$A:$A,">="&DATE(2026,1,8),SALIDAS!$A:$A,"<="&MIN(TODAY(),DATE(2026,1,14))) -> -1753.6 | E27: =SUMIFS(SALIDAS!$F:$F,SALIDAS!$U:$U,"OPEX",SALIDAS!V:V,KPIs!A27,SALIDAS!$A:$A,">="&DATE(2026,1,15),SALIDAS!$A:$A,"<="&MIN(TODAY(),DATE(2026,1,21))) -> -10412.5 | F27: =SUMIFS(SALIDAS!$F:$F,SALIDAS!$U:$U,"OPEX",SALIDAS!V:V,KPIs!A27,SALIDAS!$A:$A,">="&DATE(2026,1,22),SALIDAS!$A:$A,"<="&MIN(TODAY(),DATE(2026,1,31))) -> -2381.795 | G27: =SUM(C27:F27) -> -14547.895
A28: Margen Bruto | B28: Control | C28: =SUMIFS(INGRESOS!$J:$J,INGRESOS!$A:$A,">="&DATE(2026,1,1),INGRESOS!$A:$A,"<="&MIN(TODAY(),DATE(2026,1,7)))+SUMIFS(SALIDAS!$F:$F,SALIDAS!$U:$U,"COR",SALIDAS!$A:$A,">="&DATE(2026,1,1),SALIDAS!$A:$A,"<="&MIN(TODAY(),DATE(2026,1,7)))+SUMIFS(SALIDAS!$F:$F,SALIDAS!$V:$V,"Customer Success",SALIDAS!$U:$U,"OPEX",SALIDAS!$A:$A,">="&DATE(2026,1,1),SALIDAS!$A:$A,"<="&MIN(TODAY(),DATE(2026,1,7))) -> 27355.755 | D28: =SUMIFS(INGRESOS!$J:$J,INGRESOS!$A:$A,">="&DATE(2026,1,8),INGRESOS!$A:$A,"<="&MIN(TODAY(),DATE(2026,1,14)))+SUMIFS(SALIDAS!$F:$F,SALIDAS!$U:$U,"COR",SALIDAS!$A:$A,">="&DATE(2026,1,8),SALIDAS!$A:$A,"<="&MIN(TODAY(),DATE(2026,1,14)))+SUMIFS(SALIDAS!$F:$F,SALIDAS!$V:$V,"Customer Success",SALIDAS!$U:$U,"OPEX",SALIDAS!$A:$A,">="&DATE(2026,1,8),SALIDAS!$A:$A,"<="&MIN(TODAY(),DATE(2026,1,14))) -> 26692.879 | E28: =SUMIFS(INGRESOS!$J:$J,INGRESOS!$A:$A,">="&DATE(2026,1,15),INGRESOS!$A:$A,"<="&MIN(TODAY(),DATE(2026,1,21)))+SUMIFS(SALIDAS!$F:$F,SALIDAS!$U:$U,"COR",SALIDAS!$A:$A,">="&DATE(2026,1,15),SALIDAS!$A:$A,"<="&MIN(TODAY(),DATE(2026,1,21)))+SUMIFS(SALIDAS!$F:$F,SALIDAS!$V:$V,"Customer Success",SALIDAS!$U:$U,"OPEX",SALIDAS!$A:$A,">="&DATE(2026,1,15),SALIDAS!$A:$A,"<="&MIN(TODAY(),DATE(2026,1,21))) -> 647.21 | F28: =SUMIFS(INGRESOS!$J:$J,INGRESOS!$A:$A,">="&DATE(2026,1,22),INGRESOS!$A:$A,"<="&MIN(TODAY(),DATE(2026,1,31)))+SUMIFS(SALIDAS!$F:$F,SALIDAS!$U:$U,"COR",SALIDAS!$A:$A,">="&DATE(2026,1,22),SALIDAS!$A:$A,"<="&MIN(TODAY(),DATE(2026,1,31)))+SUMIFS(SALIDAS!$F:$F,SALIDAS!$V:$V,"Customer Success",SALIDAS!$U:$U,"OPEX",SALIDAS!$A:$A,">="&DATE(2026,1,22),SALIDAS!$A:$A,"<="&MIN(TODAY(),DATE(2026,1,31))) -> 52052.613 | G28: =SUM(C28:F28) -> 106748.46 | H28: =(G28/G21)/0.65 -> 1.2051593 | I28: -
A29: Margen Bruto % | B29: ≥65% | C29: =C28/C21 -> 0.80440646 | D29: =D28/D21 -> 0.93835441 | E29: =E28/E21 -> 0.045098348 | F29: =F28/F21 -> 0.87533148 | G29: =G28/G21 -> 0.78335354 | H29: - | I29: =IF((G28/G21)>=0.65,"✓","✗") -> ✓
A31: 4. GASTOS Y SAAS | B31: Responsable: Giovanny Bravo
A32: KPI | B32: META | C32: SEM 1 | D32: SEM 2 | E32: SEM 3 | F32: SEM 4 | G32: ACUMULADO | H32: % AVANCE | I32: ESTADO
A33: Total Gastos | B33: Control | C33: =-SUMIFS(SALIDAS!$F:$F, SALIDAS!$A:$A, ">=" & DATE(2026,1,1), SALIDAS!$A:$A, "<=" & DATE(2026,1,7)) -> 32040.4 | D33: =-SUMIFS(SALIDAS!$F:$F, SALIDAS!$A:$A, ">=" & DATE(2026,1,8), SALIDAS!$A:$A, "<=" & DATE(2026,1,14)) -> 4909.0693 | E33: =-SUMIFS(SALIDAS!$F:$F, SALIDAS!$A:$A, ">=" & DATE(2026,1,15), SALIDAS!$A:$A, "<=" & DATE(2026,1,21)) -> 19050.293 | F33: =-SUMIFS(SALIDAS!$F:$F, SALIDAS!$A:$A, ">=" & DATE(2026,1,22), SALIDAS!$A:$A, "<=" & DATE(2026,1,31)) -> 74616.928 | G33: =SUM(C33:F33) -> 130616.69 | H33: - | I33: -
A34: SaaS Mensual | B34: ≤€26,000 | C34: =-SUMIFS(SALIDAS!$F:$F,SALIDAS!$K:$K,"SaaS",SALIDAS!$A:$A,">="&DATE(2026,1,1),SALIDAS!$A:$A,"<="&DATE(2026,1,7)) -> 6324.1039 | D34: =-SUMIFS(SALIDAS!$F:$F,SALIDAS!$K:$K,"SaaS",SALIDAS!$A:$A,">="&DATE(2026,1,8),SALIDAS!$A:$A,"<="&DATE(2026,1,14)) -> 3667.5892 | E34: =-SUMIFS(SALIDAS!$F:$F,SALIDAS!$K:$K,"SaaS",SALIDAS!$A:$A,">="&DATE(2026,1,15),SALIDAS!$A:$A,"<="&DATE(2026,1,21)) -> 5599.4812 | F34: =-SUMIFS(SALIDAS!$F:$F,SALIDAS!$K:$K,"SaaS",SALIDAS!$A:$A,">="&DATE(2026,1,22),SALIDAS!$A:$A,"<="&DATE(2026,1,31)) -> 8108.8026 | G34: =SUM(C34:F34) -> 23699.977 | H34: =G34/26000 -> 0.91153757 | I34: =IF(G34<=26000,"✓","✗") -> ✓
A35: Utilización SaaS | B35: Proximamente
A36: Ahorros SaaS | B36: Proximamente
A37: Pagos On-Time | B37: Proximamente
A38: Errores Pagos | B38: Proximamente
A40: 5. FLUJO DE CAJA Y RUNWAY | B40: Responsable: Sebastián Arellano / Giovanny Bravo
A41: KPI | B41: META | C41: SEM 1 | D41: SEM 2 | E41: SEM 3 | F41: SEM 4 | G41: ACUMULADO | H41: % AVANCE | I41: ESTADO
A42: Flujo Programado | C42: =SUMIFS('CALENDARIO INGRESOS'!$I:$I,'CALENDARIO INGRESOS'!$G:$G,">="&DATE(2026,1,1),'CALENDARIO INGRESOS'!$G:$G,"<="&DATE(2026,1,7))-SUMIFS('CALENDARIO INGRESOS'!$I:$I,'CALENDARIO INGRESOS'!$G:$G,">="&DATE(2026,1,1),'CALENDARIO INGRESOS'!$G:$G,"<="&DATE(2026,1,7))*EERR!P16 -> 33436.782 | D42: =SUMIFS('CALENDARIO INGRESOS'!$I:$I,'CALENDARIO INGRESOS'!$G:$G,">="&DATE(2026,1,8),'CALENDARIO INGRESOS'!$G:$G,"<="&DATE(2026,1,14))-SUMIFS('CALENDARIO INGRESOS'!$I:$I,'CALENDARIO INGRESOS'!$G:$G,">="&DATE(2026,1,8),'CALENDARIO INGRESOS'!$G:$G,"<="&DATE(2026,1,14))*EERR!P16 -> 21245.824 | E42: =SUMIFS('CALENDARIO INGRESOS'!$I:$I,'CALENDARIO INGRESOS'!$G:$G,">="&DATE(2026,1,15),'CALENDARIO INGRESOS'!$G:$G,"<="&DATE(2026,1,21))-SUMIFS('CALENDARIO INGRESOS'!$I:$I,'CALENDARIO INGRESOS'!$G:$G,">="&DATE(2026,1,15),'CALENDARIO INGRESOS'!$G:$G,"<="&DATE(2026,1,21))*EERR!P16 -> 17900.436 | F42: =SUMIFS('CALENDARIO INGRESOS'!$I:$I,'CALENDARIO INGRESOS'!$G:$G,">="&DATE(2026,1,22),'CALENDARIO INGRESOS'!$G:$G,"<="&DATE(2026,1,31))-SUMIFS('CALENDARIO INGRESOS'!$I:$I,'CALENDARIO INGRESOS'!$G:$G,">="&DATE(2026,1,22),'CALENDARIO INGRESOS'!$G:$G,"<="&DATE(2026,1,31))*EERR!P16 -> 63224.731 | G42: =SUM(C42:F42) -> 135807.77 | H42: - | I42: -
A43: Flujo Caja Neto | C43: =C21-C33 -> 1966.9795 | D43: =D21-D33 -> 23537.41 | E43: =E21-E33 -> -4699.2125 | F43: =F21-F33 -> -15150.755 | G43: =SUM(C43:F43) -> 5654.4221 | H43: =IF(G42>0,"✓ Positivo","✗ Negativo") -> ✓ Positivo | I43: =IF(G41>=0,"✓","✗") -> ✓
A44: Caja Neta Acumulada | C44: =C43 -> 1966.9795 | D44: =C44+D43 -> 25504.389 | E44: =D44+E43 -> 20805.177 | F44: =E44+F43 -> 5654.4221 | G44: =+F44 -> 5654.4221 | H44: =IF(F44>0,"✓ Positivo","✗ Negativo") -> ✓ Positivo | I44: =IF(G44>=0,"✓","✗") -> ✓
A45: Runway Proyectado | C45: - | D45: - | E45: - | F45: - | G45: (saldo 0)
A47: SEGUIMIENTO SEMANAL DE KPIs - FEBRERO 2026
A49: 1. CAJA Y COBRANZA | B49: Responsable: Sebastián Arellano
A50: KPI | B50: META | C50: SEM 1 | D50: SEM 2 | E50: SEM 3 | F50: SEM 4 | G50: ACUMULADO | H50: % AVANCE | I50: ESTADO
A51: Ratio Cobranza | B51: ≥90% | C51: =SUMIFS('CALENDARIO INGRESOS'!$I:$I,'CALENDARIO INGRESOS'!$L:$L,"PAGADA",'CALENDARIO INGRESOS'!$G:$G,">="&DATE(2026,2,1),'CALENDARIO INGRESOS'!$G:$G,"<="&DATE(2026,2,7))/SUMIFS('CALENDARIO INGRESOS'!$I:$I,'CALENDARIO INGRESOS'!$G:$G,">="&DATE(2026,2,1),'CALENDARIO INGRESOS'!$G:$G,"<="&DATE(2026,2,7)) -> 0.95457355 | D51: =SUMIFS('CALENDARIO INGRESOS'!$I:$I,'CALENDARIO INGRESOS'!$L:$L,"PAGADA",'CALENDARIO INGRESOS'!$G:$G,">="&DATE(2026,2,8),'CALENDARIO INGRESOS'!$G:$G,"<="&DATE(2026,2,14))/SUMIFS('CALENDARIO INGRESOS'!$I:$I,'CALENDARIO INGRESOS'!$G:$G,">="&DATE(2026,2,8),'CALENDARIO INGRESOS'!$G:$G,"<="&DATE(2026,2,14)) -> 0.48470209 | E51: =SUMIFS('CALENDARIO INGRESOS'!$I:$I,'CALENDARIO INGRESOS'!$L:$L,"PAGADA",'CALENDARIO INGRESOS'!$G:$G,">="&DATE(2026,2,15),'CALENDARIO INGRESOS'!$G:$G,"<="&DATE(2026,2,21))/SUMIFS('CALENDARIO INGRESOS'!$I:$I,'CALENDARIO INGRESOS'!$G:$G,">="&DATE(2026,2,15),'CALENDARIO INGRESOS'!$G:$G,"<="&DATE(2026,2,21)) -> 0.80763098 | F51: =SUMIFS('CALENDARIO INGRESOS'!$I:$I,'CALENDARIO INGRESOS'!$L:$L,"PAGADA",'CALENDARIO INGRESOS'!$G:$G,">="&DATE(2026,2,22),'CALENDARIO INGRESOS'!$G:$G,"<="&DATE(2026,2,28))/SUMIFS('CALENDARIO INGRESOS'!$I:$I,'CALENDARIO INGRESOS'!$G:$G,">="&DATE(2026,2,22),'CALENDARIO INGRESOS'!$G:$G,"<="&DATE(2026,2,28)) -> 0.92780355 | G51: =SUMIFS('CALENDARIO INGRESOS'!$I:$I,'CALENDARIO INGRESOS'!$L:$L,"PAGADA",'CALENDARIO INGRESOS'!$G:$G,">="&DATE(2026,2,1),'CALENDARIO INGRESOS'!$G:$G,"<="&DATE(2026,2,28))/SUMIFS('CALENDARIO INGRESOS'!$I:$I,'CALENDARIO INGRESOS'!$G:$G,">="&DATE(2026,2,1),'CALENDARIO INGRESOS'!$G:$G,"<="&DATE(2026,2,28)) -> 0.85275903 | H51: - | I51: =IF(G51>=0.9,"✓","✗") -> ✗
A52: Cobranza Bruta | B52: ≥€120,000 | C52: =SUMIFS(INGRESOS!$G:$G,INGRESOS!$A:$A,">="&DATE(2026,2,1),INGRESOS!$A:$A,"<="&DATE(2026,2,7)) -> 46144.303 | D52: =SUMIFS(INGRESOS!$G:$G,INGRESOS!$A:$A,">="&DATE(2026,2,8),INGRESOS!$A:$A,"<="&DATE(2026,2,14)) -> 18213.168 | E52: =SUMIFS(INGRESOS!$G:$G,INGRESOS!$A:$A,">="&DATE(2026,2,15),INGRESOS!$A:$A,"<="&DATE(2026,2,21)) -> 19740 | F52: =SUMIFS(INGRESOS!$G:$G,INGRESOS!$A:$A,">="&DATE(2026,2,22),INGRESOS!$A:$A,"<="&DATE(2026,2,28)) -> 31382.698 | G52: =SUMIFS(INGRESOS!$G:$G,INGRESOS!$A:$A,">="&DATE(2026,2,1),INGRESOS!$A:$A,"<="&DATE(2026,2,28)) -> 115480.17 | H52: =G52/120000 -> 0.96233473 | I52: =IF(G52>=120000,"✓","✗") -> ✗
A53: Cobros pendientes | C53: =SUMIFS('CALENDARIO INGRESOS'!$I:$I,'CALENDARIO INGRESOS'!$D:$D,"OK",'CALENDARIO INGRESOS'!$L:$L,"<>PAGADA",'CALENDARIO INGRESOS'!$G:$G,">="&DATE(2026,2,1),'CALENDARIO INGRESOS'!$G:$G,"<="&DATE(2026,2,7)) -> 0 | D53: =SUMIFS('CALENDARIO INGRESOS'!$I:$I,'CALENDARIO INGRESOS'!$D:$D,"OK",'CALENDARIO INGRESOS'!$L:$L,"<>PAGADA",'CALENDARIO INGRESOS'!$G:$G,">="&DATE(2026,2,8),'CALENDARIO INGRESOS'!$G:$G,"<="&DATE(2026,2,14)) -> 100 | E53: =SUMIFS('CALENDARIO INGRESOS'!$I:$I,'CALENDARIO INGRESOS'!$D:$D,"OK",'CALENDARIO INGRESOS'!$L:$L,"<>PAGADA",'CALENDARIO INGRESOS'!$G:$G,">="&DATE(2026,2,15),'CALENDARIO INGRESOS'!$G:$G,"<="&DATE(2026,2,21)) -> 1750 | F53: =SUMIFS('CALENDARIO INGRESOS'!$I:$I,'CALENDARIO INGRESOS'!$D:$D,"OK",'CALENDARIO INGRESOS'!$L:$L,"<>PAGADA",'CALENDARIO INGRESOS'!$G:$G,">="&DATE(2026,2,22),'CALENDARIO INGRESOS'!$G:$G,"<="&DATE(2026,2,28)) -> 1000 | G53: =SUMIFS('CALENDARIO INGRESOS'!$I:$I,'CALENDARIO INGRESOS'!$D:$D,"OK",'CALENDARIO INGRESOS'!$L:$L,"<>PAGADA",'CALENDARIO INGRESOS'!$G:$G,">="&DATE(2026,2,1),'CALENDARIO INGRESOS'!$G:$G,"<="&DATE(2026,2,28)) -> 2850
A54: Incobrable | C54: =SUMIFS('CALENDARIO INGRESOS'!$I:$I,'CALENDARIO INGRESOS'!$D:$D,"ELIMINADO",'CALENDARIO INGRESOS'!$L:$L,"<>PAGADA",'CALENDARIO INGRESOS'!$G:$G,">="&DATE(2026,2,1),'CALENDARIO INGRESOS'!$G:$G,"<="&DATE(2026,2,7)) -> 0 | D54: =SUMIFS('CALENDARIO INGRESOS'!$I:$I,'CALENDARIO INGRESOS'!$D:$D,"ELIMINADO",'CALENDARIO INGRESOS'!$L:$L,"<>PAGADA",'CALENDARIO INGRESOS'!$G:$G,">="&DATE(2026,2,8),'CALENDARIO INGRESOS'!$G:$G,"<="&DATE(2026,2,14)) -> 9500 | E54: =SUMIFS('CALENDARIO INGRESOS'!$I:$I,'CALENDARIO INGRESOS'!$D:$D,"ELIMINADO",'CALENDARIO INGRESOS'!$L:$L,"<>PAGADA",'CALENDARIO INGRESOS'!$G:$G,">="&DATE(2026,2,15),'CALENDARIO INGRESOS'!$G:$G,"<="&DATE(2026,2,21)) -> 0 | F54: =SUMIFS('CALENDARIO INGRESOS'!$I:$I,'CALENDARIO INGRESOS'!$D:$D,"ELIMINADO",'CALENDARIO INGRESOS'!$L:$L,"<>PAGADA",'CALENDARIO INGRESOS'!$G:$G,">="&DATE(2026,2,22),'CALENDARIO INGRESOS'!$G:$G,"<="&DATE(2026,2,28)) -> 0 | G54: =SUMIFS('CALENDARIO INGRESOS'!$I:$I,'CALENDARIO INGRESOS'!$D:$D,"ELIMINADO",'CALENDARIO INGRESOS'!$L:$L,"<>PAGADA",'CALENDARIO INGRESOS'!$G:$G,">="&DATE(2026,2,1),'CALENDARIO INGRESOS'!$G:$G,"<="&DATE(2026,2,28)) -> 9500
A55: Facturas On-Time | B55: ≥95% | C55: =COUNTIFS('CALENDARIO INGRESOS'!$L:$L,"PAGADA",'CALENDARIO INGRESOS'!$M:$M,">=0",'CALENDARIO INGRESOS'!$G:$G,">="&DATE(2026,2,1),'CALENDARIO INGRESOS'!$G:$G,"<="&DATE(2026,2,7))/COUNTIFS('CALENDARIO INGRESOS'!$G:$G,">="&DATE(2026,2,1),'CALENDARIO INGRESOS'!$G:$G,"<="&DATE(2026,2,7)) -> 0.72916667 | D55: =COUNTIFS('CALENDARIO INGRESOS'!$L:$L,"PAGADA",'CALENDARIO INGRESOS'!$M:$M,">=0",'CALENDARIO INGRESOS'!$G:$G,">="&DATE(2026,2,8),'CALENDARIO INGRESOS'!$G:$G,"<="&DATE(2026,2,14))/COUNTIFS('CALENDARIO INGRESOS'!$G:$G,">="&DATE(2026,2,8),'CALENDARIO INGRESOS'!$G:$G,"<="&DATE(2026,2,14)) -> 0.63636364 | E55: =IF(TODAY()>=DATE(2026,2,15),COUNTIFS('CALENDARIO INGRESOS'!$L:$L,"PAGADA",'CALENDARIO INGRESOS'!$M:$M,">=0",'CALENDARIO INGRESOS'!$G:$G,">="&DATE(2026,2,15),'CALENDARIO INGRESOS'!$G:$G,"<="&DATE(2026,2,21))/COUNTIFS('CALENDARIO INGRESOS'!$G:$G,">="&DATE(2026,2,15),'CALENDARIO INGRESOS'!$G:$G,"<="&DATE(2026,2,21)),0) -> 0.38461538 | F55: =IF(TODAY()>=DATE(2026,2,22),COUNTIFS('CALENDARIO INGRESOS'!$L:$L,"PAGADA",'CALENDARIO INGRESOS'!$M:$M,">=0",'CALENDARIO INGRESOS'!$G:$G,">="&DATE(2026,2,22),'CALENDARIO INGRESOS'!$G:$G,"<="&DATE(2026,2,28))/COUNTIFS('CALENDARIO INGRESOS'!$G:$G,">="&DATE(2026,2,22),'CALENDARIO INGRESOS'!$G:$G,"<="&DATE(2026,2,28)),0) -> 0.825 | G55: =COUNTIFS('CALENDARIO INGRESOS'!$L:$L,"PAGADA",'CALENDARIO INGRESOS'!$M:$M,">=0",'CALENDARIO INGRESOS'!$G:$G,">="&DATE(2026,2,1),'CALENDARIO INGRESOS'!$G:$G,"<="&DATE(2026,2,28))/COUNTIFS('CALENDARIO INGRESOS'!$G:$G,">="&DATE(2026,2,1),'CALENDARIO INGRESOS'!$G:$G,"<="&DATE(2026,2,28)) -> 0.68 | H55: =G55/0.95 -> 0.71578947 | I55: =IF(G55>=0.95,"✓","✗") -> ✗
A56: Dias de retraso promedio | B56: ≤2/mes | C56: =SUMIFS('CALENDARIO INGRESOS'!M:M,'CALENDARIO INGRESOS'!M:M,"<0",'CALENDARIO INGRESOS'!G:G,">="&DATE(2026,2,1),'CALENDARIO INGRESOS'!G:G,"<="&DATE(2026,2,7))/COUNTIFS('CALENDARIO INGRESOS'!M:M,"<0",'CALENDARIO INGRESOS'!G:G,">="&DATE(2026,2,1),'CALENDARIO INGRESOS'!G:G,"<="&DATE(2026,2,7)) -> -4.8181818 | D56: =IFERROR(SUMIFS('CALENDARIO INGRESOS'!M:M,'CALENDARIO INGRESOS'!M:M,"<0",'CALENDARIO INGRESOS'!G:G,">="&DATE(2026,2,8),'CALENDARIO INGRESOS'!G:G,"<="&DATE(2026,2,14))/COUNTIFS('CALENDARIO INGRESOS'!M:M,"<0",'CALENDARIO INGRESOS'!G:G,">="&DATE(2026,2,8),'CALENDARIO INGRESOS'!G:G,"<="&DATE(2026,2,14)),0) -> -5 | E56: =IFERROR(SUMIFS('CALENDARIO INGRESOS'!M:M,'CALENDARIO INGRESOS'!M:M,"<0",'CALENDARIO INGRESOS'!G:G,">="&DATE(2026,2,15),'CALENDARIO INGRESOS'!G:G,"<="&DATE(2026,2,21))/COUNTIFS('CALENDARIO INGRESOS'!M:M,"<0",'CALENDARIO INGRESOS'!G:G,">="&DATE(2026,2,15),'CALENDARIO INGRESOS'!G:G,"<="&DATE(2026,2,21)),0) -> -2.7857143 | F56: =IFERROR(SUMIFS('CALENDARIO INGRESOS'!M:M,'CALENDARIO INGRESOS'!M:M,"<0",'CALENDARIO INGRESOS'!G:G,">="&DATE(2026,2,22),'CALENDARIO INGRESOS'!G:G,"<="&DATE(2026,2,28))/COUNTIFS('CALENDARIO INGRESOS'!M:M,"<0",'CALENDARIO INGRESOS'!G:G,">="&DATE(2026,2,22),'CALENDARIO INGRESOS'!G:G,"<="&DATE(2026,2,28)),0) -> -3.5 | G56: =SUMIFS('CALENDARIO INGRESOS'!M:M,'CALENDARIO INGRESOS'!M:M,"<0",'CALENDARIO INGRESOS'!G:G,">="&DATE(2026,2,1),'CALENDARIO INGRESOS'!G:G,"<="&DATE(2026,2,28))/COUNTIFS('CALENDARIO INGRESOS'!M:M,"<0",'CALENDARIO INGRESOS'!G:G,">="&DATE(2026,2,1),'CALENDARIO INGRESOS'!G:G,"<="&DATE(2026,2,28)) -> -3.7419355 | I56: =IF(G56>=-2,"✓","✗") -> ✗
A57: AR > 15 días | B57: ≤15% | C57: =COUNTIFS('CALENDARIO INGRESOS'!$M:$M,">15",'CALENDARIO INGRESOS'!$G:$G,">="&DATE(2026,2,1),'CALENDARIO INGRESOS'!$G:$G,"<="&DATE(2026,2,7))/COUNTIFS('CALENDARIO INGRESOS'!$G:$G,">="&DATE(2026,2,1),'CALENDARIO INGRESOS'!$G:$G,"<="&DATE(2026,2,7)) -> 0.020833333 | D57: =COUNTIFS('CALENDARIO INGRESOS'!$M:$M,">15",'CALENDARIO INGRESOS'!$G:$G,">="&DATE(2026,2,8),'CALENDARIO INGRESOS'!$G:$G,"<="&DATE(2026,2,14))/COUNTIFS('CALENDARIO INGRESOS'!$G:$G,">="&DATE(2026,2,8),'CALENDARIO INGRESOS'!$G:$G,"<="&DATE(2026,2,14)) -> 0 | E57: =COUNTIFS('CALENDARIO INGRESOS'!$M:$M,">15",'CALENDARIO INGRESOS'!$G:$G,">="&DATE(2026,2,15),'CALENDARIO INGRESOS'!$G:$G,"<="&DATE(2026,2,21))/COUNTIFS('CALENDARIO INGRESOS'!$G:$G,">="&DATE(2026,2,15),'CALENDARIO INGRESOS'!$G:$G,"<="&DATE(2026,2,21)) -> 0.038461538 | F57: =COUNTIFS('CALENDARIO INGRESOS'!$M:$M,">15",'CALENDARIO INGRESOS'!$G:$G,">="&DATE(2026,2,22),'CALENDARIO INGRESOS'!$G:$G,"<="&DATE(2026,2,28))/COUNTIFS('CALENDARIO INGRESOS'!$G:$G,">="&DATE(2026,2,22),'CALENDARIO INGRESOS'!$G:$G,"<="&DATE(2026,2,28)) -> 0.025 | G57: =COUNTIFS('CALENDARIO INGRESOS'!$M:$M,">15",'CALENDARIO INGRESOS'!$G:$G,">="&DATE(2026,2,1),'CALENDARIO INGRESOS'!$G:$G,"<="&DATE(2026,2,28))/COUNTIFS('CALENDARIO INGRESOS'!$G:$G,">="&DATE(2026,2,1),'CALENDARIO INGRESOS'!$G:$G,"<="&DATE(2026,2,28)) -> 0.024 | H57: - | I57: =IF(G57<=0.15,"✓","✗") -> ✓
A59: 2. CLIENTES | B59: Responsable: Sebastián Arellano
A60: KPI | B60: META | C60: SEM 1 | D60: SEM 2 | E60: SEM 3 | F60: SEM 4 | G60: ACUMULADO | H60: % AVANCE | I60: ESTADO
A61: Clientes Activos | B61: ≥140 | C61: =IF(TODAY()>=DATE(2026,2,1),COUNTIFS('RESUMEN CLIENTES'!G:G,"<="&DATE(2026,2,7),'RESUMEN CLIENTES'!M:M,"OK")+COUNTIFS('RESUMEN CLIENTES'!G:G,"<="&DATE(2026,2,7),'RESUMEN CLIENTES'!M:M,"¡REGULARIZAR!")+COUNTIFS('RESUMEN CLIENTES'!G:G,"<="&DATE(2026,2,7),'RESUMEN CLIENTES'!M:M,"EVALUACION"),0) -> 142 | D61: =IF(TODAY()>=DATE(2026,2,8),COUNTIFS('RESUMEN CLIENTES'!G:G,"<="&DATE(2026,2,14),'RESUMEN CLIENTES'!M:M,"OK")+COUNTIFS('RESUMEN CLIENTES'!G:G,"<="&DATE(2026,2,14),'RESUMEN CLIENTES'!M:M,"¡REGULARIZAR!")+COUNTIFS('RESUMEN CLIENTES'!G:G,"<="&DATE(2026,2,14),'RESUMEN CLIENTES'!M:M,"EVALUACION"),0) -> 143 | E61: =IF(TODAY()>=DATE(2026,2,15),COUNTIFS('RESUMEN CLIENTES'!G:G,"<="&DATE(2026,2,21),'RESUMEN CLIENTES'!M:M,"OK")+COUNTIFS('RESUMEN CLIENTES'!G:G,"<="&DATE(2026,2,21),'RESUMEN CLIENTES'!M:M,"¡REGULARIZAR!")+COUNTIFS('RESUMEN CLIENTES'!G:G,"<="&DATE(2026,2,21),'RESUMEN CLIENTES'!M:M,"EVALUACION"),0) -> 144 | F61: =IF(TODAY()>=DATE(2026,2,22),COUNTIFS('RESUMEN CLIENTES'!G:G,"<="&DATE(2026,2,28),'RESUMEN CLIENTES'!M:M,"OK")+COUNTIFS('RESUMEN CLIENTES'!G:G,"<="&DATE(2026,2,28),'RESUMEN CLIENTES'!M:M,"¡REGULARIZAR!")+COUNTIFS('RESUMEN CLIENTES'!G:G,"<="&DATE(2026,2,28),'RESUMEN CLIENTES'!M:M,"EVALUACION"),0) -> 145 | G61: =COUNTIFS('RESUMEN CLIENTES'!G:G,"<="&DATE(2026,2,28),'RESUMEN CLIENTES'!M:M,"OK")+COUNTIFS('RESUMEN CLIENTES'!G:G,"<="&DATE(2026,2,28),'RESUMEN CLIENTES'!M:M,"¡REGULARIZAR!")+COUNTIFS('RESUMEN CLIENTES'!G:G,"<="&DATE(2026,2,28),'RESUMEN CLIENTES'!M:M,"EVALUACION") -> 145 | H61: - | I61: =IF(G61>=140,"✓","✗") -> ✓
A62: Nuevos Clientes | B62: ≥20/mes | C62: =COUNTIFS('RESUMEN CLIENTES'!$G:$G,">="&DATE(2026,2,1),'RESUMEN CLIENTES'!$G:$G,"<="&DATE(2026,2,7)) -> 2 | D62: =COUNTIFS('RESUMEN CLIENTES'!$G:$G,">="&DATE(2026,2,8),'RESUMEN CLIENTES'!$G:$G,"<="&DATE(2026,2,14)) -> 1 | E62: =COUNTIFS('RESUMEN CLIENTES'!$G:$G,">="&DATE(2026,2,15),'RESUMEN CLIENTES'!$G:$G,"<="&DATE(2026,2,21)) -> 1 | F62: =COUNTIFS('RESUMEN CLIENTES'!$G:$G,">="&DATE(2026,2,22),'RESUMEN CLIENTES'!$G:$G,"<="&DATE(2026,2,28)) -> 1 | G62: =COUNTIFS('RESUMEN CLIENTES'!$G:$G,">="&DATE(2026,2,1),'RESUMEN CLIENTES'!$G:$G,"<="&DATE(2026,2,28)) -> 5 | H62: =G62/20 -> 0.25 | I62: =IF(G62>=20,"✓","✗") -> ✗
A63: Tasa Abandono | B63: ≤5% | C63: =(COUNTIFS('RESUMEN CLIENTES'!J:J,">="&DATE(2026,2,1),'RESUMEN CLIENTES'!J:J,"<="&DATE(2026,2,7),'RESUMEN CLIENTES'!M:M,"ELIMINADO")+COUNTIFS('RESUMEN CLIENTES'!J:J,">="&DATE(2026,2,1),'RESUMEN CLIENTES'!J:J,"<="&DATE(2026,2,7),'RESUMEN CLIENTES'!M:M,"SUSPENDIDO")+COUNTIFS('RESUMEN CLIENTES'!J:J,">="&DATE(2026,2,1),'RESUMEN CLIENTES'!J:J,"<="&DATE(2026,2,7),'RESUMEN CLIENTES'!M:M,"EN PAUSA"))/C61 -> 0 | D63: =(COUNTIFS('RESUMEN CLIENTES'!J:J,">="&DATE(2026,2,8),'RESUMEN CLIENTES'!J:J,"<="&DATE(2026,2,14),'RESUMEN CLIENTES'!M:M,"ELIMINADO")+COUNTIFS('RESUMEN CLIENTES'!J:J,">="&DATE(2026,2,8),'RESUMEN CLIENTES'!J:J,"<="&DATE(2026,2,14),'RESUMEN CLIENTES'!M:M,"SUSPENDIDO")+COUNTIFS('RESUMEN CLIENTES'!J:J,">="&DATE(2026,2,8),'RESUMEN CLIENTES'!J:J,"<="&DATE(2026,2,14),'RESUMEN CLIENTES'!M:M,"EN PAUSA"))/D61 -> 0 | E63: =IFERROR((COUNTIFS('RESUMEN CLIENTES'!J:J,">="&DATE(2026,2,15),'RESUMEN CLIENTES'!J:J,"<="&DATE(2026,2,21),'RESUMEN CLIENTES'!M:M,"ELIMINADO")+COUNTIFS('RESUMEN CLIENTES'!J:J,">="&DATE(2026,2,15),'RESUMEN CLIENTES'!J:J,"<="&DATE(2026,2,21),'RESUMEN CLIENTES'!M:M,"SUSPENDIDO")+COUNTIFS('RESUMEN CLIENTES'!J:J,">="&DATE(2026,2,15),'RESUMEN CLIENTES'!J:J,"<="&DATE(2026,2,21),'RESUMEN CLIENTES'!M:M,"EN PAUSA"))/E61,0) -> 0 | F63: =IFERROR((COUNTIFS('RESUMEN CLIENTES'!J:J,">="&DATE(2026,2,22),'RESUMEN CLIENTES'!J:J,"<="&DATE(2026,2,28),'RESUMEN CLIENTES'!M:M,"ELIMINADO")+COUNTIFS('RESUMEN CLIENTES'!J:J,">="&DATE(2026,2,22),'RESUMEN CLIENTES'!J:J,"<="&DATE(2026,2,28),'RESUMEN CLIENTES'!M:M,"SUSPENDIDO")+COUNTIFS('RESUMEN CLIENTES'!J:J,">="&DATE(2026,2,22),'RESUMEN CLIENTES'!J:J,"<="&DATE(2026,2,28),'RESUMEN CLIENTES'!M:M,"EN PAUSA"))/F61,0) -> 0 | G63: =(COUNTIFS('RESUMEN CLIENTES'!J:J,">="&DATE(2026,2,1),'RESUMEN CLIENTES'!J:J,"<="&DATE(2026,2,28),'RESUMEN CLIENTES'!M:M,"ELIMINADO")+COUNTIFS('RESUMEN CLIENTES'!J:J,">="&DATE(2026,2,1),'RESUMEN CLIENTES'!J:J,"<="&DATE(2026,2,28),'RESUMEN CLIENTES'!M:M,"SUSPENDIDO")+COUNTIFS('RESUMEN CLIENTES'!J:J,">="&DATE(2026,2,1),'RESUMEN CLIENTES'!J:J,"<="&DATE(2026,2,28),'RESUMEN CLIENTES'!M:M,"EN PAUSA"))/G61 -> 0 | H63: - | I63: =IF(G63<=0.05,"✓","✗") -> ✓
A64: Clientes OK | B64: ≥90% | C64: =COUNTIFS('RESUMEN CLIENTES'!$G:$G,"<="&DATE(2026,2,7),'RESUMEN CLIENTES'!$M:$M,"OK")/C61 -> 0.9084507 | D64: =COUNTIFS('RESUMEN CLIENTES'!$G:$G,"<="&DATE(2026,2,14),'RESUMEN CLIENTES'!$M:$M,"OK")/D61 -> 0.90909091 | E64: =IFERROR(COUNTIFS('RESUMEN CLIENTES'!$G:$G,"<="&DATE(2026,2,21),'RESUMEN CLIENTES'!$M:$M,"OK")/E61,0) -> 0.90972222 | F64: =IFERROR(COUNTIFS('RESUMEN CLIENTES'!$G:$G,"<="&DATE(2026,2,28),'RESUMEN CLIENTES'!$M:$M,"OK")/F61,0) -> 0.91034483 | G64: =IFERROR(COUNTIFS('RESUMEN CLIENTES'!$G:$G,"<="&DATE(2026,2,28),'RESUMEN CLIENTES'!$M:$M,"OK")/G61,0) -> 0.91034483 | H64: =G64/0.9 -> 1.0114943 | I64: =IF(G64>=0.9,"✓","✗") -> ✓
A65: % Suscripción Activa | B65: ≥70% | C65: =IF(TODAY()>=DATE(2026,2,1),COUNTIFS('RESUMEN CLIENTES'!$G:$G,"<="&DATE(2026,2,7),'RESUMEN CLIENTES'!$M:$M,"OK",'RESUMEN CLIENTES'!$W:$W,1)/COUNTIFS('RESUMEN CLIENTES'!$G:$G,"<="&DATE(2026,2,7),'RESUMEN CLIENTES'!$M:$M,"OK"),0) -> 0.51162791 | D65: =IF(TODAY()>=DATE(2026,2,8),COUNTIFS('RESUMEN CLIENTES'!$G:$G,"<="&DATE(2026,2,14),'RESUMEN CLIENTES'!$M:$M,"OK",'RESUMEN CLIENTES'!$W:$W,1)/COUNTIFS('RESUMEN CLIENTES'!$G:$G,"<="&DATE(2026,2,14),'RESUMEN CLIENTES'!$M:$M,"OK"),0) -> 0.50769231 | E65: =IF(TODAY()>=DATE(2026,2,15),COUNTIFS('RESUMEN CLIENTES'!$G:$G,"<="&DATE(2026,2,21),'RESUMEN CLIENTES'!$M:$M,"OK",'RESUMEN CLIENTES'!$W:$W,1)/COUNTIFS('RESUMEN CLIENTES'!$G:$G,"<="&DATE(2026,2,21),'RESUMEN CLIENTES'!$M:$M,"OK"),0) -> 0.50381679 | F65: =IF(TODAY()>=DATE(2026,2,22),COUNTIFS('RESUMEN CLIENTES'!$G:$G,"<="&DATE(2026,2,28),'RESUMEN CLIENTES'!$M:$M,"OK",'RESUMEN CLIENTES'!$W:$W,1)/COUNTIFS('RESUMEN CLIENTES'!$G:$G,"<="&DATE(2026,2,28),'RESUMEN CLIENTES'!$M:$M,"OK"),0) -> 0.5 | G65: =COUNTIFS('RESUMEN CLIENTES'!$G:$G,"<="&DATE(2026,2,28),'RESUMEN CLIENTES'!$M:$M,"OK",'RESUMEN CLIENTES'!$W:$W,1)/COUNTIFS('RESUMEN CLIENTES'!$G:$G,"<="&DATE(2026,2,28),'RESUMEN CLIENTES'!$M:$M,"OK") -> 0.5 | H65: =G65/0.7 -> 0.71428571 | I65: =IF(G65>=0.7,"✓","✗") -> ✗
A67: 3. MÉTRICAS FINANCIERAS | B67: Responsables: José I. Donoso / S. Arellano
A68: KPI | B68: META | C68: SEM 1 | D68: SEM 2 | E68: SEM 3 | F68: SEM 4 | G68: ACUMULADO | H68: % AVANCE | I68: ESTADO
A69: Ingreso Neto | B69: Monitor | C69: =SUMIFS(INGRESOS!$J:$J,INGRESOS!$A:$A,">="&DATE(2026,2,1),INGRESOS!$A:$A,"<="&MIN(TODAY(),DATE(2026,2,7))) -> 44659.404 | D69: =SUMIFS(INGRESOS!$J:$J,INGRESOS!$A:$A,">="&DATE(2026,2,8),INGRESOS!$A:$A,"<="&MIN(TODAY(),DATE(2026,2,14))) -> 17737.098 | E69: =SUMIFS(INGRESOS!$J:$J,INGRESOS!$A:$A,">="&DATE(2026,2,15),INGRESOS!$A:$A,"<="&MIN(TODAY(),DATE(2026,2,21))) -> 19243.14 | F69: =SUMIFS(INGRESOS!$J:$J,INGRESOS!$A:$A,">="&DATE(2026,2,22),INGRESOS!$A:$A,"<="&MIN(TODAY(),DATE(2026,2,28))) -> 30353.728 | G69: =SUM(C69:F69) -> 111993.37 | H69: - | I69: -
A70: COR | C70: =SUMIFS(SALIDAS!$F:$F,SALIDAS!$U:$U,"COR",SALIDAS!$A:$A,">="&DATE(2026,2,1),SALIDAS!$A:$A,"<="&MIN(TODAY(),DATE(2026,2,7))) -> -1702.3085 | D70: =SUMIFS(SALIDAS!$F:$F,SALIDAS!$U:$U,"COR",SALIDAS!$A:$A,">="&DATE(2026,2,8),SALIDAS!$A:$A,"<="&MIN(TODAY(),DATE(2026,2,14))) -> -1800 | E70: =SUMIFS(SALIDAS!$F:$F,SALIDAS!$U:$U,"COR",SALIDAS!$A:$A,">="&DATE(2026,2,15),SALIDAS!$A:$A,"<="&MIN(TODAY(),DATE(2026,2,21))) -> -268.03 | F70: =SUMIFS(SALIDAS!$F:$F,SALIDAS!$U:$U,"COR",SALIDAS!$A:$A,">="&DATE(2026,2,22),SALIDAS!$A:$A,"<="&MIN(TODAY(),DATE(2026,2,28))) -> -2046.6161 | G70: =+SUM(C70:F70) -> -5816.9546
A71: Margen Bruto | B71: Control | C71: =SUMIFS(INGRESOS!$J:$J,INGRESOS!$A:$A,">="&DATE(2026,2,1),INGRESOS!$A:$A,"<="&MIN(TODAY(),DATE(2026,2,7)))+SUMIFS(SALIDAS!$F:$F,SALIDAS!$U:$U,"COR",SALIDAS!$A:$A,">="&DATE(2026,2,1),SALIDAS!$A:$A,"<="&MIN(TODAY(),DATE(2026,2,7)))+SUMIFS(SALIDAS!$F:$F,SALIDAS!$V:$V,"Customer Success",SALIDAS!$U:$U,"OPEX",SALIDAS!$A:$A,">="&DATE(2026,2,1),SALIDAS!$A:$A,"<="&MIN(TODAY(),DATE(2026,2,7))) -> 42957.095 | D71: =SUMIFS(INGRESOS!$J:$J,INGRESOS!$A:$A,">="&DATE(2026,2,8),INGRESOS!$A:$A,"<="&MIN(TODAY(),DATE(2026,2,14)))+SUMIFS(SALIDAS!$F:$F,SALIDAS!$U:$U,"COR",SALIDAS!$A:$A,">="&DATE(2026,2,8),SALIDAS!$A:$A,"<="&MIN(TODAY(),DATE(2026,2,14)))+SUMIFS(SALIDAS!$F:$F,SALIDAS!$V:$V,"Customer Success",SALIDAS!$U:$U,"OPEX",SALIDAS!$A:$A,">="&DATE(2026,2,8),SALIDAS!$A:$A,"<="&MIN(TODAY(),DATE(2026,2,14))) -> 14557.128 | E71: =SUMIFS(INGRESOS!$J:$J,INGRESOS!$A:$A,">="&DATE(2026,2,15),INGRESOS!$A:$A,"<="&MIN(TODAY(),DATE(2026,2,21)))+SUMIFS(SALIDAS!$F:$F,SALIDAS!$U:$U,"COR",SALIDAS!$A:$A,">="&DATE(2026,2,15),SALIDAS!$A:$A,"<="&MIN(TODAY(),DATE(2026,2,21)))+SUMIFS(SALIDAS!$F:$F,SALIDAS!$V:$V,"Customer Success",SALIDAS!$U:$U,"OPEX",SALIDAS!$A:$A,">="&DATE(2026,2,15),SALIDAS!$A:$A,"<="&MIN(TODAY(),DATE(2026,2,21))) -> 8295.84 | F71: =SUMIFS(INGRESOS!$J:$J,INGRESOS!$A:$A,">="&DATE(2026,2,22),INGRESOS!$A:$A,"<="&MIN(TODAY(),DATE(2026,2,28)))+SUMIFS(SALIDAS!$F:$F,SALIDAS!$U:$U,"COR",SALIDAS!$A:$A,">="&DATE(2026,2,22),SALIDAS!$A:$A,"<="&MIN(TODAY(),DATE(2026,2,28)))+SUMIFS(SALIDAS!$F:$F,SALIDAS!$V:$V,"Customer Success",SALIDAS!$U:$U,"OPEX",SALIDAS!$A:$A,">="&DATE(2026,2,22),SALIDAS!$A:$A,"<="&MIN(TODAY(),DATE(2026,2,28))) -> 28307.112 | G71: =SUM(C71:F71) -> 94117.175 | H71: =(G71/G69)/0.65 -> 1.2928949 | I71: -
A72: Margen Bruto % | B72: ≥65% | C72: =IF(TODAY()>=DATE(2026,2,1),C71/C69,0) -> 0.96188242 | D72: =IF(TODAY()>=DATE(2026,2,8),D71/D69,0) -> 0.82071644 | E72: =IF(TODAY()>=DATE(2026,2,15),E71/E69,0) -> 0.43110636 | F72: =IF(TODAY()>=DATE(2026,2,22),F71/F69,0) -> 0.93257447 | G72: =G71/G69 -> 0.84038167 | H72: - | I72: =IF((G71/G69)>=0.65,"✓","✗") -> ✓
A73: EBITDA | B73: ≥€0 | C73: =SUMIFS(INGRESOS!$J:$J,INGRESOS!$A:$A,">="&DATE(2026,2,1),INGRESOS!$A:$A,"<="&MIN(TODAY(),DATE(2026,2,7)))+SUMIFS(SALIDAS!$F:$F,SALIDAS!$U:$U,"COR",SALIDAS!$A:$A,">="&DATE(2026,2,1),SALIDAS!$A:$A,"<="&MIN(TODAY(),DATE(2026,2,7)))+SUMIFS(SALIDAS!$F:$F,SALIDAS!$U:$U,"OPEX",SALIDAS!$A:$A,">="&DATE(2026,2,1),SALIDAS!$A:$A,"<="&MIN(TODAY(),DATE(2026,2,7))) -> 19257.812 | D73: =SUMIFS(INGRESOS!$J:$J,INGRESOS!$A:$A,">="&DATE(2026,2,8),INGRESOS!$A:$A,"<="&MIN(TODAY(),DATE(2026,2,14)))+SUMIFS(SALIDAS!$F:$F,SALIDAS!$U:$U,"COR",SALIDAS!$A:$A,">="&DATE(2026,2,8),SALIDAS!$A:$A,"<="&MIN(TODAY(),DATE(2026,2,14)))+SUMIFS(SALIDAS!$F:$F,SALIDAS!$U:$U,"OPEX",SALIDAS!$A:$A,">="&DATE(2026,2,8),SALIDAS!$A:$A,"<="&MIN(TODAY(),DATE(2026,2,14))) -> 13345.933 | E73: =SUMIFS(INGRESOS!$J:$J,INGRESOS!$A:$A,">="&DATE(2026,2,15),INGRESOS!$A:$A,"<="&MIN(TODAY(),DATE(2026,2,21)))+SUMIFS(SALIDAS!$F:$F,SALIDAS!$U:$U,"COR",SALIDAS!$A:$A,">="&DATE(2026,2,15),SALIDAS!$A:$A,"<="&MIN(TODAY(),DATE(2026,2,21)))+SUMIFS(SALIDAS!$F:$F,SALIDAS!$U:$U,"OPEX",SALIDAS!$A:$A,">="&DATE(2026,2,15),SALIDAS!$A:$A,"<="&MIN(TODAY(),DATE(2026,2,21))) -> 2016.6691 | F73: =SUMIFS(INGRESOS!$J:$J,INGRESOS!$A:$A,">="&DATE(2026,2,22),INGRESOS!$A:$A,"<="&MIN(TODAY(),DATE(2026,2,28)))+SUMIFS(SALIDAS!$F:$F,SALIDAS!$U:$U,"COR",SALIDAS!$A:$A,">="&DATE(2026,2,22),SALIDAS!$A:$A,"<="&MIN(TODAY(),DATE(2026,2,28)))+SUMIFS(SALIDAS!$F:$F,SALIDAS!$U:$U,"OPEX",SALIDAS!$A:$A,">="&DATE(2026,2,22),SALIDAS!$A:$A,"<="&MIN(TODAY(),DATE(2026,2,28))) -> -41368.993 | G73: =SUM(C73:F73) -> -6748.5793 | H73: =IF(G73>=0,1,0) -> 0 | I73: =IF(G73>=0,"✓","✗") -> ✗
A74: TOTAL OPEX | B74: Control | C74: =SUMIFS(SALIDAS!$F:$F,SALIDAS!$U:$U,"OPEX",SALIDAS!$A:$A,">="&DATE(2026,2,1),SALIDAS!$A:$A,"<="&MIN(TODAY(),DATE(2026,2,7))) -> -23699.284 | D74: =SUMIFS(SALIDAS!$F:$F,SALIDAS!$U:$U,"OPEX",SALIDAS!$A:$A,">="&DATE(2026,2,8),SALIDAS!$A:$A,"<="&MIN(TODAY(),DATE(2026,2,14))) -> -2591.1649 | E74: =SUMIFS(SALIDAS!$F:$F,SALIDAS!$U:$U,"OPEX",SALIDAS!$A:$A,">="&DATE(2026,2,15),SALIDAS!$A:$A,"<="&MIN(TODAY(),DATE(2026,2,21))) -> -16958.441 | F74: =SUMIFS(SALIDAS!$F:$F,SALIDAS!$U:$U,"OPEX",SALIDAS!$A:$A,">="&DATE(2026,2,22),SALIDAS!$A:$A,"<="&MIN(TODAY(),DATE(2026,2,28))) -> -69676.105 | G74: =SUM(C74:F74) -> -112924.99 | H74: - | I74: -
A75: Sales & Marketing | C75: =SUMIFS(SALIDAS!$F:$F,SALIDAS!$U:$U,"OPEX",SALIDAS!V:V,KPIs!A75,SALIDAS!$A:$A,">="&DATE(2026,2,1),SALIDAS!$A:$A,"<="&MIN(TODAY(),DATE(2026,2,7))) -> -16188.303 | D75: =SUMIFS(SALIDAS!$F:$F,SALIDAS!$U:$U,"OPEX",SALIDAS!V:V,KPIs!A75,SALIDAS!$A:$A,">="&DATE(2026,2,8),SALIDAS!$A:$A,"<="&MIN(TODAY(),DATE(2026,2,14))) -> -840.3349 | E75: =SUMIFS(SALIDAS!$F:$F,SALIDAS!$U:$U,"OPEX",SALIDAS!V:V,KPIs!A75,SALIDAS!$A:$A,">="&DATE(2026,2,15),SALIDAS!$A:$A,"<="&MIN(TODAY(),DATE(2026,2,21))) -> -624.51254 | F75: =SUMIFS(SALIDAS!$F:$F,SALIDAS!$U:$U,"OPEX",SALIDAS!V:V,KPIs!A75,SALIDAS!$A:$A,">="&DATE(2026,2,22),SALIDAS!$A:$A,"<="&MIN(TODAY(),DATE(2026,2,28))) -> -35433.867 | G75: =SUM(C75:F75) -> -53087.017
A76: Research & Development | C76: =SUMIFS(SALIDAS!$F:$F,SALIDAS!$U:$U,"OPEX",SALIDAS!V:V,A76,SALIDAS!$A:$A,">="&DATE(2026,2,1),SALIDAS!$A:$A,"<="&MIN(TODAY(),DATE(2026,2,7))) -> -325.62904 | D76: =SUMIFS(SALIDAS!$F:$F,SALIDAS!$U:$U,"OPEX",SALIDAS!V:V,KPIs!A76,SALIDAS!$A:$A,">="&DATE(2026,2,8),SALIDAS!$A:$A,"<="&MIN(TODAY(),DATE(2026,2,14))) -> 0 | E76: =SUMIFS(SALIDAS!$F:$F,SALIDAS!$U:$U,"OPEX",SALIDAS!V:V,KPIs!A76,SALIDAS!$A:$A,">="&DATE(2026,2,15),SALIDAS!$A:$A,"<="&MIN(TODAY(),DATE(2026,2,21))) -> -276.7997 | F76: =SUMIFS(SALIDAS!$F:$F,SALIDAS!$U:$U,"OPEX",SALIDAS!V:V,KPIs!A76,SALIDAS!$A:$A,">="&DATE(2026,2,22),SALIDAS!$A:$A,"<="&MIN(TODAY(),DATE(2026,2,28))) -> -299.71314 | G76: =SUM(C76:F76) -> -902.14188
A77: General & Administrative | C77: =SUMIFS(SALIDAS!$F:$F,SALIDAS!$U:$U,"OPEX",SALIDAS!V:V,A77,SALIDAS!$A:$A,">="&DATE(2026,2,1),SALIDAS!$A:$A,"<="&MIN(TODAY(),DATE(2026,2,7))) -> -7185.3522 | D77: =SUMIFS(SALIDAS!$F:$F,SALIDAS!$U:$U,"OPEX",SALIDAS!V:V,KPIs!A77,SALIDAS!$A:$A,">="&DATE(2026,2,8),SALIDAS!$A:$A,"<="&MIN(TODAY(),DATE(2026,2,14))) -> -370.86 | E77: =SUMIFS(SALIDAS!$F:$F,SALIDAS!$U:$U,"OPEX",SALIDAS!V:V,KPIs!A77,SALIDAS!$A:$A,">="&DATE(2026,2,15),SALIDAS!$A:$A,"<="&MIN(TODAY(),DATE(2026,2,21))) -> -5377.8586 | F77: =SUMIFS(SALIDAS!$F:$F,SALIDAS!$U:$U,"OPEX",SALIDAS!V:V,KPIs!A77,SALIDAS!$A:$A,">="&DATE(2026,2,22),SALIDAS!$A:$A,"<="&MIN(TODAY(),DATE(2026,2,28))) -> -33942.525 | G77: =SUM(C77:F77) -> -46876.596
A78: Customer Success | C78: =SUMIFS(SALIDAS!$F:$F,SALIDAS!$U:$U,"OPEX",SALIDAS!V:V,A78,SALIDAS!$A:$A,">="&DATE(2026,2,1),SALIDAS!$A:$A,"<="&MIN(TODAY(),DATE(2026,2,7))) -> 0 | D78: =SUMIFS(SALIDAS!$F:$F,SALIDAS!$U:$U,"OPEX",SALIDAS!V:V,KPIs!A78,SALIDAS!$A:$A,">="&DATE(2026,2,8),SALIDAS!$A:$A,"<="&MIN(TODAY(),DATE(2026,2,14))) -> -1379.97 | E78: =SUMIFS(SALIDAS!$F:$F,SALIDAS!$U:$U,"OPEX",SALIDAS!V:V,KPIs!A78,SALIDAS!$A:$A,">="&DATE(2026,2,15),SALIDAS!$A:$A,"<="&MIN(TODAY(),DATE(2026,2,21))) -> -10679.27 | F78: =SUMIFS(SALIDAS!$F:$F,SALIDAS!$U:$U,"OPEX",SALIDAS!V:V,KPIs!A78,SALIDAS!$A:$A,">="&DATE(2026,2,22),SALIDAS!$A:$A,"<="&MIN(TODAY(),DATE(2026,2,28))) -> 0 | G78: =SUM(C78:F78) -> -12059.24
A80: 4. GASTOS Y SAAS | B80: Responsable: Giovanny Bravo
A81: KPI | B81: META | C81: SEM 1 | D81: SEM 2 | E81: SEM 3 | F81: SEM 4 | G81: ACUMULADO | H81: % AVANCE | I81: ESTADO
A82: Total Gastos | B82: Control | C82: =-SUMIFS(SALIDAS!$F:$F, SALIDAS!$A:$A, ">=" & DATE(2026,2,1), SALIDAS!$A:$A, "<=" & DATE(2026,2,7)) -> 25401.592 | D82: =-SUMIFS(SALIDAS!$F:$F, SALIDAS!$A:$A, ">=" & DATE(2026,2,8), SALIDAS!$A:$A, "<=" & DATE(2026,2,14)) -> 4391.1649 | E82: =-SUMIFS(SALIDAS!$F:$F, SALIDAS!$A:$A, ">=" & DATE(2026,2,15), SALIDAS!$A:$A, "<=" & DATE(2026,2,21)) -> 17226.471 | F82: =-SUMIFS(SALIDAS!$F:$F, SALIDAS!$A:$A, ">=" & DATE(2026,2,22), SALIDAS!$A:$A, "<=" & DATE(2026,2,28)) -> 71722.721 | G82: =SUM(C82:F82) -> 118741.95 | H82: - | I82: -
A83: SaaS Mensual | B83: ≤€26,000 | C83: =-SUMIFS(SALIDAS!$F:$F,SALIDAS!$K:$K,"SaaS",SALIDAS!$A:$A,">="&DATE(2026,2,1),SALIDAS!$A:$A,"<="&DATE(2026,2,7)) -> 1685.8918 | D83: =-SUMIFS(SALIDAS!$F:$F,SALIDAS!$K:$K,"SaaS",SALIDAS!$A:$A,">="&DATE(2026,2,8),SALIDAS!$A:$A,"<="&DATE(2026,2,14)) -> 4326.9049 | E83: =-SUMIFS(SALIDAS!$F:$F,SALIDAS!$K:$K,"SaaS",SALIDAS!$A:$A,">="&DATE(2026,2,15),SALIDAS!$A:$A,"<="&DATE(2026,2,21)) -> 2654.158 | F83: =-SUMIFS(SALIDAS!$F:$F,SALIDAS!$K:$K,"SaaS",SALIDAS!$A:$A,">="&DATE(2026,2,22),SALIDAS!$A:$A,"<="&DATE(2026,2,28)) -> 8071.717 | G83: =SUM(C83:F83) -> 16738.672 | H83: =G83/26000 -> 0.64379506 | I83: =IF(G83<=26000,"✓","✗") -> ✓
A84: Utilización SaaS | B84: Proximamente
A86: 5. FLUJO DE CAJA Y RUNWAY | B86: Responsable: Sebastián Arellano / Giovanny Bravo
A87: KPI | B87: META | C87: SEM 1 | D87: SEM 2 | E87: SEM 3 | F87: SEM 4 | G87: ACUMULADO | H87: % AVANCE | I87: ESTADO
A88: Flujo Proyectado | C88: 44659.404 | D88: 17737.098 | E88: 19243.14 | F88: 30353.728 | G88: =SUM(C88:F88) -> 111993.37
A89: Flujo Caja Neto | C89: =C69-C82 -> 19257.812 | D89: =D69-D82 -> 13345.933 | E89: =E69-E82 -> 2016.6691 | F89: =F69-F82 -> -41368.993 | G89: =SUM(C89:F89) -> -6748.5793
A90: Caja Neta Acumulada | C90: =C89 -> 19257.812 | D90: =C90+D89 -> 32603.744 | E90: =D90+E89 -> 34620.414 | F90: =E90+F89 -> -6748.5793 | G90: =+F90+G44 -> -1094.1573
A91: Runway Proyectado | C91: - | D91: - | E91: - | F91: - | G91: (+caja neta acumulada enero)
A93: SEGUIMIENTO SEMANAL DE KPIs - MARZO 2026
A95: 1. CAJA Y COBRANZA | B95: Responsable: Sebastián Arellano
A96: KPI | B96: META | C96: SEM 1 | D96: SEM 2 | E96: SEM 3 | F96: SEM 4 | G96: ACUMULADO | H96: % AVANCE | I96: ESTADO
A97: Ratio Cobranza | B97: ≥90% | C97: =SUMIFS('CALENDARIO INGRESOS'!$I:$I,'CALENDARIO INGRESOS'!$L:$L,"PAGADA",'CALENDARIO INGRESOS'!$G:$G,">="&DATE(2026,3,1),'CALENDARIO INGRESOS'!$G:$G,"<="&DATE(2026,3,7))/SUMIFS('CALENDARIO INGRESOS'!$I:$I,'CALENDARIO INGRESOS'!$G:$G,">="&DATE(2026,3,1),'CALENDARIO INGRESOS'!$G:$G,"<="&TODAY()) -> 0.93496982 | D97: =SUMIFS('CALENDARIO INGRESOS'!$I:$I,'CALENDARIO INGRESOS'!$L:$L,"PAGADA",'CALENDARIO INGRESOS'!$G:$G,">="&DATE(2026,3,8),'CALENDARIO INGRESOS'!$G:$G,"<="&DATE(2026,3,14))/SUMIFS('CALENDARIO INGRESOS'!$I:$I,'CALENDARIO INGRESOS'!$G:$G,">="&DATE(2026,3,8),'CALENDARIO INGRESOS'!$G:$G,"<="&DATE(2026,3,14)) -> 0.13361839 | E97: =SUMIFS('CALENDARIO INGRESOS'!$I:$I,'CALENDARIO INGRESOS'!$L:$L,"PAGADA",'CALENDARIO INGRESOS'!$G:$G,">="&DATE(2026,3,15),'CALENDARIO INGRESOS'!$G:$G,"<="&DATE(2026,3,21))/SUMIFS('CALENDARIO INGRESOS'!$I:$I,'CALENDARIO INGRESOS'!$G:$G,">="&DATE(2026,3,15),'CALENDARIO INGRESOS'!$G:$G,"<="&DATE(2026,3,21)) -> 0 | F97: =SUMIFS('CALENDARIO INGRESOS'!$I:$I,'CALENDARIO INGRESOS'!$L:$L,"PAGADA",'CALENDARIO INGRESOS'!$G:$G,">="&DATE(2026,3,22),'CALENDARIO INGRESOS'!$G:$G,"<="&DATE(2026,3,31))/SUMIFS('CALENDARIO INGRESOS'!$I:$I,'CALENDARIO INGRESOS'!$G:$G,">="&DATE(2026,3,22),'CALENDARIO INGRESOS'!$G:$G,"<="&DATE(2026,3,31)) -> 0 | G97: =SUMIFS('CALENDARIO INGRESOS'!$I:$I,'CALENDARIO INGRESOS'!$L:$L,"PAGADA",'CALENDARIO INGRESOS'!$G:$G,">="&DATE(2026,3,1),'CALENDARIO INGRESOS'!$G:$G,"<="&DATE(2026,3,31))/SUMIFS('CALENDARIO INGRESOS'!$I:$I,'CALENDARIO INGRESOS'!$G:$G,">="&DATE(2026,3,1),'CALENDARIO INGRESOS'!$G:$G,"<="&TODAY()) -> 0.96293979 | H97: - | I97: =IF(G97>=0.9,"✓","✗") -> ✓
A98: Cobranza Bruta | B98: ≥€120,000 | C98: =SUMIFS(INGRESOS!$G:$G,INGRESOS!$A:$A,">="&DATE(2026,3,1),INGRESOS!$A:$A,"<="&DATE(2026,3,7)) -> 38328.919 | D98: =SUMIFS(INGRESOS!$G:$G,INGRESOS!$A:$A,">="&DATE(2026,3,8),INGRESOS!$A:$A,"<="&DATE(2026,3,14)) -> 0 | E98: =SUMIFS(INGRESOS!$G:$G,INGRESOS!$A:$A,">="&DATE(2026,3,15),INGRESOS!$A:$A,"<="&DATE(2026,3,21)) -> 0 | F98: =SUMIFS(INGRESOS!$G:$G,INGRESOS!$A:$A,">="&DATE(2026,3,22),INGRESOS!$A:$A,"<="&DATE(2026,3,31)) -> 0 | G98: =SUMIFS(INGRESOS!$G:$G,INGRESOS!$A:$A,">="&DATE(2026,3,1),INGRESOS!$A:$A,"<="&DATE(2026,3,31)) -> 38328.919 | H98: =G98/120000 -> 0.31940766 | I98: =IF(G98>=120000,"✓","✗") -> ✗
A99: Cobros pendientes | C99: =SUMIFS('CALENDARIO INGRESOS'!$I:$I,'CALENDARIO INGRESOS'!$D:$D,"OK",'CALENDARIO INGRESOS'!$L:$L,"<>PAGADA",'CALENDARIO INGRESOS'!$G:$G,">="&DATE(2026,3,1),'CALENDARIO INGRESOS'!$G:$G,"<="&DATE(2026,3,7)) -> 1700 | D99: =SUMIFS('CALENDARIO INGRESOS'!$I:$I,'CALENDARIO INGRESOS'!$D:$D,"OK",'CALENDARIO INGRESOS'!$L:$L,"<>PAGADA",'CALENDARIO INGRESOS'!$G:$G,">="&DATE(2026,3,8),'CALENDARIO INGRESOS'!$G:$G,"<="&DATE(2026,3,14)) -> 6484 | E99: =SUMIFS('CALENDARIO INGRESOS'!$I:$I,'CALENDARIO INGRESOS'!$D:$D,"OK",'CALENDARIO INGRESOS'!$L:$L,"<>PAGADA",'CALENDARIO INGRESOS'!$G:$G,">="&DATE(2026,3,15),'CALENDARIO INGRESOS'!$G:$G,"<="&DATE(2026,3,21)) -> 18478 | F99: =SUMIFS('CALENDARIO INGRESOS'!$I:$I,'CALENDARIO INGRESOS'!$D:$D,"OK",'CALENDARIO INGRESOS'!$L:$L,"<>PAGADA",'CALENDARIO INGRESOS'!$G:$G,">="&DATE(2026,3,22),'CALENDARIO INGRESOS'!$G:$G,"<="&DATE(2026,3,31)) -> 31078 | G99: =SUMIFS('CALENDARIO INGRESOS'!$I:$I,'CALENDARIO INGRESOS'!$D:$D,"OK",'CALENDARIO INGRESOS'!$L:$L,"<>PAGADA",'CALENDARIO INGRESOS'!$G:$G,">="&DATE(2026,3,1),'CALENDARIO INGRESOS'!$G:$G,"<="&DATE(2026,3,31)) -> 57740
A100: Incobrable | C100: =SUMIFS('CALENDARIO INGRESOS'!$I:$I,'CALENDARIO INGRESOS'!$D:$D,"ELIMINADO",'CALENDARIO INGRESOS'!$L:$L,"<>PAGADA",'CALENDARIO INGRESOS'!$G:$G,">="&DATE(2026,3,1),'CALENDARIO INGRESOS'!$G:$G,"<="&DATE(2026,3,7)) -> 0 | D100: =SUMIFS('CALENDARIO INGRESOS'!$I:$I,'CALENDARIO INGRESOS'!$D:$D,"ELIMINADO",'CALENDARIO INGRESOS'!$L:$L,"<>PAGADA",'CALENDARIO INGRESOS'!$G:$G,">="&DATE(2026,3,8),'CALENDARIO INGRESOS'!$G:$G,"<="&DATE(2026,3,14)) -> 0 | E100: =SUMIFS('CALENDARIO INGRESOS'!$I:$I,'CALENDARIO INGRESOS'!$D:$D,"ELIMINADO",'CALENDARIO INGRESOS'!$L:$L,"<>PAGADA",'CALENDARIO INGRESOS'!$G:$G,">="&DATE(2026,3,15),'CALENDARIO INGRESOS'!$G:$G,"<="&DATE(2026,3,21)) -> 0 | F100: =SUMIFS('CALENDARIO INGRESOS'!$I:$I,'CALENDARIO INGRESOS'!$D:$D,"ELIMINADO",'CALENDARIO INGRESOS'!$L:$L,"<>PAGADA",'CALENDARIO INGRESOS'!$G:$G,">="&DATE(2026,3,22),'CALENDARIO INGRESOS'!$G:$G,"<="&DATE(2026,3,31)) -> 0 | G100: =SUMIFS('CALENDARIO INGRESOS'!$I:$I,'CALENDARIO INGRESOS'!$D:$D,"ELIMINADO",'CALENDARIO INGRESOS'!$L:$L,"<>PAGADA",'CALENDARIO INGRESOS'!$G:$G,">="&DATE(2026,3,1),'CALENDARIO INGRESOS'!$G:$G,"<="&DATE(2026,3,31)) -> 0
A101: Facturas On-Time | B101: ≥95% | C101: =COUNTIFS('CALENDARIO INGRESOS'!$L:$L,"PAGADA",'CALENDARIO INGRESOS'!$M:$M,">=0",'CALENDARIO INGRESOS'!$G:$G,">="&DATE(2026,3,1),'CALENDARIO INGRESOS'!$G:$G,"<="&DATE(2026,3,7))/COUNTIFS('CALENDARIO INGRESOS'!$G:$G,">="&DATE(2026,3,1),'CALENDARIO INGRESOS'!$G:$G,"<="&DATE(2026,3,7)) -> 0.61904762 | D101: =COUNTIFS('CALENDARIO INGRESOS'!$L:$L,"PAGADA",'CALENDARIO INGRESOS'!$M:$M,">=0",'CALENDARIO INGRESOS'!$G:$G,">="&DATE(2026,3,8),'CALENDARIO INGRESOS'!$G:$G,"<="&DATE(2026,3,14))/COUNTIFS('CALENDARIO INGRESOS'!$G:$G,">="&DATE(2026,3,8),'CALENDARIO INGRESOS'!$G:$G,"<="&DATE(2026,3,14)) -> 0.14285714 | E101: =IF(TODAY()>=DATE(2026,3,15),COUNTIFS('CALENDARIO INGRESOS'!$L:$L,"PAGADA",'CALENDARIO INGRESOS'!$M:$M,">=0",'CALENDARIO INGRESOS'!$G:$G,">="&DATE(2026,3,15),'CALENDARIO INGRESOS'!$G:$G,"<="&DATE(2026,3,21))/COUNTIFS('CALENDARIO INGRESOS'!$G:$G,">="&DATE(2026,3,15),'CALENDARIO INGRESOS'!$G:$G,"<="&DATE(2026,3,21)),0) -> 0 | F101: =IF(TODAY()>=DATE(2026,3,22),COUNTIFS('CALENDARIO INGRESOS'!$L:$L,"PAGADA",'CALENDARIO INGRESOS'!$M:$M,">=0",'CALENDARIO INGRESOS'!$G:$G,">="&DATE(2026,3,22),'CALENDARIO INGRESOS'!$G:$G,"<="&DATE(2026,3,31))/COUNTIFS('CALENDARIO INGRESOS'!$G:$G,">="&DATE(2026,3,22),'CALENDARIO INGRESOS'!$G:$G,"<="&DATE(2026,3,31)),0) -> 0 | G101: =COUNTIFS('CALENDARIO INGRESOS'!$L:$L,"PAGADA",'CALENDARIO INGRESOS'!$M:$M,">=0",'CALENDARIO INGRESOS'!$G:$G,">="&DATE(2026,3,1),'CALENDARIO INGRESOS'!$G:$G,"<="&DATE(2026,3,31))/COUNTIFS('CALENDARIO INGRESOS'!$G:$G,">="&DATE(2026,3,1),'CALENDARIO INGRESOS'!$G:$G,"<="&TODAY()) -> 0.64285714 | H101: =G101/0.95 -> 0.67669173 | I101: =IF(G101>=0.95,"✓","✗") -> ✗
A102: Dias de retraso promedio | B102: ≤2/mes | C102: =IFERROR(SUMIFS('CALENDARIO INGRESOS'!M:M,'CALENDARIO INGRESOS'!M:M,"<0",'CALENDARIO INGRESOS'!G:G,">="&DATE(2026,3,1),'CALENDARIO INGRESOS'!G:G,"<="&DATE(2026,3,7))/COUNTIFS('CALENDARIO INGRESOS'!M:M,"<0",'CALENDARIO INGRESOS'!G:G,">="&DATE(2026,3,1),'CALENDARIO INGRESOS'!G:G,"<="&DATE(2026,3,7)),0) -> -1.6153846 | D102: =IFERROR(SUMIFS('CALENDARIO INGRESOS'!M:M,'CALENDARIO INGRESOS'!M:M,"<0",'CALENDARIO INGRESOS'!G:G,">="&DATE(2026,3,8),'CALENDARIO INGRESOS'!G:G,"<="&DATE(2026,3,14))/COUNTIFS('CALENDARIO INGRESOS'!M:M,"<0",'CALENDARIO INGRESOS'!G:G,">="&DATE(2026,3,8),'CALENDARIO INGRESOS'!G:G,"<="&DATE(2026,3,14)),0) -> 0 | E102: =IFERROR(SUMIFS('CALENDARIO INGRESOS'!M:M,'CALENDARIO INGRESOS'!M:M,"<0",'CALENDARIO INGRESOS'!G:G,">="&DATE(2026,3,15),'CALENDARIO INGRESOS'!G:G,"<="&DATE(2026,3,21))/COUNTIFS('CALENDARIO INGRESOS'!M:M,"<0",'CALENDARIO INGRESOS'!G:G,">="&DATE(2026,3,15),'CALENDARIO INGRESOS'!G:G,"<="&DATE(2026,3,21)),0) -> 0 | F102: =IFERROR(SUMIFS('CALENDARIO INGRESOS'!M:M,'CALENDARIO INGRESOS'!M:M,"<0",'CALENDARIO INGRESOS'!G:G,">="&DATE(2026,3,22),'CALENDARIO INGRESOS'!G:G,"<="&DATE(2026,3,31))/COUNTIFS('CALENDARIO INGRESOS'!M:M,"<0",'CALENDARIO INGRESOS'!G:G,">="&DATE(2026,3,22),'CALENDARIO INGRESOS'!G:G,"<="&DATE(2026,3,31)),0) -> 0 | G102: =IFERROR(SUMIFS('CALENDARIO INGRESOS'!M:M,'CALENDARIO INGRESOS'!M:M,"<0",'CALENDARIO INGRESOS'!G:G,">="&DATE(2026,3,1),'CALENDARIO INGRESOS'!G:G,"<="&DATE(2026,3,31))/COUNTIFS('CALENDARIO INGRESOS'!M:M,"<0",'CALENDARIO INGRESOS'!G:G,">="&DATE(2026,3,1),'CALENDARIO INGRESOS'!G:G,"<="&DATE(2026,3,31)),0) -> -1.6153846 | I102: =IF(G102>=-2,"✓","✗") -> ✓
A103: AR > 15 días | B103: ≤15% | C103: =COUNTIFS('CALENDARIO INGRESOS'!$M:$M,">15",'CALENDARIO INGRESOS'!$G:$G,">="&DATE(2026,3,1),'CALENDARIO INGRESOS'!$G:$G,"<="&DATE(2026,3,7))/COUNTIFS('CALENDARIO INGRESOS'!$G:$G,">="&DATE(2026,3,1),'CALENDARIO INGRESOS'!$G:$G,"<="&DATE(2026,3,7)) -> 0 | D103: =COUNTIFS('CALENDARIO INGRESOS'!$M:$M,">15",'CALENDARIO INGRESOS'!$G:$G,">="&DATE(2026,3,8),'CALENDARIO INGRESOS'!$G:$G,"<="&DATE(2026,3,14))/COUNTIFS('CALENDARIO INGRESOS'!$G:$G,">="&DATE(2026,3,8),'CALENDARIO INGRESOS'!$G:$G,"<="&DATE(2026,3,14)) -> 0 | E103: =COUNTIFS('CALENDARIO INGRESOS'!$M:$M,">15",'CALENDARIO INGRESOS'!$G:$G,">="&DATE(2026,3,15),'CALENDARIO INGRESOS'!$G:$G,"<="&DATE(2026,3,21))/COUNTIFS('CALENDARIO INGRESOS'!$G:$G,">="&DATE(2026,3,15),'CALENDARIO INGRESOS'!$G:$G,"<="&DATE(2026,3,21)) -> 0 | F103: =COUNTIFS('CALENDARIO INGRESOS'!$M:$M,">15",'CALENDARIO INGRESOS'!$G:$G,">="&DATE(2026,3,22),'CALENDARIO INGRESOS'!$G:$G,"<="&DATE(2026,3,31))/COUNTIFS('CALENDARIO INGRESOS'!$G:$G,">="&DATE(2026,3,22),'CALENDARIO INGRESOS'!$G:$G,"<="&DATE(2026,3,31)) -> 0 | G103: =COUNTIFS('CALENDARIO INGRESOS'!$M:$M,">15",'CALENDARIO INGRESOS'!$G:$G,">="&DATE(2026,3,1),'CALENDARIO INGRESOS'!$G:$G,"<="&DATE(2026,3,28))/COUNTIFS('CALENDARIO INGRESOS'!$G:$G,">="&DATE(2026,3,1),'CALENDARIO INGRESOS'!$G:$G,"<="&DATE(2026,3,31)) -> 0 | H103: - | I103: =IF(G103<=0.15,"✓","✗") -> ✓
A105: 2. CLIENTES | B105: Responsable: Sebastián Arellano
A106: KPI | B106: META | C106: SEM 1 | D106: SEM 2 | E106: SEM 3 | F106: SEM 4 | G106: ACUMULADO | H106: % AVANCE | I106: ESTADO
A107: Clientes Activos | B107: ≥140 | C107: =IF(TODAY()>=DATE(2026,3,1),COUNTIFS('RESUMEN CLIENTES'!G:G,"<="&DATE(2026,3,7),'RESUMEN CLIENTES'!M:M,"OK")+COUNTIFS('RESUMEN CLIENTES'!G:G,"<="&DATE(2026,3,7),'RESUMEN CLIENTES'!M:M,"¡REGULARIZAR!")+COUNTIFS('RESUMEN CLIENTES'!G:G,"<="&DATE(2026,3,7),'RESUMEN CLIENTES'!M:M,"EVALUACION"),0) -> 148 | D107: =IF(TODAY()>=DATE(2026,3,8),COUNTIFS('RESUMEN CLIENTES'!G:G,"<="&DATE(2026,3,14),'RESUMEN CLIENTES'!M:M,"OK")+COUNTIFS('RESUMEN CLIENTES'!G:G,"<="&DATE(2026,3,14),'RESUMEN CLIENTES'!M:M,"¡REGULARIZAR!")+COUNTIFS('RESUMEN CLIENTES'!G:G,"<="&DATE(2026,3,14),'RESUMEN CLIENTES'!M:M,"EVALUACION"),0) -> 0 | E107: =IF(TODAY()>=DATE(2026,3,15),COUNTIFS('RESUMEN CLIENTES'!G:G,"<="&DATE(2026,3,21),'RESUMEN CLIENTES'!M:M,"OK")+COUNTIFS('RESUMEN CLIENTES'!G:G,"<="&DATE(2026,3,21),'RESUMEN CLIENTES'!M:M,"¡REGULARIZAR!")+COUNTIFS('RESUMEN CLIENTES'!G:G,"<="&DATE(2026,3,21),'RESUMEN CLIENTES'!M:M,"EVALUACION"),0) -> 0 | F107: =IF(TODAY()>=DATE(2026,3,22),COUNTIFS('RESUMEN CLIENTES'!G:G,"<="&DATE(2026,3,31),'RESUMEN CLIENTES'!M:M,"OK")+COUNTIFS('RESUMEN CLIENTES'!G:G,"<="&DATE(2026,3,31),'RESUMEN CLIENTES'!M:M,"¡REGULARIZAR!")+COUNTIFS('RESUMEN CLIENTES'!G:G,"<="&DATE(2026,3,31),'RESUMEN CLIENTES'!M:M,"EVALUACION"),0) -> 0 | G107: =COUNTIFS('RESUMEN CLIENTES'!G:G,"<="&DATE(2026,3,31),'RESUMEN CLIENTES'!M:M,"OK")+COUNTIFS('RESUMEN CLIENTES'!G:G,"<="&DATE(2026,3,31),'RESUMEN CLIENTES'!M:M,"¡REGULARIZAR!")+COUNTIFS('RESUMEN CLIENTES'!G:G,"<="&DATE(2026,3,31),'RESUMEN CLIENTES'!M:M,"EVALUACION") -> 148 | H107: - | I107: =IF(G107>=140,"✓","✗") -> ✓
A108: Nuevos Clientes | B108: ≥20/mes | C108: =COUNTIFS('RESUMEN CLIENTES'!$G:$G,">="&DATE(2026,3,1),'RESUMEN CLIENTES'!$G:$G,"<="&DATE(2026,3,7)) -> 4 | D108: =COUNTIFS('RESUMEN CLIENTES'!$G:$G,">="&DATE(2026,3,8),'RESUMEN CLIENTES'!$G:$G,"<="&DATE(2026,3,14)) -> 0 | E108: =COUNTIFS('RESUMEN CLIENTES'!$G:$G,">="&DATE(2026,3,15),'RESUMEN CLIENTES'!$G:$G,"<="&DATE(2026,3,21)) -> 0 | F108: =COUNTIFS('RESUMEN CLIENTES'!$G:$G,">="&DATE(2026,3,22),'RESUMEN CLIENTES'!$G:$G,"<="&DATE(2026,3,31)) -> 0 | G108: =COUNTIFS('RESUMEN CLIENTES'!$G:$G,">="&DATE(2026,3,1),'RESUMEN CLIENTES'!$G:$G,"<="&DATE(2026,3,31)) -> 4 | H108: =G108/20 -> 0.2 | I108: =IF(G108>=20,"✓","✗") -> ✗
A109: Tasa Abandono | B109: ≤5% | C109: =(COUNTIFS('RESUMEN CLIENTES'!J:J,">="&DATE(2026,3,1),'RESUMEN CLIENTES'!J:J,"<="&DATE(2026,3,7),'RESUMEN CLIENTES'!M:M,"ELIMINADO")+COUNTIFS('RESUMEN CLIENTES'!J:J,">="&DATE(2026,3,1),'RESUMEN CLIENTES'!J:J,"<="&DATE(2026,3,7),'RESUMEN CLIENTES'!M:M,"SUSPENDIDO")+COUNTIFS('RESUMEN CLIENTES'!J:J,">="&DATE(2026,3,1),'RESUMEN CLIENTES'!J:J,"<="&DATE(2026,3,7),'RESUMEN CLIENTES'!M:M,"EN PAUSA"))/C107 -> 0 | D109: =IFERROR((COUNTIFS('RESUMEN CLIENTES'!J:J,">="&DATE(2026,3,8),'RESUMEN CLIENTES'!J:J,"<="&DATE(2026,3,14),'RESUMEN CLIENTES'!M:M,"ELIMINADO")+COUNTIFS('RESUMEN CLIENTES'!J:J,">="&DATE(2026,3,8),'RESUMEN CLIENTES'!J:J,"<="&DATE(2026,3,14),'RESUMEN CLIENTES'!M:M,"SUSPENDIDO")+COUNTIFS('RESUMEN CLIENTES'!J:J,">="&DATE(2026,3,8),'RESUMEN CLIENTES'!J:J,"<="&DATE(2026,3,14),'RESUMEN CLIENTES'!M:M,"EN PAUSA"))/D107,0) -> 0 | E109: =IFERROR((COUNTIFS('RESUMEN CLIENTES'!J:J,">="&DATE(2026,3,15),'RESUMEN CLIENTES'!J:J,"<="&DATE(2026,3,21),'RESUMEN CLIENTES'!M:M,"ELIMINADO")+COUNTIFS('RESUMEN CLIENTES'!J:J,">="&DATE(2026,3,15),'RESUMEN CLIENTES'!J:J,"<="&DATE(2026,3,21),'RESUMEN CLIENTES'!M:M,"SUSPENDIDO")+COUNTIFS('RESUMEN CLIENTES'!J:J,">="&DATE(2026,3,15),'RESUMEN CLIENTES'!J:J,"<="&DATE(2026,3,21),'RESUMEN CLIENTES'!M:M,"EN PAUSA"))/E107,0) -> 0 | F109: =IFERROR((COUNTIFS('RESUMEN CLIENTES'!J:J,">="&DATE(2026,3,22),'RESUMEN CLIENTES'!J:J,"<="&DATE(2026,3,31),'RESUMEN CLIENTES'!M:M,"ELIMINADO")+COUNTIFS('RESUMEN CLIENTES'!J:J,">="&DATE(2026,3,22),'RESUMEN CLIENTES'!J:J,"<="&DATE(2026,3,31),'RESUMEN CLIENTES'!M:M,"SUSPENDIDO")+COUNTIFS('RESUMEN CLIENTES'!J:J,">="&DATE(2026,3,22),'RESUMEN CLIENTES'!J:J,"<="&DATE(2026,3,31),'RESUMEN CLIENTES'!M:M,"EN PAUSA"))/F107,0) -> 0 | G109: =(COUNTIFS('RESUMEN CLIENTES'!J:J,">="&DATE(2026,3,1),'RESUMEN CLIENTES'!J:J,"<="&DATE(2026,3,31),'RESUMEN CLIENTES'!M:M,"ELIMINADO")+COUNTIFS('RESUMEN CLIENTES'!J:J,">="&DATE(2026,3,1),'RESUMEN CLIENTES'!J:J,"<="&DATE(2026,3,31),'RESUMEN CLIENTES'!M:M,"SUSPENDIDO")+COUNTIFS('RESUMEN CLIENTES'!J:J,">="&DATE(2026,3,1),'RESUMEN CLIENTES'!J:J,"<="&DATE(2026,3,31),'RESUMEN CLIENTES'!M:M,"EN PAUSA"))/G107 -> 0 | H109: - | I109: =IF(G109<=0.05,"✓","✗") -> ✓
A110: Clientes OK | B110: ≥90% | C110: =COUNTIFS('RESUMEN CLIENTES'!$G:$G,"<="&DATE(2026,3,7),'RESUMEN CLIENTES'!$M:$M,"OK")/C107 -> 0.90540541 | D110: =IFERROR(COUNTIFS('RESUMEN CLIENTES'!$G:$G,"<="&DATE(2026,3,14),'RESUMEN CLIENTES'!$M:$M,"OK")/D107,0) -> 0 | E110: =IFERROR(COUNTIFS('RESUMEN CLIENTES'!$G:$G,"<="&DATE(2026,3,21),'RESUMEN CLIENTES'!$M:$M,"OK")/E107,0) -> 0 | F110: =IFERROR(COUNTIFS('RESUMEN CLIENTES'!$G:$G,"<="&DATE(2026,3,31),'RESUMEN CLIENTES'!$M:$M,"OK")/F107,0) -> 0 | G110: =IFERROR(COUNTIFS('RESUMEN CLIENTES'!$G:$G,"<="&DATE(2026,3,31),'RESUMEN CLIENTES'!$M:$M,"OK")/G107,0) -> 0.90540541 | H110: =G110/0.9 -> 1.006006 | I110: =IF(G110>=0.9,"✓","✗") -> ✓
A111: % Suscripción Activa | B111: ≥70% | C111: =IF(TODAY()>=DATE(2026,3,1),COUNTIFS('RESUMEN CLIENTES'!$G:$G,"<="&DATE(2026,3,7),'RESUMEN CLIENTES'!$M:$M,"OK",'RESUMEN CLIENTES'!$W:$W,1)/COUNTIFS('RESUMEN CLIENTES'!$G:$G,"<="&DATE(2026,3,7),'RESUMEN CLIENTES'!$M:$M,"OK"),0) -> 0.49253731 | D111: =IF(TODAY()>=DATE(2026,3,8),COUNTIFS('RESUMEN CLIENTES'!$G:$G,"<="&DATE(2026,3,14),'RESUMEN CLIENTES'!$M:$M,"OK",'RESUMEN CLIENTES'!$W:$W,1)/COUNTIFS('RESUMEN CLIENTES'!$G:$G,"<="&DATE(2026,3,14),'RESUMEN CLIENTES'!$M:$M,"OK"),0) -> 0 | E111: =IF(TODAY()>=DATE(2026,3,15),COUNTIFS('RESUMEN CLIENTES'!$G:$G,"<="&DATE(2026,3,21),'RESUMEN CLIENTES'!$M:$M,"OK",'RESUMEN CLIENTES'!$W:$W,1)/COUNTIFS('RESUMEN CLIENTES'!$G:$G,"<="&DATE(2026,3,21),'RESUMEN CLIENTES'!$M:$M,"OK"),0) -> 0 | F111: =IF(TODAY()>=DATE(2026,3,22),COUNTIFS('RESUMEN CLIENTES'!$G:$G,"<="&DATE(2026,3,31),'RESUMEN CLIENTES'!$M:$M,"OK",'RESUMEN CLIENTES'!$W:$W,1)/COUNTIFS('RESUMEN CLIENTES'!$G:$G,"<="&DATE(2026,3,31),'RESUMEN CLIENTES'!$M:$M,"OK"),0) -> 0 | G111: =COUNTIFS('RESUMEN CLIENTES'!$G:$G,"<="&DATE(2026,3,31),'RESUMEN CLIENTES'!$M:$M,"OK",'RESUMEN CLIENTES'!$W:$W,1)/COUNTIFS('RESUMEN CLIENTES'!$G:$G,"<="&DATE(2026,3,31),'RESUMEN CLIENTES'!$M:$M,"OK") -> 0.49253731 | H111: =G111/0.7 -> 0.70362473 | I111: =IF(G111>=0.7,"✓","✗") -> ✗
A113: 3. MÉTRICAS FINANCIERAS | B113: Responsables: José I. Donoso / S. Arellano
A114: KPI | B114: META | C114: SEM 1 | D114: SEM 2 | E114: SEM 3 | F114: SEM 4 | G114: ACUMULADO | H114: % AVANCE | I114: ESTADO
A115: Ingreso Neto | B115: Monitor | C115: =SUMIFS(INGRESOS!$J:$J,INGRESOS!$A:$A,">="&DATE(2026,3,1),INGRESOS!$A:$A,"<="&MIN(TODAY(),DATE(2026,3,7))) -> 37064.052 | D115: =SUMIFS(INGRESOS!$J:$J,INGRESOS!$A:$A,">="&DATE(2026,3,8),INGRESOS!$A:$A,"<="&MIN(TODAY(),DATE(2026,3,14))) -> 0 | E115: =SUMIFS(INGRESOS!$J:$J,INGRESOS!$A:$A,">="&DATE(2026,3,15),INGRESOS!$A:$A,"<="&MIN(TODAY(),DATE(2026,3,21))) -> 0 | F115: =SUMIFS(INGRESOS!$J:$J,INGRESOS!$A:$A,">="&DATE(2026,3,22),INGRESOS!$A:$A,"<="&MIN(TODAY(),DATE(2026,3,31))) -> 0 | G115: =SUM(C115:F115) -> 37064.052 | H115: - | I115: -
...

Sheet EERR
A1: MES | B1: INGRESO TOTAL MES | C1: CRECIMIENTO | D1: INGRESO MES RECIBIDO | E1: Q TRANSACCIONES | F1: RATIO COBRANZA | G1: INGRESO PROGRAMADO PEND. | H1: MONTO PEND RETRASADO | I1: Q PEND RETRASADO | J1: MONTO PEND AL DIA | K1: Q PEND AL DIA | L1: MONTO CASOS X REG. | M1: Q CASOS X REG. | N1: INCOBRABLE | O1: % NO PAGO | P1: % CARGO | Q1: INGRESO MES RECIBIDO NETO | R1: TOTAL SALIDAS MES | S1: COR | T1: MARGEN BRUTO | U1: %MARGEN BRUTO | V1: Sales & Marketing | W1: Research & Development | X1: General & Administrative | Y1: Customer Success | Z1: TOTAL OPEX | AA1: EBITDA | AB1: TOTAL CAPEX | AC1: FCF | AD1: FCF ACUMULADO | AE1: CAC | AF1: COSTO SERVICIO UNIT. | AG1: MARGEN CONTRIBUCION | AH1: CASH IN NETO PROM MES
A2: 45597 | B2: =+Tabla7[[#This Row],[INGRESO MES RECIBIDO]]+Tabla7[[#This Row],[INGRESO PROGRAMADO PEND.]] -> 0 | C2: =IFERROR((Tabla7[[#This Row],[INGRESO TOTAL MES]]/B1)-1,"0") -> 0 | D2: =SUMIFS(INGRESOS!G:G,INGRESOS!A:A,">="&EOMONTH(Tabla7[[#This Row],[MES]],-1)+1,INGRESOS!A:A,"<="&EOMONTH(Tabla7[[#This Row],[MES]],0)) -> 0 | E2: =COUNTIFS(INGRESOS!$A:$A,">="&Tabla7[[#This Row],[MES]],INGRESOS!$A:$A,"<="&MIN(TODAY(),EOMONTH(Tabla7[[#This Row],[MES]],0))) -> 0 | F2: 0 | G2: =SUMIFS('CALENDARIO INGRESOS'!I:I,'CALENDARIO INGRESOS'!G:G,">="&EOMONTH(Tabla7[[#This Row],[MES]],-1)+1,'CALENDARIO INGRESOS'!G:G,"<="&EOMONTH(Tabla7[[#This Row],[MES]],0),'CALENDARIO INGRESOS'!L:L, "<>PAGADA",'CALENDARIO INGRESOS'!D:D,"<>ELIMINADO",'CALENDARIO INGRESOS'!D:D,"<>¡REGULARIZAR!") -> 0 | H2: =SUMIFS('CALENDARIO INGRESOS'!$I:$I, 'CALENDARIO INGRESOS'!$G:$G,">="&EOMONTH(Tabla7[[#This Row],[MES]],-1)+1, 'CALENDARIO INGRESOS'!$G:$G,"<="&EOMONTH(Tabla7[[#This Row],[MES]],0), 'CALENDARIO INGRESOS'!$L:$L,"<>PAGADA", 'CALENDARIO INGRESOS'!$G:$G,"<="&TODAY(),'CALENDARIO INGRESOS'!D:D,"<>¡REGULARIZAR!",'CALENDARIO INGRESOS'!D:D,"<>ELIMINADO") -> 0 | I2: =COUNTIFS('CALENDARIO INGRESOS'!$G:$G,">="&EOMONTH(Tabla7[[#This Row],[MES]],-1)+1,'CALENDARIO INGRESOS'!$G:$G,"<="&EOMONTH(Tabla7[[#This Row],[MES]],0),'CALENDARIO INGRESOS'!$D:$D,"<>ELIMINADO",'CALENDARIO INGRESOS'!$D:$D,"<>¡REGULARIZAR!",'CALENDARIO INGRESOS'!$L:$L,"<>PAGADA",'CALENDARIO INGRESOS'!$G:$G,"<="&TODAY()) -> 0 | J2: =SUMIFS('CALENDARIO INGRESOS'!$I:$I, 'CALENDARIO INGRESOS'!$G:$G,">="&EOMONTH(Tabla7[[#This Row],[MES]],-1)+1, 'CALENDARIO INGRESOS'!$G:$G,"<="&EOMONTH(Tabla7[[#This Row],[MES]],0), 'CALENDARIO INGRESOS'!$L:$L,"<>PAGADA", 'CALENDARIO INGRESOS'!$G:$G,">="&TODAY(),'CALENDARIO INGRESOS'!$D:$D,"<>ELIMINADO",'CALENDARIO INGRESOS'!$D:$D,"<>¡REGULARIZAR!") -> 0 | K2: =COUNTIFS('CALENDARIO INGRESOS'!$G:$G,">="&EOMONTH(Tabla7[[#This Row],[MES]],-1)+1,'CALENDARIO INGRESOS'!$G:$G,"<="&EOMONTH(Tabla7[[#This Row],[MES]],0),'CALENDARIO INGRESOS'!$D:$D,"<>ELIMINADO",'CALENDARIO INGRESOS'!$D:$D,"<>¡REGULARIZAR!",'CALENDARIO INGRESOS'!$L:$L,"<>PAGADA",'CALENDARIO INGRESOS'!$G:$G,">="&TODAY()) -> 0 | L2: =SUMIFS('CALENDARIO INGRESOS'!I:I,'CALENDARIO INGRESOS'!G:G,">="&EOMONTH(Tabla7[[#This Row],[MES]],-1)+1,'CALENDARIO INGRESOS'!G:G,"<="&EOMONTH(Tabla7[[#This Row],[MES]],0),'CALENDARIO INGRESOS'!L:L, "<>PAGADA",'CALENDARIO INGRESOS'!D:D,"¡REGULARIZAR!") -> 0 | M2: =COUNTIFS('CALENDARIO INGRESOS'!$G:$G,">="&EOMONTH(Tabla7[[#This Row],[MES]],-1)+1,'CALENDARIO INGRESOS'!$G:$G,"<="&EOMONTH(Tabla7[[#This Row],[MES]],0),'CALENDARIO INGRESOS'!$D:$D,"¡REGULARIZAR!",'CALENDARIO INGRESOS'!$L:$L,"<>PAGADA") -> 0 | N2: =SUMIFS('CALENDARIO INGRESOS'!I:I,'CALENDARIO INGRESOS'!G:G,">="&EOMONTH(Tabla7[[#This Row],[MES]],-1)+1,'CALENDARIO INGRESOS'!G:G,"<="&EOMONTH(Tabla7[[#This Row],[MES]],0),'CALENDARIO INGRESOS'!L:L, "<>PAGADA",'CALENDARIO INGRESOS'!D:D,"ELIMINADO") -> 0 | O2: =+IFERROR(Tabla7[[#This Row],[INCOBRABLE]]/Tabla7[[#This Row],[INGRESO TOTAL MES]],0) -> 0 | P2: =IFERROR(AVERAGEIFS(INGRESOS!I:I,INGRESOS!A:A,">="&Tabla7[[#This Row],[MES]],INGRESOS!A:A,"<="&MIN(TODAY(),EOMONTH(Tabla7[[#This Row],[MES]],0))),0) -> 0 | Q2: =SUMIFS(INGRESOS!$J:$J,INGRESOS!$A:$A,">="&Tabla7[[#This Row],[MES]],INGRESOS!$A:$A,"<="&MIN(TODAY(),EOMONTH(Tabla7[[#This Row],[MES]],0))) -> 0 | R2: =SUMIFS(SALIDAS!F:F,SALIDAS!A:A,">="&Tabla7[[#This Row],[MES]],SALIDAS!A:A,"<="&MIN(TODAY(),EOMONTH(Tabla7[[#This Row],[MES]],0))) -> -2543.38 | S2: =SUMIFS(SALIDAS!F:F,SALIDAS!U:U,"COR",SALIDAS!A:A,">="&Tabla7[[#This Row],[MES]],SALIDAS!A:A,"<="&MIN(TODAY(),EOMONTH(Tabla7[[#This Row],[MES]],0))) -> -2500 | T2: =Tabla7[[#This Row],[INGRESO MES RECIBIDO NETO]]+Tabla7[[#This Row],[COR]]+Tabla7[[#This Row],[Customer Success]] -> -2500 | U2: =+IFERROR(Tabla7[[#This Row],[MARGEN BRUTO]]/Tabla7[[#This Row],[INGRESO MES RECIBIDO NETO]],"null") -> null | V2: =SUMIFS(SALIDAS!F:F,SALIDAS!U:U,"OPEX",SALIDAS!V:V,Tabla7[[#Headers],[Sales & Marketing]],SALIDAS!A:A,">="&Tabla7[[#This Row],[MES]],SALIDAS!A:A,"<="&MIN(TODAY(),EOMONTH(Tabla7[[#This Row],[MES]],0))) -> -43.38 | W2: =SUMIFS(SALIDAS!F:F,SALIDAS!U:U,"OPEX",SALIDAS!V:V,Tabla7[[#Headers],[Research & Development]],SALIDAS!A:A,">="&Tabla7[[#This Row],[MES]],SALIDAS!A:A,"<="&MIN(TODAY(),EOMONTH(Tabla7[[#This Row],[MES]],0))) -> 0 | X2: =SUMIFS(SALIDAS!F:F,SALIDAS!U:U,"OPEX",SALIDAS!V:V,Tabla7[[#Headers],[General & Administrative]],SALIDAS!A:A,">="&Tabla7[[#This Row],[MES]],SALIDAS!A:A,"<="&MIN(TODAY(),EOMONTH(Tabla7[[#This Row],[MES]],0))) -> 0 | Y2: =SUMIFS(SALIDAS!F:F,SALIDAS!U:U,"OPEX",SALIDAS!V:V,Tabla7[[#Headers],[Customer Success]],SALIDAS!A:A,">="&Tabla7[[#This Row],[MES]],SALIDAS!A:A,"<="&MIN(TODAY(),EOMONTH(Tabla7[[#This Row],[MES]],0))) -> 0 | Z2: =SUMIFS(SALIDAS!F:F,SALIDAS!U:U,"OPEX",SALIDAS!A:A,">="&Tabla7[[#This Row],[MES]],SALIDAS!A:A,"<="&MIN(TODAY(),EOMONTH(Tabla7[[#This Row],[MES]],0))) -> -43.38 | AA2: =+Tabla7[[#This Row],[MARGEN BRUTO]]+SUM(Tabla7[[#This Row],[Sales & Marketing]:[General & Administrative]]) -> -2543.38 | AB2: =ABS(SUMIFS(SALIDAS!F:F,SALIDAS!U:U,"CAPEX",SALIDAS!A:A,">="&Tabla7[[#This Row],[MES]],SALIDAS!A:A,"<="&MIN(TODAY(),EOMONTH(Tabla7[[#This Row],[MES]],0)))) -> 0 | AC2: =+Tabla7[[#This Row],[EBITDA]]-Tabla7[[#This Row],[TOTAL CAPEX]] -> -2543.38 | AD2: =+Tabla7[[#This Row],[FCF]] -> -2543.38 | AE2: =IFERROR(SUMIFS(SALIDAS!F:F,SALIDAS!U:U,"OPEX",SALIDAS!V:V,Tabla7[[#Headers],[Sales & Marketing]],SALIDAS!A:A,">="&Tabla7[[#This Row],[MES]],SALIDAS!A:A,"<="&MIN(TODAY(),EOMONTH(Tabla7[[#This Row],[MES]],0)))/_xlfn.XLOOKUP(Tabla7[[#This Row],[MES]],'COHORTES INGRESO'!A:A,'COHORTES INGRESO'!C:C),0) -> 0 | AF2: =+IFERROR(Tabla7[[#This Row],[COR]]/Tabla711[[#This Row],[NUEVOS CLIENTES TOTAL]],0) -> 0 | AG2: =Tabla7[[#This Row],[INGRESO MES RECIBIDO NETO]]+SUMIFS(SALIDAS!F:F,SALIDAS!T:T,"Costo variable",SALIDAS!A:A,">="&Tabla7[[#This Row],[MES]],SALIDAS!A:A,"<="&MIN(TODAY(),EOMONTH(Tabla7[[#This Row],[MES]],0))) -> -2500 | AH2: =+IFERROR(AVERAGEIFS(INGRESOS!J:J,INGRESOS!$A:$A,">="&Tabla7[[#This Row],[MES]],INGRESOS!$A:$A,"<="&MIN(TODAY(),EOMONTH(Tabla7[[#This Row],[MES]],0))),0) -> 0
A3: 45627 | B3: =+Tabla7[[#This Row],[INGRESO MES RECIBIDO]]+Tabla7[[#This Row],[INGRESO PROGRAMADO PEND.]] -> 0 | C3: =IFERROR((Tabla7[[#This Row],[INGRESO TOTAL MES]]/B2)-1,"0") -> 0 | D3: =SUMIFS(INGRESOS!G:G,INGRESOS!A:A,">="&EOMONTH(Tabla7[[#This Row],[MES]],-1)+1,INGRESOS!A:A,"<="&EOMONTH(Tabla7[[#This Row],[MES]],0)) -> 0 | E3: =COUNTIFS(INGRESOS!$A:$A,">="&Tabla7[[#This Row],[MES]],INGRESOS!$A:$A,"<="&MIN(TODAY(),EOMONTH(Tabla7[[#This Row],[MES]],0))) -> 0 | F3: =SUMIFS('CALENDARIO INGRESOS'!I:I,'CALENDARIO INGRESOS'!G:G,">="&EOMONTH(Tabla7[[#This Row],[MES]],-1)+1,'CALENDARIO INGRESOS'!G:G,"<="&EOMONTH(Tabla7[[#This Row],[MES]],0),'CALENDARIO INGRESOS'!L:L,"PAGADA")/SUMIFS('CALENDARIO INGRESOS'!I:I,'CALENDARIO INGRESOS'!G:G,">="&EOMONTH(Tabla7[[#This Row],[MES]],-1)+1,'CALENDARIO INGRESOS'!G:G,"<="&EOMONTH(Tabla7[[#This Row],[MES]],0)) -> 1 | G3: =SUMIFS('CALENDARIO INGRESOS'!I:I,'CALENDARIO INGRESOS'!G:G,">="&EOMONTH(Tabla7[[#This Row],[MES]],-1)+1,'CALENDARIO INGRESOS'!G:G,"<="&EOMONTH(Tabla7[[#This Row],[MES]],0),'CALENDARIO INGRESOS'!L:L, "<>PAGADA",'CALENDARIO INGRESOS'!D:D,"<>ELIMINADO",'CALENDARIO INGRESOS'!D:D,"<>¡REGULARIZAR!") -> 0 | H3: =SUMIFS('CALENDARIO INGRESOS'!$I:$I, 'CALENDARIO INGRESOS'!$G:$G,">="&EOMONTH(Tabla7[[#This Row],[MES]],-1)+1, 'CALENDARIO INGRESOS'!$G:$G,"<="&EOMONTH(Tabla7[[#This Row],[MES]],0), 'CALENDARIO INGRESOS'!$L:$L,"<>PAGADA", 'CALENDARIO INGRESOS'!$G:$G,"<="&TODAY(),'CALENDARIO INGRESOS'!D:D,"<>¡REGULARIZAR!",'CALENDARIO INGRESOS'!D:D,"<>ELIMINADO") -> 0 | I3: =COUNTIFS('CALENDARIO INGRESOS'!$G:$G,">="&EOMONTH(Tabla7[[#This Row],[MES]],-1)+1,'CALENDARIO INGRESOS'!$G:$G,"<="&EOMONTH(Tabla7[[#This Row],[MES]],0),'CALENDARIO INGRESOS'!$D:$D,"<>ELIMINADO",'CALENDARIO INGRESOS'!$D:$D,"<>¡REGULARIZAR!",'CALENDARIO INGRESOS'!$L:$L,"<>PAGADA",'CALENDARIO INGRESOS'!$G:$G,"<="&TODAY()) -> 0 | J3: =SUMIFS('CALENDARIO INGRESOS'!$I:$I, 'CALENDARIO INGRESOS'!$G:$G,">="&EOMONTH(Tabla7[[#This Row],[MES]],-1)+1, 'CALENDARIO INGRESOS'!$G:$G,"<="&EOMONTH(Tabla7[[#This Row],[MES]],0), 'CALENDARIO INGRESOS'!$L:$L,"<>PAGADA", 'CALENDARIO INGRESOS'!$G:$G,">="&TODAY(),'CALENDARIO INGRESOS'!$D:$D,"<>ELIMINADO",'CALENDARIO INGRESOS'!$D:$D,"<>¡REGULARIZAR!") -> 0 | K3: =COUNTIFS('CALENDARIO INGRESOS'!$G:$G,">="&EOMONTH(Tabla7[[#This Row],[MES]],-1)+1,'CALENDARIO INGRESOS'!$G:$G,"<="&EOMONTH(Tabla7[[#This Row],[MES]],0),'CALENDARIO INGRESOS'!$D:$D,"<>ELIMINADO",'CALENDARIO INGRESOS'!$D:$D,"<>¡REGULARIZAR!",'CALENDARIO INGRESOS'!$L:$L,"<>PAGADA",'CALENDARIO INGRESOS'!$G:$G,">="&TODAY()) -> 0 | L3: =SUMIFS('CALENDARIO INGRESOS'!I:I,'CALENDARIO INGRESOS'!G:G,">="&EOMONTH(Tabla7[[#This Row],[MES]],-1)+1,'CALENDARIO INGRESOS'!G:G,"<="&EOMONTH(Tabla7[[#This Row],[MES]],0),'CALENDARIO INGRESOS'!L:L, "<>PAGADA",'CALENDARIO INGRESOS'!D:D,"¡REGULARIZAR!") -> 0 | M3: =COUNTIFS('CALENDARIO INGRESOS'!$G:$G,">="&EOMONTH(Tabla7[[#This Row],[MES]],-1)+1,'CALENDARIO INGRESOS'!$G:$G,"<="&EOMONTH(Tabla7[[#This Row],[MES]],0),'CALENDARIO INGRESOS'!$D:$D,"¡REGULARIZAR!",'CALENDARIO INGRESOS'!$L:$L,"<>PAGADA") -> 0 | N3: =SUMIFS('CALENDARIO INGRESOS'!I:I,'CALENDARIO INGRESOS'!G:G,">="&EOMONTH(Tabla7[[#This Row],[MES]],-1)+1,'CALENDARIO INGRESOS'!G:G,"<="&EOMONTH(Tabla7[[#This Row],[MES]],0),'CALENDARIO INGRESOS'!L:L, "<>PAGADA",'CALENDARIO INGRESOS'!D:D,"ELIMINADO") -> 0 | O3: =+IFERROR(Tabla7[[#This Row],[INCOBRABLE]]/Tabla7[[#This Row],[INGRESO TOTAL MES]],0) -> 0 | P3: =IFERROR(AVERAGEIFS(INGRESOS!I:I,INGRESOS!A:A,">="&Tabla7[[#This Row],[MES]],INGRESOS!A:A,"<="&MIN(TODAY(),EOMONTH(Tabla7[[#This Row],[MES]],0))),0) -> 0 | Q3: =SUMIFS(INGRESOS!$J:$J,INGRESOS!$A:$A,">="&Tabla7[[#This Row],[MES]],INGRESOS!$A:$A,"<="&MIN(TODAY(),EOMONTH(Tabla7[[#This Row],[MES]],0))) -> 0 | R3: =SUMIFS(SALIDAS!F:F,SALIDAS!A:A,">="&Tabla7[[#This Row],[MES]],SALIDAS!A:A,"<="&MIN(TODAY(),EOMONTH(Tabla7[[#This Row],[MES]],0))) -> -9913.5796 | S3: =SUMIFS(SALIDAS!F:F,SALIDAS!U:U,"COR",SALIDAS!A:A,">="&Tabla7[[#This Row],[MES]],SALIDAS!A:A,"<="&MIN(TODAY(),EOMONTH(Tabla7[[#This Row],[MES]],0))) -> -1500 | T3: =Tabla7[[#This Row],[INGRESO MES RECIBIDO NETO]]+Tabla7[[#This Row],[COR]]+Tabla7[[#This Row],[Customer Success]] -> -1500 | U3: =+IFERROR(Tabla7[[#This Row],[MARGEN BRUTO]]/Tabla7[[#This Row],[INGRESO MES RECIBIDO NETO]],"null") -> null | V3: =SUMIFS(SALIDAS!F:F,SALIDAS!U:U,"OPEX",SALIDAS!V:V,Tabla7[[#Headers],[Sales & Marketing]],SALIDAS!A:A,">="&Tabla7[[#This Row],[MES]],SALIDAS!A:A,"<="&MIN(TODAY(),EOMONTH(Tabla7[[#This Row],[MES]],0))) -> -8067.9296 | W3: =SUMIFS(SALIDAS!F:F,SALIDAS!U:U,"OPEX",SALIDAS!V:V,Tabla7[[#Headers],[Research & Development]],SALIDAS!A:A,">="&Tabla7[[#This Row],[MES]],SALIDAS!A:A,"<="&MIN(TODAY(),EOMONTH(Tabla7[[#This Row],[MES]],0))) -> -239.05 | X3: =SUMIFS(SALIDAS!F:F,SALIDAS!U:U,"OPEX",SALIDAS!V:V,Tabla7[[#Headers],[General & Administrative]],SALIDAS!A:A,">="&Tabla7[[#This Row],[MES]],SALIDAS!A:A,"<="&MIN(TODAY(),EOMONTH(Tabla7[[#This Row],[MES]],0))) -> -106.6 | Y3: =SUMIFS(SALIDAS!F:F,SALIDAS!U:U,"OPEX",SALIDAS!V:V,Tabla7[[#Headers],[Customer Success]],SALIDAS!A:A,">="&Tabla7[[#This Row],[MES]],SALIDAS!A:A,"<="&MIN(TODAY(),EOMONTH(Tabla7[[#This Row],[MES]],0))) -> 0 | Z3: =SUMIFS(SALIDAS!F:F,SALIDAS!U:U,"OPEX",SALIDAS!A:A,">="&Tabla7[[#This Row],[MES]],SALIDAS!A:A,"<="&MIN(TODAY(),EOMONTH(Tabla7[[#This Row],[MES]],0))) -> -8413.5796 | AA3: =+Tabla7[[#This Row],[MARGEN BRUTO]]+SUM(Tabla7[[#This Row],[Sales & Marketing]:[General & Administrative]]) -> -9913.5796 | AB3: =ABS(SUMIFS(SALIDAS!F:F,SALIDAS!U:U,"CAPEX",SALIDAS!A:A,">="&Tabla7[[#This Row],[MES]],SALIDAS!A:A,"<="&MIN(TODAY(),EOMONTH(Tabla7[[#This Row],[MES]],0)))) -> 0 | AC3: =+Tabla7[[#This Row],[EBITDA]]-Tabla7[[#This Row],[TOTAL CAPEX]] -> -9913.5796 | AD3: =+Tabla7[[#This Row],[FCF]]+AD2 -> -12456.96 | AE3: =IFERROR(SUMIFS(SALIDAS!F:F,SALIDAS!U:U,"OPEX",SALIDAS!V:V,Tabla7[[#Headers],[Sales & Marketing]],SALIDAS!A:A,">="&Tabla7[[#This Row],[MES]],SALIDAS!A:A,"<="&MIN(TODAY(),EOMONTH(Tabla7[[#This Row],[MES]],0)))/_xlfn.XLOOKUP(Tabla7[[#This Row],[MES]],'COHORTES INGRESO'!A:A,'COHORTES INGRESO'!C:C),0) -> 0 | AF3: =+IFERROR(Tabla7[[#This Row],[COR]]/Tabla711[[#This Row],[NUEVOS CLIENTES TOTAL]],0) -> 0 | AG3: =Tabla7[[#This Row],[INGRESO MES RECIBIDO NETO]]+SUMIFS(SALIDAS!F:F,SALIDAS!T:T,"Costo variable",SALIDAS!A:A,">="&Tabla7[[#This Row],[MES]],SALIDAS!A:A,"<="&MIN(TODAY(),EOMONTH(Tabla7[[#This Row],[MES]],0))) -> -9850.2796 | AH3: =+IFERROR(AVERAGEIFS(INGRESOS!J:J,INGRESOS!$A:$A,">="&Tabla7[[#This Row],[MES]],INGRESOS!$A:$A,"<="&MIN(TODAY(),EOMONTH(Tabla7[[#This Row],[MES]],0))),0) -> 0
A4: 45658 | B4: =+Tabla7[[#This Row],[INGRESO MES RECIBIDO]]+Tabla7[[#This Row],[INGRESO PROGRAMADO PEND.]] -> 10953.596 | C4: =IFERROR((Tabla7[[#This Row],[INGRESO TOTAL MES]]/B3)-1,"0") -> 0 | D4: =SUMIFS(INGRESOS!G:G,INGRESOS!A:A,">="&EOMONTH(Tabla7[[#This Row],[MES]],-1)+1,INGRESOS!A:A,"<="&EOMONTH(Tabla7[[#This Row],[MES]],0)) -> 10953.596 | E4: =COUNTIFS(INGRESOS!$A:$A,">="&Tabla7[[#This Row],[MES]],INGRESOS!$A:$A,"<="&MIN(TODAY(),EOMONTH(Tabla7[[#This Row],[MES]],0))) -> 3 | F4: =SUMIFS('CALENDARIO INGRESOS'!I:I,'CALENDARIO INGRESOS'!G:G,">="&EOMONTH(Tabla7[[#This Row],[MES]],-1)+1,'CALENDARIO INGRESOS'!G:G,"<="&EOMONTH(Tabla7[[#This Row],[MES]],0),'CALENDARIO INGRESOS'!L:L,"PAGADA")/SUMIFS('CALENDARIO INGRESOS'!I:I,'CALENDARIO INGRESOS'!G:G,">="&EOMONTH(Tabla7[[#This Row],[MES]],-1)+1,'CALENDARIO INGRESOS'!G:G,"<="&EOMONTH(Tabla7[[#This Row],[MES]],0)) -> 1 | G4: =SUMIFS('CALENDARIO INGRESOS'!I:I,'CALENDARIO INGRESOS'!G:G,">="&EOMONTH(Tabla7[[#This Row],[MES]],-1)+1,'CALENDARIO INGRESOS'!G:G,"<="&EOMONTH(Tabla7[[#This Row],[MES]],0),'CALENDARIO INGRESOS'!L:L, "<>PAGADA",'CALENDARIO INGRESOS'!D:D,"<>ELIMINADO",'CALENDARIO INGRESOS'!D:D,"<>¡REGULARIZAR!") -> 0 | H4: =SUMIFS('CALENDARIO INGRESOS'!$I:$I, 'CALENDARIO INGRESOS'!$G:$G,">="&EOMONTH(Tabla7[[#This Row],[MES]],-1)+1, 'CALENDARIO INGRESOS'!$G:$G,"<="&EOMONTH(Tabla7[[#This Row],[MES]],0), 'CALENDARIO INGRESOS'!$L:$L,"<>PAGADA", 'CALENDARIO INGRESOS'!$G:$G,"<="&TODAY(),'CALENDARIO INGRESOS'!D:D,"<>¡REGULARIZAR!",'CALENDARIO INGRESOS'!D:D,"<>ELIMINADO") -> 0 | I4: =COUNTIFS('CALENDARIO INGRESOS'!$G:$G,">="&EOMONTH(Tabla7[[#This Row],[MES]],-1)+1,'CALENDARIO INGRESOS'!$G:$G,"<="&EOMONTH(Tabla7[[#This Row],[MES]],0),'CALENDARIO INGRESOS'!$D:$D,"<>ELIMINADO",'CALENDARIO INGRESOS'!$D:$D,"<>¡REGULARIZAR!",'CALENDARIO INGRESOS'!$L:$L,"<>PAGADA",'CALENDARIO INGRESOS'!$G:$G,"<="&TODAY()) -> 0 | J4: =SUMIFS('CALENDARIO INGRESOS'!$I:$I, 'CALENDARIO INGRESOS'!$G:$G,">="&EOMONTH(Tabla7[[#This Row],[MES]],-1)+1, 'CALENDARIO INGRESOS'!$G:$G,"<="&EOMONTH(Tabla7[[#This Row],[MES]],0), 'CALENDARIO INGRESOS'!$L:$L,"<>PAGADA", 'CALENDARIO INGRESOS'!$G:$G,">="&TODAY(),'CALENDARIO INGRESOS'!$D:$D,"<>ELIMINADO",'CALENDARIO INGRESOS'!$D:$D,"<>¡REGULARIZAR!") -> 0 | K4: =COUNTIFS('CALENDARIO INGRESOS'!$G:$G,">="&EOMONTH(Tabla7[[#This Row],[MES]],-1)+1,'CALENDARIO INGRESOS'!$G:$G,"<="&EOMONTH(Tabla7[[#This Row],[MES]],0),'CALENDARIO INGRESOS'!$D:$D,"<>ELIMINADO",'CALENDARIO INGRESOS'!$D:$D,"<>¡REGULARIZAR!",'CALENDARIO INGRESOS'!$L:$L,"<>PAGADA",'CALENDARIO INGRESOS'!$G:$G,">="&TODAY()) -> 0 | L4: =SUMIFS('CALENDARIO INGRESOS'!I:I,'CALENDARIO INGRESOS'!G:G,">="&EOMONTH(Tabla7[[#This Row],[MES]],-1)+1,'CALENDARIO INGRESOS'!G:G,"<="&EOMONTH(Tabla7[[#This Row],[MES]],0),'CALENDARIO INGRESOS'!L:L, "<>PAGADA",'CALENDARIO INGRESOS'!D:D,"¡REGULARIZAR!") -> 0 | M4: =COUNTIFS('CALENDARIO INGRESOS'!$G:$G,">="&EOMONTH(Tabla7[[#This Row],[MES]],-1)+1,'CALENDARIO INGRESOS'!$G:$G,"<="&EOMONTH(Tabla7[[#This Row],[MES]],0),'CALENDARIO INGRESOS'!$D:$D,"¡REGULARIZAR!",'CALENDARIO INGRESOS'!$L:$L,"<>PAGADA") -> 0 | N4: =SUMIFS('CALENDARIO INGRESOS'!I:I,'CALENDARIO INGRESOS'!G:G,">="&EOMONTH(Tabla7[[#This Row],[MES]],-1)+1,'CALENDARIO INGRESOS'!G:G,"<="&EOMONTH(Tabla7[[#This Row],[MES]],0),'CALENDARIO INGRESOS'!L:L, "<>PAGADA",'CALENDARIO INGRESOS'!D:D,"ELIMINADO") -> 0 | O4: =+IFERROR(Tabla7[[#This Row],[INCOBRABLE]]/Tabla7[[#This Row],[INGRESO TOTAL MES]],0) -> 0 | P4: =IFERROR(AVERAGEIFS(INGRESOS!I:I,INGRESOS!A:A,">="&Tabla7[[#This Row],[MES]],INGRESOS!A:A,"<="&MIN(TODAY(),EOMONTH(Tabla7[[#This Row],[MES]],0))),0) -> 0 | Q4: =SUMIFS(INGRESOS!$J:$J,INGRESOS!$A:$A,">="&Tabla7[[#This Row],[MES]],INGRESOS!$A:$A,"<="&MIN(TODAY(),EOMONTH(Tabla7[[#This Row],[MES]],0))) -> 10953.596 | R4: =SUMIFS(SALIDAS!F:F,SALIDAS!A:A,">="&Tabla7[[#This Row],[MES]],SALIDAS!A:A,"<="&MIN(TODAY(),EOMONTH(Tabla7[[#This Row],[MES]],0))) -> -17765.302 | S4: =SUMIFS(SALIDAS!F:F,SALIDAS!U:U,"COR",SALIDAS!A:A,">="&Tabla7[[#This Row],[MES]],SALIDAS!A:A,"<="&MIN(TODAY(),EOMONTH(Tabla7[[#This Row],[MES]],0))) -> -928.4 | T4: =Tabla7[[#This Row],[INGRESO MES RECIBIDO NETO]]+Tabla7[[#This Row],[COR]]+Tabla7[[#This Row],[Customer Success]] -> 8478.1963 | U4: =+IFERROR(Tabla7[[#This Row],[MARGEN BRUTO]]/Tabla7[[#This Row],[INGRESO MES RECIBIDO NETO]],"null") -> 0.77401029 | V4: =SUMIFS(SALIDAS!F:F,SALIDAS!U:U,"OPEX",SALIDAS!V:V,Tabla7[[#Headers],[Sales & Marketing]],SALIDAS!A:A,">="&Tabla7[[#This Row],[MES]],SALIDAS!A:A,"<="&MIN(TODAY(),EOMONTH(Tabla7[[#This Row],[MES]],0))) -> -8224.4055 | W4: =SUMIFS(SALIDAS!F:F,SALIDAS!U:U,"OPEX",SALIDAS!V:V,Tabla7[[#Headers],[Research & Development]],SALIDAS!A:A,">="&Tabla7[[#This Row],[MES]],SALIDAS!A:A,"<="&MIN(TODAY(),EOMONTH(Tabla7[[#This Row],[MES]],0))) -> -1347.22 | X4: =SUMIFS(SALIDAS!F:F,SALIDAS!U:U,"OPEX",SALIDAS!V:V,Tabla7[[#Headers],[General & Administrative]],SALIDAS!A:A,">="&Tabla7[[#This Row],[MES]],SALIDAS!A:A,"<="&MIN(TODAY(),EOMONTH(Tabla7[[#This Row],[MES]],0))) -> -5718.2762 | Y4: =SUMIFS(SALIDAS!F:F,SALIDAS!U:U,"OPEX",SALIDAS!V:V,Tabla7[[#Headers],[Customer Success]],SALIDAS!A:A,">="&Tabla7[[#This Row],[MES]],SALIDAS!A:A,"<="&MIN(TODAY(),EOMONTH(Tabla7[[#This Row],[MES]],0))) -> -1547 | Z4: =SUMIFS(SALIDAS!F:F,SALIDAS!U:U,"OPEX",SALIDAS!A:A,">="&Tabla7[[#This Row],[MES]],SALIDAS!A:A,"<="&MIN(TODAY(),EOMONTH(Tabla7[[#This Row],[MES]],0))) -> -16836.902 | AA4: =+Tabla7[[#This Row],[MARGEN BRUTO]]+SUM(Tabla7[[#This Row],[Sales & Marketing]:[General & Administrative]]) -> -6811.7054 | AB4: =ABS(SUMIFS(SALIDAS!F:F,SALIDAS!U:U,"CAPEX",SALIDAS!A:A,">="&Tabla7[[#This Row],[MES]],SALIDAS!A:A,"<="&MIN(TODAY(),EOMONTH(Tabla7[[#This Row],[MES]],0)))) -> 0 | AC4: =+Tabla7[[#This Row],[EBITDA]]-Tabla7[[#This Row],[TOTAL CAPEX]] -> -6811.7054 | AD4: =+Tabla7[[#This Row],[FCF]]+AD3 -> -19268.665 | AE4: =IFERROR(SUMIFS(SALIDAS!F:F,SALIDAS!U:U,"OPEX",SALIDAS!V:V,Tabla7[[#Headers],[Sales & Marketing]],SALIDAS!A:A,">="&Tabla7[[#This Row],[MES]],SALIDAS!A:A,"<="&MIN(TODAY(),EOMONTH(Tabla7[[#This Row],[MES]],0)))/_xlfn.XLOOKUP(Tabla7[[#This Row],[MES]],'COHORTES INGRESO'!A:A,'COHORTES INGRESO'!C:C),0) -> -2741.4685 | AF4: =+IFERROR(Tabla7[[#This Row],[COR]]/Tabla711[[#This Row],[NUEVOS CLIENTES TOTAL]],0) -> -309.46667 | AG4: =Tabla7[[#This Row],[INGRESO MES RECIBIDO NETO]]+SUMIFS(SALIDAS!F:F,SALIDAS!T:T,"Costo variable",SALIDAS!A:A,">="&Tabla7[[#This Row],[MES]],SALIDAS!A:A,"<="&MIN(TODAY(),EOMONTH(Tabla7[[#This Row],[MES]],0))) -> 9039.2263 | AH4: =+IFERROR(AVERAGEIFS(INGRESOS!J:J,INGRESOS!$A:$A,">="&Tabla7[[#This Row],[MES]],INGRESOS!$A:$A,"<="&MIN(TODAY(),EOMONTH(Tabla7[[#This Row],[MES]],0))),0) -> 3651.1988
A5: 45689 | B5: =+Tabla7[[#This Row],[INGRESO MES RECIBIDO]]+Tabla7[[#This Row],[INGRESO PROGRAMADO PEND.]] -> 10597.553 | C5: =IFERROR((Tabla7[[#This Row],[INGRESO TOTAL MES]]/B4)-1,"0") -> -0.032504712 | D5: =SUMIFS(INGRESOS!G:G,INGRESOS!A:A,">="&EOMONTH(Tabla7[[#This Row],[MES]],-1)+1,INGRESOS!A:A,"<="&EOMONTH(Tabla7[[#This Row],[MES]],0)) -> 10597.553 | E5: =COUNTIFS(INGRESOS!$A:$A,">="&Tabla7[[#This Row],[MES]],INGRESOS!$A:$A,"<="&MIN(TODAY(),EOMONTH(Tabla7[[#This Row],[MES]],0))) -> 1 | F5: =SUMIFS('CALENDARIO INGRESOS'!I:I,'CALENDARIO INGRESOS'!G:G,">="&EOMONTH(Tabla7[[#This Row],[MES]],-1)+1,'CALENDARIO INGRESOS'!G:G,"<="&EOMONTH(Tabla7[[#This Row],[MES]],0),'CALENDARIO INGRESOS'!L:L,"PAGADA")/SUMIFS('CALENDARIO INGRESOS'!I:I,'CALENDARIO INGRESOS'!G:G,">="&EOMONTH(Tabla7[[#This Row],[MES]],-1)+1,'CALENDARIO INGRESOS'!G:G,"<="&EOMONTH(Tabla7[[#This Row],[MES]],0)) -> 1 | G5: =SUMIFS('CALENDARIO INGRESOS'!I:I,'CALENDARIO INGRESOS'!G:G,">="&EOMONTH(Tabla7[[#This Row],[MES]],-1)+1,'CALENDARIO INGRESOS'!G:G,"<="&EOMONTH(Tabla7[[#This Row],[MES]],0),'CALENDARIO INGRESOS'!L:L, "<>PAGADA",'CALENDARIO INGRESOS'!D:D,"<>ELIMINADO",'CALENDARIO INGRESOS'!D:D,"<>¡REGULARIZAR!") -> 0 | H5: =SUMIFS('CALENDARIO INGRESOS'!$I:$I, 'CALENDARIO INGRESOS'!$G:$G,">="&EOMONTH(Tabla7[[#This Row],[MES]],-1)+1, 'CALENDARIO INGRESOS'!$G:$G,"<="&EOMONTH(Tabla7[[#This Row],[MES]],0), 'CALENDARIO INGRESOS'!$L:$L,"<>PAGADA", 'CALENDARIO INGRESOS'!$G:$G,"<="&TODAY(),'CALENDARIO INGRESOS'!D:D,"<>¡REGULARIZAR!",'CALENDARIO INGRESOS'!D:D,"<>ELIMINADO") -> 0 | I5: =COUNTIFS('CALENDARIO INGRESOS'!$G:$G,">="&EOMONTH(Tabla7[[#This Row],[MES]],-1)+1,'CALENDARIO INGRESOS'!$G:$G,"<="&EOMONTH(Tabla7[[#This Row],[MES]],0),'CALENDARIO INGRESOS'!$D:$D,"<>ELIMINADO",'CALENDARIO INGRESOS'!$D:$D,"<>¡REGULARIZAR!",'CALENDARIO INGRESOS'!$L:$L,"<>PAGADA",'CALENDARIO INGRESOS'!$G:$G,"<="&TODAY()) -> 0 | J5: =SUMIFS('CALENDARIO INGRESOS'!$I:$I, 'CALENDARIO INGRESOS'!$G:$G,">="&EOMONTH(Tabla7[[#This Row],[MES]],-1)+1, 'CALENDARIO INGRESOS'!$G:$G,"<="&EOMONTH(Tabla7[[#This Row],[MES]],0), 'CALENDARIO INGRESOS'!$L:$L,"<>PAGADA", 'CALENDARIO INGRESOS'!$G:$G,">="&TODAY(),'CALENDARIO INGRESOS'!$D:$D,"<>ELIMINADO",'CALENDARIO INGRESOS'!$D:$D,"<>¡REGULARIZAR!") -> 0 | K5: =COUNTIFS('CALENDARIO INGRESOS'!$G:$G,">="&EOMONTH(Tabla7[[#This Row],[MES]],-1)+1,'CALENDARIO INGRESOS'!$G:$G,"<="&EOMONTH(Tabla7[[#This Row],[MES]],0),'CALENDARIO INGRESOS'!$D:$D,"<>ELIMINADO",'CALENDARIO INGRESOS'!$D:$D,"<>¡REGULARIZAR!",'CALENDARIO INGRESOS'!$L:$L,"<>PAGADA",'CALENDARIO INGRESOS'!$G:$G,">="&TODAY()) -> 0 | L5: =SUMIFS('CALENDARIO INGRESOS'!I:I,'CALENDARIO INGRESOS'!G:G,">="&EOMONTH(Tabla7[[#This Row],[MES]],-1)+1,'CALENDARIO INGRESOS'!G:G,"<="&EOMONTH(Tabla7[[#This Row],[MES]],0),'CALENDARIO INGRESOS'!L:L, "<>PAGADA",'CALENDARIO INGRESOS'!D:D,"¡REGULARIZAR!") -> 0 | M5: =COUNTIFS('CALENDARIO INGRESOS'!$G:$G,">="&EOMONTH(Tabla7[[#This Row],[MES]],-1)+1,'CALENDARIO INGRESOS'!$G:$G,"<="&EOMONTH(Tabla7[[#This Row],[MES]],0),'CALENDARIO INGRESOS'!$D:$D,"¡REGULARIZAR!",'CALENDARIO INGRESOS'!$L:$L,"<>PAGADA") -> 0 | N5: =SUMIFS('CALENDARIO INGRESOS'!I:I,'CALENDARIO INGRESOS'!G:G,">="&EOMONTH(Tabla7[[#This Row],[MES]],-1)+1,'CALENDARIO INGRESOS'!G:G,"<="&EOMONTH(Tabla7[[#This Row],[MES]],0),'CALENDARIO INGRESOS'!L:L, "<>PAGADA",'CALENDARIO INGRESOS'!D:D,"ELIMINADO") -> 0 | O5: =+IFERROR(Tabla7[[#This Row],[INCOBRABLE]]/Tabla7[[#This Row],[INGRESO TOTAL MES]],0) -> 0 | P5: =IFERROR(AVERAGEIFS(INGRESOS!I:I,INGRESOS!A:A,">="&Tabla7[[#This Row],[MES]],INGRESOS!A:A,"<="&MIN(TODAY(),EOMONTH(Tabla7[[#This Row],[MES]],0))),0) -> 0.038000019 | Q5: =SUMIFS(INGRESOS!$J:$J,INGRESOS!$A:$A,">="&Tabla7[[#This Row],[MES]],INGRESOS!$A:$A,"<="&MIN(TODAY(),EOMONTH(Tabla7[[#This Row],[MES]],0))) -> 10194.846 | R5: =SUMIFS(SALIDAS!F:F,SALIDAS!A:A,">="&Tabla7[[#This Row],[MES]],SALIDAS!A:A,"<="&MIN(TODAY(),EOMONTH(Tabla7[[#This Row],[MES]],0))) -> -32402.219 | S5: =SUMIFS(SALIDAS!F:F,SALIDAS!U:U,"COR",SALIDAS!A:A,">="&Tabla7[[#This Row],[MES]],SALIDAS!A:A,"<="&MIN(TODAY(),EOMONTH(Tabla7[[#This Row],[MES]],0))) -> 0 | T5: =Tabla7[[#This Row],[INGRESO MES RECIBIDO NETO]]+Tabla7[[#This Row],[COR]]+Tabla7[[#This Row],[Customer Success]] -> 3410.5309 | U5: =+IFERROR(Tabla7[[#This Row],[MARGEN BRUTO]]/Tabla7[[#This Row],[INGRESO MES RECIBIDO NETO]],"null") -> 0.33453483 | V5: =SUMIFS(SALIDAS!F:F,SALIDAS!U:U,"OPEX",SALIDAS!V:V,Tabla7[[#Headers],[Sales & Marketing]],SALIDAS!A:A,">="&Tabla7[[#This Row],[MES]],SALIDAS!A:A,"<="&MIN(TODAY(),EOMONTH(Tabla7[[#This Row],[MES]],0))) -> -17413.583 | W5: =SUMIFS(SALIDAS!F:F,SALIDAS!U:U,"OPEX",SALIDAS!V:V,Tabla7[[#Headers],[Research & Development]],SALIDAS!A:A,">="&Tabla7[[#This Row],[MES]],SALIDAS!A:A,"<="&MIN(TODAY(),EOMONTH(Tabla7[[#This Row],[MES]],0))) -> -221.28 | X5: =SUMIFS(SALIDAS!F:F,SALIDAS!U:U,"OPEX",SALIDAS!V:V,Tabla7[[#Headers],[General & Administrative]],SALIDAS!A:A,">="&Tabla7[[#This Row],[MES]],SALIDAS!A:A,"<="&MIN(TODAY(),EOMONTH(Tabla7[[#This Row],[MES]],0))) -> -7983.0411 | Y5: =SUMIFS(SALIDAS!F:F,SALIDAS!U:U,"OPEX",SALIDAS!V:V,Tabla7[[#Headers],[Customer Success]],SALIDAS!A:A,">="&Tabla7[[#This Row],[MES]],SALIDAS!A:A,"<="&MIN(TODAY(),EOMONTH(Tabla7[[#This Row],[MES]],0))) -> -6784.3147 | Z5: =SUMIFS(SALIDAS!F:F,SALIDAS!U:U,"OPEX",SALIDAS!A:A,">="&Tabla7[[#This Row],[MES]],SALIDAS!A:A,"<="&MIN(TODAY(),EOMONTH(Tabla7[[#This Row],[MES]],0))) -> -32402.219 | AA5: =+Tabla7[[#This Row],[MARGEN BRUTO]]+SUM(Tabla7[[#This Row],[Sales & Marketing]:[General & Administrative]]) -> -22207.374 | AB5: =ABS(SUMIFS(SALIDAS!F:F,SALIDAS!U:U,"CAPEX",SALIDAS!A:A,">="&Tabla7[[#This Row],[MES]],SALIDAS!A:A,"<="&MIN(TODAY(),EOMONTH(Tabla7[[#This Row],[MES]],0)))) -> 0 | AC5: =+Tabla7[[#This Row],[EBITDA]]-Tabla7[[#This Row],[TOTAL CAPEX]] -> -22207.374 | AD5: =+Tabla7[[#This Row],[FCF]]+AD4 -> -41476.038 | AE5: =IFERROR(SUMIFS(SALIDAS!F:F,SALIDAS!U:U,"OPEX",SALIDAS!V:V,Tabla7[[#Headers],[Sales & Marketing]],SALIDAS!A:A,">="&Tabla7[[#This Row],[MES]],SALIDAS!A:A,"<="&MIN(TODAY(),EOMONTH(Tabla7[[#This Row],[MES]],0)))/_xlfn.XLOOKUP(Tabla7[[#This Row],[MES]],'COHORTES INGRESO'!A:A,'COHORTES INGRESO'!C:C),0) -> -17413.583 | AF5: =+IFERROR(Tabla7[[#This Row],[COR]]/Tabla711[[#This Row],[NUEVOS CLIENTES TOTAL]],0) -> 0 | AG5: =Tabla7[[#This Row],[INGRESO MES RECIBIDO NETO]]+SUMIFS(SALIDAS!F:F,SALIDAS!T:T,"Costo variable",SALIDAS!A:A,">="&Tabla7[[#This Row],[MES]],SALIDAS!A:A,"<="&MIN(TODAY(),EOMONTH(Tabla7[[#This Row],[MES]],0))) -> 4733.2656 | AH5: =+IFERROR(AVERAGEIFS(INGRESOS!J:J,INGRESOS!$A:$A,">="&Tabla7[[#This Row],[MES]],INGRESOS!$A:$A,"<="&MIN(TODAY(),EOMONTH(Tabla7[[#This Row],[MES]],0))),0) -> 10194.846
A6: 45717 | B6: =+Tabla7[[#This Row],[INGRESO MES RECIBIDO]]+Tabla7[[#This Row],[INGRESO PROGRAMADO PEND.]] -> 25909.029 | C6: =IFERROR((Tabla7[[#This Row],[INGRESO TOTAL MES]]/B5)-1,"0") -> 1.4448125 | D6: =SUMIFS(INGRESOS!G:G,INGRESOS!A:A,">="&EOMONTH(Tabla7[[#This Row],[MES]],-1)+1,INGRESOS!A:A,"<="&EOMONTH(Tabla7[[#This Row],[MES]],0)) -> 25909.029 | E6: =COUNTIFS(INGRESOS!$A:$A,">="&Tabla7[[#This Row],[MES]],INGRESOS!$A:$A,"<="&MIN(TODAY(),EOMONTH(Tabla7[[#This Row],[MES]],0))) -> 16 | F6: =SUMIFS('CALENDARIO INGRESOS'!I:I,'CALENDARIO INGRESOS'!G:G,">="&EOMONTH(Tabla7[[#This Row],[MES]],-1)+1,'CALENDARIO INGRESOS'!G:G,"<="&EOMONTH(Tabla7[[#This Row],[MES]],0),'CALENDARIO INGRESOS'!L:L,"PAGADA")/SUMIFS('CALENDARIO INGRESOS'!I:I,'CALENDARIO INGRESOS'!G:G,">="&EOMONTH(Tabla7[[#This Row],[MES]],-1)+1,'CALENDARIO INGRESOS'!G:G,"<="&EOMONTH(Tabla7[[#This Row],[MES]],0)) -> 1 | G6: =SUMIFS('CALENDARIO INGRESOS'!I:I,'CALENDARIO INGRESOS'!G:G,">="&EOMONTH(Tabla7[[#This Row],[MES]],-1)+1,'CALENDARIO INGRESOS'!G:G,"<="&EOMONTH(Tabla7[[#This Row],[MES]],0),'CALENDARIO INGRESOS'!L:L, "<>PAGADA",'CALENDARIO INGRESOS'!D:D,"<>ELIMINADO",'CALENDARIO INGRESOS'!D:D,"<>¡REGULARIZAR!") -> 0 | H6: =SUMIFS('CALENDARIO INGRESOS'!$I:$I, 'CALENDARIO INGRESOS'!$G:$G,">="&EOMONTH(Tabla7[[#This Row],[MES]],-1)+1, 'CALENDARIO INGRESOS'!$G:$G,"<="&EOMONTH(Tabla7[[#This Row],[MES]],0), 'CALENDARIO INGRESOS'!$L:$L,"<>PAGADA", 'CALENDARIO INGRESOS'!$G:$G,"<="&TODAY(),'CALENDARIO INGRESOS'!D:D,"<>¡REGULARIZAR!",'CALENDARIO INGRESOS'!D:D,"<>ELIMINADO") -> 0 | I6: =COUNTIFS('CALENDARIO INGRESOS'!$G:$G,">="&EOMONTH(Tabla7[[#This Row],[MES]],-1)+1,'CALENDARIO INGRESOS'!$G:$G,"<="&EOMONTH(Tabla7[[#This Row],[MES]],0),'CALENDARIO INGRESOS'!$D:$D,"<>ELIMINADO",'CALENDARIO INGRESOS'!$D:$D,"<>¡REGULARIZAR!",'CALENDARIO INGRESOS'!$L:$L,"<>PAGADA",'CALENDARIO INGRESOS'!$G:$G,"<="&TODAY()) -> 0 | J6: =SUMIFS('CALENDARIO INGRESOS'!$I:$I, 'CALENDARIO INGRESOS'!$G:$G,">="&EOMONTH(Tabla7[[#This Row],[MES]],-1)+1, 'CALENDARIO INGRESOS'!$G:$G,"<="&EOMONTH(Tabla7[[#This Row],[MES]],0), 'CALENDARIO INGRESOS'!$L:$L,"<>PAGADA", 'CALENDARIO INGRESOS'!$G:$G,">="&TODAY(),'CALENDARIO INGRESOS'!$D:$D,"<>ELIMINADO",'CALENDARIO INGRESOS'!$D:$D,"<>¡REGULARIZAR!") -> 0 | K6: =COUNTIFS('CALENDARIO INGRESOS'!$G:$G,">="&EOMONTH(Tabla7[[#This Row],[MES]],-1)+1,'CALENDARIO INGRESOS'!$G:$G,"<="&EOMONTH(Tabla7[[#This Row],[MES]],0),'CALENDARIO INGRESOS'!$D:$D,"<>ELIMINADO",'CALENDARIO INGRESOS'!$D:$D,"<>¡REGULARIZAR!",'CALENDARIO INGRESOS'!$L:$L,"<>PAGADA",'CALENDARIO INGRESOS'!$G:$G,">="&TODAY()) -> 0 | L6: =SUMIFS('CALENDARIO INGRESOS'!I:I,'CALENDARIO INGRESOS'!G:G,">="&EOMONTH(Tabla7[[#This Row],[MES]],-1)+1,'CALENDARIO INGRESOS'!G:G,"<="&EOMONTH(Tabla7[[#This Row],[MES]],0),'CALENDARIO INGRESOS'!L:L, "<>PAGADA",'CALENDARIO INGRESOS'!D:D,"¡REGULARIZAR!") -> 0 | M6: =COUNTIFS('CALENDARIO INGRESOS'!$G:$G,">="&EOMONTH(Tabla7[[#This Row],[MES]],-1)+1,'CALENDARIO INGRESOS'!$G:$G,"<="&EOMONTH(Tabla7[[#This Row],[MES]],0),'CALENDARIO INGRESOS'!$D:$D,"¡REGULARIZAR!",'CALENDARIO INGRESOS'!$L:$L,"<>PAGADA") -> 0 | N6: =SUMIFS('CALENDARIO INGRESOS'!I:I,'CALENDARIO INGRESOS'!G:G,">="&EOMONTH(Tabla7[[#This Row],[MES]],-1)+1,'CALENDARIO INGRESOS'!G:G,"<="&EOMONTH(Tabla7[[#This Row],[MES]],0),'CALENDARIO INGRESOS'!L:L, "<>PAGADA",'CALENDARIO INGRESOS'!D:D,"ELIMINADO") -> 0 | O6: =+IFERROR(Tabla7[[#This Row],[INCOBRABLE]]/Tabla7[[#This Row],[INGRESO TOTAL MES]],0) -> 0 | P6: =IFERROR(AVERAGEIFS(INGRESOS!I:I,INGRESOS!A:A,">="&Tabla7[[#This Row],[MES]],INGRESOS!A:A,"<="&MIN(TODAY(),EOMONTH(Tabla7[[#This Row],[MES]],0))),0) -> 0.033873762 | Q6: =SUMIFS(INGRESOS!$J:$J,INGRESOS!$A:$A,">="&Tabla7[[#This Row],[MES]],INGRESOS!$A:$A,"<="&MIN(TODAY(),EOMONTH(Tabla7[[#This Row],[MES]],0))) -> 25071.169 | R6: =SUMIFS(SALIDAS!F:F,SALIDAS!A:A,">="&Tabla7[[#This Row],[MES]],SALIDAS!A:A,"<="&MIN(TODAY(),EOMONTH(Tabla7[[#This Row],[MES]],0))) -> -56929.488 | S6: =SUMIFS(SALIDAS!F:F,SALIDAS!U:U,"COR",SALIDAS!A:A,">="&Tabla7[[#This Row],[MES]],SALIDAS!A:A,"<="&MIN(TODAY(),EOMONTH(Tabla7[[#This Row],[MES]],0))) -> -24882 | T6: =Tabla7[[#This Row],[INGRESO MES RECIBIDO NETO]]+Tabla7[[#This Row],[COR]]+Tabla7[[#This Row],[Customer Success]] -> -3515.267 | U6: =+IFERROR(Tabla7[[#This Row],[MARGEN BRUTO]]/Tabla7[[#This Row],[INGRESO MES RECIBIDO NETO]],"null") -> -0.14021153 | V6: =SUMIFS(SALIDAS!F:F,SALIDAS!U:U,"OPEX",SALIDAS!V:V,Tabla7[[#Headers],[Sales & Marketing]],SALIDAS!A:A,">="&Tabla7[[#This Row],[MES]],SALIDAS!A:A,"<="&MIN(TODAY(),EOMONTH(Tabla7[[#This Row],[MES]],0))) -> -22734.694 | W6: =SUMIFS(SALIDAS!F:F,SALIDAS!U:U,"OPEX",SALIDAS!V:V,Tabla7[[#Headers],[Research & Development]],SALIDAS!A:A,">="&Tabla7[[#This Row],[MES]],SALIDAS!A:A,"<="&MIN(TODAY(),EOMONTH(Tabla7[[#This Row],[MES]],0))) -> -221.52 | X6: =SUMIFS(SALIDAS!F:F,SALIDAS!U:U,"OPEX",SALIDAS!V:V,Tabla7[[#Headers],[General & Administrative]],SALIDAS!A:A,">="&Tabla7[[#This Row],[MES]],SALIDAS!A:A,"<="&MIN(TODAY(),EOMONTH(Tabla7[[#This Row],[MES]],0))) -> -3687.8382 | Y6: =SUMIFS(SALIDAS!F:F,SALIDAS!U:U,"OPEX",SALIDAS!V:V,Tabla7[[#Headers],[Customer Success]],SALIDAS!A:A,">="&Tabla7[[#This Row],[MES]],SALIDAS!A:A,"<="&MIN(TODAY(),EOMONTH(Tabla7[[#This Row],[MES]],0))) -> -3704.4358 | Z6: =SUMIFS(SALIDAS!F:F,SALIDAS!U:U,"OPEX",SALIDAS!A:A,">="&Tabla7[[#This Row],[MES]],SALIDAS!A:A,"<="&MIN(TODAY(),EOMONTH(Tabla7[[#This Row],[MES]],0))) -> -30348.488 | AA6: =+Tabla7[[#This Row],[MARGEN BRUTO]]+SUM(Tabla7[[#This Row],[Sales & Marketing]:[General & Administrative]]) -> -30159.319 | AB6: =ABS(SUMIFS(SALIDAS!F:F,SALIDAS!U:U,"CAPEX",SALIDAS!A:A,">="&Tabla7[[#This Row],[MES]],SALIDAS!A:A,"<="&MIN(TODAY(),EOMONTH(Tabla7[[#This Row],[MES]],0)))) -> 1699 | AC6: =+Tabla7[[#This Row],[EBITDA]]-Tabla7[[#This Row],[TOTAL CAPEX]] -> -31858.319 | AD6: =+Tabla7[[#This Row],[FCF]]+AD5 -> -73334.358 | AE6: =IFERROR(SUMIFS(SALIDAS!F:F,SALIDAS!U:U,"OPEX",SALIDAS!V:V,Tabla7[[#Headers],[Sales & Marketing]],SALIDAS!A:A,">="&Tabla7[[#This Row],[MES]],SALIDAS!A:A,"<="&MIN(TODAY(),EOMONTH(Tabla7[[#This Row],[MES]],0)))/_xlfn.XLOOKUP(Tabla7[[#This Row],[MES]],'COHORTES INGRESO'!A:A,'COHORTES INGRESO'!C:C),0) -> -1623.9067 | AF6: =+IFERROR(Tabla7[[#This Row],[COR]]/Tabla711[[#This Row],[NUEVOS CLIENTES TOTAL]],0) -> -1777.2857 | AG6: =Tabla7[[#This Row],[INGRESO MES RECIBIDO NETO]]+SUMIFS(SALIDAS!F:F,SALIDAS!T:T,"Costo variable",SALIDAS!A:A,">="&Tabla7[[#This Row],[MES]],SALIDAS!A:A,"<="&MIN(TODAY(),EOMONTH(Tabla7[[#This Row],[MES]],0))) -> 1508.1161 | AH6: =+IFERROR(AVERAGEIFS(INGRESOS!J:J,INGRESOS!$A:$A,">="&Tabla7[[#This Row],[MES]],INGRESOS!$A:$A,"<="&MIN(TODAY(),EOMONTH(Tabla7[[#This Row],[MES]],0))),0) -> 1566.9481
A7: 45748 | B7: =+Tabla7[[#This Row],[INGRESO MES RECIBIDO]]+Tabla7[[#This Row],[INGRESO PROGRAMADO PEND.]] -> 60640.365 | C7: =IFERROR((Tabla7[[#This Row],[INGRESO TOTAL MES]]/B6)-1,"0") -> 1.3405109 | D7: =SUMIFS(INGRESOS!G:G,INGRESOS!A:A,">="&EOMONTH(Tabla7[[#This Row],[MES]],-1)+1,INGRESOS!A:A,"<="&EOMONTH(Tabla7[[#This Row],[MES]],0)) -> 60640.365 | E7: =COUNTIFS(INGRESOS!$A:$A,">="&Tabla7[[#This Row],[MES]],INGRESOS!$A:$A,"<="&MIN(TODAY(),EOMONTH(Tabla7[[#This Row],[MES]],0))) -> 25 | F7: =SUMIFS('CALENDARIO INGRESOS'!I:I,'CALENDARIO INGRESOS'!G:G,">="&EOMONTH(Tabla7[[#This Row],[MES]],-1)+1,'CALENDARIO INGRESOS'!G:G,"<="&EOMONTH(Tabla7[[#This Row],[MES]],0),'CALENDARIO INGRESOS'!L:L,"PAGADA")/SUMIFS('CALENDARIO INGRESOS'!I:I,'CALENDARIO INGRESOS'!G:G,">="&EOMONTH(Tabla7[[#This Row],[MES]],-1)+1,'CALENDARIO INGRESOS'!G:G,"<="&EOMONTH(Tabla7[[#This Row],[MES]],0)) -> 1 | G7: =SUMIFS('CALENDARIO INGRESOS'!I:I,'CALENDARIO INGRESOS'!G:G,">="&EOMONTH(Tabla7[[#This Row],[MES]],-1)+1,'CALENDARIO INGRESOS'!G:G,"<="&EOMONTH(Tabla7[[#This Row],[MES]],0),'CALENDARIO INGRESOS'!L:L, "<>PAGADA",'CALENDARIO INGRESOS'!D:D,"<>ELIMINADO",'CALENDARIO INGRESOS'!D:D,"<>¡REGULARIZAR!") -> 0 | H7: =SUMIFS('CALENDARIO INGRESOS'!$I:$I, 'CALENDARIO INGRESOS'!$G:$G,">="&EOMONTH(Tabla7[[#This Row],[MES]],-1)+1, 'CALENDARIO INGRESOS'!$G:$G,"<="&EOMONTH(Tabla7[[#This Row],[MES]],0), 'CALENDARIO INGRESOS'!$L:$L,"<>PAGADA", 'CALENDARIO INGRESOS'!$G:$G,"<="&TODAY(),'CALENDARIO INGRESOS'!D:D,"<>¡REGULARIZAR!",'CALENDARIO INGRESOS'!D:D,"<>ELIMINADO") -> 0 | I7: =COUNTIFS('CALENDARIO INGRESOS'!$G:$G,">="&EOMONTH(Tabla7[[#This Row],[MES]],-1)+1,'CALENDARIO INGRESOS'!$G:$G,"<="&EOMONTH(Tabla7[[#This Row],[MES]],0),'CALENDARIO INGRESOS'!$D:$D,"<>ELIMINADO",'CALENDARIO INGRESOS'!$D:$D,"<>¡REGULARIZAR!",'CALENDARIO INGRESOS'!$L:$L,"<>PAGADA",'CALENDARIO INGRESOS'!$G:$G,"<="&TODAY()) -> 0 | J7: =SUMIFS('CALENDARIO INGRESOS'!$I:$I, 'CALENDARIO INGRESOS'!$G:$G,">="&EOMONTH(Tabla7[[#This Row],[MES]],-1)+1, 'CALENDARIO INGRESOS'!$G:$G,"<="&EOMONTH(Tabla7[[#This Row],[MES]],0), 'CALENDARIO INGRESOS'!$L:$L,"<>PAGADA", 'CALENDARIO INGRESOS'!$G:$G,">="&TODAY(),'CALENDARIO INGRESOS'!$D:$D,"<>ELIMINADO",'CALENDARIO INGRESOS'!$D:$D,"<>¡REGULARIZAR!") -> 0 | K7: =COUNTIFS('CALENDARIO INGRESOS'!$G:$G,">="&EOMONTH(Tabla7[[#This Row],[MES]],-1)+1,'CALENDARIO INGRESOS'!$G:$G,"<="&EOMONTH(Tabla7[[#This Row],[MES]],0),'CALENDARIO INGRESOS'!$D:$D,"<>ELIMINADO",'CALENDARIO INGRESOS'!$D:$D,"<>¡REGULARIZAR!",'CALENDARIO INGRESOS'!$L:$L,"<>PAGADA",'CALENDARIO INGRESOS'!$G:$G,">="&TODAY()) -> 0 | L7: =SUMIFS('CALENDARIO INGRESOS'!I:I,'CALENDARIO INGRESOS'!G:G,">="&EOMONTH(Tabla7[[#This Row],[MES]],-1)+1,'CALENDARIO INGRESOS'!G:G,"<="&EOMONTH(Tabla7[[#This Row],[MES]],0),'CALENDARIO INGRESOS'!L:L, "<>PAGADA",'CALENDARIO INGRESOS'!D:D,"¡REGULARIZAR!") -> 0 | M7: =COUNTIFS('CALENDARIO INGRESOS'!$G:$G,">="&EOMONTH(Tabla7[[#This Row],[MES]],-1)+1,'CALENDARIO INGRESOS'!$G:$G,"<="&EOMONTH(Tabla7[[#This Row],[MES]],0),'CALENDARIO INGRESOS'!$D:$D,"¡REGULARIZAR!",'CALENDARIO INGRESOS'!$L:$L,"<>PAGADA") -> 0 | N7: =SUMIFS('CALENDARIO INGRESOS'!I:I,'CALENDARIO INGRESOS'!G:G,">="&EOMONTH(Tabla7[[#This Row],[MES]],-1)+1,'CALENDARIO INGRESOS'!G:G,"<="&EOMONTH(Tabla7[[#This Row],[MES]],0),'CALENDARIO INGRESOS'!L:L, "<>PAGADA",'CALENDARIO INGRESOS'!D:D,"ELIMINADO") -> 0 | O7: =+IFERROR(Tabla7[[#This Row],[INCOBRABLE]]/Tabla7[[#This Row],[INGRESO TOTAL MES]],0) -> 0 | P7: =IFERROR(AVERAGEIFS(INGRESOS!I:I,INGRESOS!A:A,">="&Tabla7[[#This Row],[MES]],INGRESOS!A:A,"<="&MIN(TODAY(),EOMONTH(Tabla7[[#This Row],[MES]],0))),0) -> 0.023155143 | Q7: =SUMIFS(INGRESOS!$J:$J,INGRESOS!$A:$A,">="&Tabla7[[#This Row],[MES]],INGRESOS!$A:$A,"<="&MIN(TODAY(),EOMONTH(Tabla7[[#This Row],[MES]],0))) -> 59179.123 | R7: =SUMIFS(SALIDAS!F:F,SALIDAS!A:A,">="&Tabla7[[#This Row],[MES]],SALIDAS!A:A,"<="&MIN(TODAY(),EOMONTH(Tabla7[[#This Row],[MES]],0))) -> -47061.493 | S7: =SUMIFS(SALIDAS!F:F,SALIDAS!U:U,"COR",SALIDAS!A:A,">="&Tabla7[[#This Row],[MES]],SALIDAS!A:A,"<="&MIN(TODAY(),EOMONTH(Tabla7[[#This Row],[MES]],0))) -> -10827.76 | T7: =Tabla7[[#This Row],[INGRESO MES RECIBIDO NETO]]+Tabla7[[#This Row],[COR]]+Tabla7[[#This Row],[Customer Success]] -> 44256.081 | U7: =+IFERROR(Tabla7[[#This Row],[MARGEN BRUTO]]/Tabla7[[#This Row],[INGRESO MES RECIBIDO NETO]],"null") -> 0.74783265 | V7: =SUMIFS(SALIDAS!F:F,SALIDAS!U:U,"OPEX",SALIDAS!V:V,Tabla7[[#Headers],[Sales & Marketing]],SALIDAS!A:A,">="&Tabla7[[#This Row],[MES]],SALIDAS!A:A,"<="&MIN(TODAY(),EOMONTH(Tabla7[[#This Row],[MES]],0))) -> -23562.81 | W7: =SUMIFS(SALIDAS!F:F,SALIDAS!U:U,"OPEX",SALIDAS!V:V,Tabla7[[#Headers],[Research & Development]],SALIDAS!A:A,">="&Tabla7[[#This Row],[MES]],SALIDAS!A:A,"<="&MIN(TODAY(),EOMONTH(Tabla7[[#This Row],[MES]],0))) -> -180.022 | X7: =SUMIFS(SALIDAS!F:F,SALIDAS!U:U,"OPEX",SALIDAS!V:V,Tabla7[[#Headers],[General & Administrative]],SALIDAS!A:A,">="&Tabla7[[#This Row],[MES]],SALIDAS!A:A,"<="&MIN(TODAY(),EOMONTH(Tabla7[[#This Row],[MES]],0))) -> -8395.6184 | Y7: =SUMIFS(SALIDAS!F:F,SALIDAS!U:U,"OPEX",SALIDAS!V:V,Tabla7[[#Headers],[Customer Success]],SALIDAS!A:A,">="&Tabla7[[#This Row],[MES]],SALIDAS!A:A,"<="&MIN(TODAY(),EOMONTH(Tabla7[[#This Row],[MES]],0))) -> -4095.2829 | Z7: =SUMIFS(SALIDAS!F:F,SALIDAS!U:U,"OPEX",SALIDAS!A:A,">="&Tabla7[[#This Row],[MES]],SALIDAS!A:A,"<="&MIN(TODAY(),EOMONTH(Tabla7[[#This Row],[MES]],0))) -> -36233.733 | AA7: =+Tabla7[[#This Row],[MARGEN BRUTO]]+SUM(Tabla7[[#This Row],[Sales & Marketing]:[General & Administrative]]) -> 12117.631 | AB7: =ABS(SUMIFS(SALIDAS!F:F,SALIDAS!U:U,"CAPEX",SALIDAS!A:A,">="&Tabla7[[#This Row],[MES]],SALIDAS!A:A,"<="&MIN(TODAY(),EOMONTH(Tabla7[[#This Row],[MES]],0)))) -> 0 | AC7: =+Tabla7[[#This Row],[EBITDA]]-Tabla7[[#This Row],[TOTAL CAPEX]] -> 12117.631 | AD7: =+Tabla7[[#This Row],[FCF]]+AD6 -> -61216.727 | AE7: =IFERROR(SUMIFS(SALIDAS!F:F,SALIDAS!U:U,"OPEX",SALIDAS!V:V,Tabla7[[#Headers],[Sales & Marketing]],SALIDAS!A:A,">="&Tabla7[[#This Row],[MES]],SALIDAS!A:A,"<="&MIN(TODAY(),EOMONTH(Tabla7[[#This Row],[MES]],0)))/_xlfn.XLOOKUP(Tabla7[[#This Row],[MES]],'COHORTES INGRESO'!A:A,'COHORTES INGRESO'!C:C),0) -> -1240.1479 | AF7: =+IFERROR(Tabla7[[#This Row],[COR]]/Tabla711[[#This Row],[NUEVOS CLIENTES TOTAL]],0) -> -569.88211 | AG7: =Tabla7[[#This Row],[INGRESO MES RECIBIDO NETO]]+SUMIFS(SALIDAS!F:F,SALIDAS!T:T,"Costo variable",SALIDAS!A:A,">="&Tabla7[[#This Row],[MES]],SALIDAS!A:A,"<="&MIN(TODAY(),EOMONTH(Tabla7[[#This Row],[MES]],0))) -> 40927.489 | AH7: =+IFERROR(AVERAGEIFS(INGRESOS!J:J,INGRESOS!$A:$A,">="&Tabla7[[#This Row],[MES]],INGRESOS!$A:$A,"<="&MIN(TODAY(),EOMONTH(Tabla7[[#This Row],[MES]],0))),0) -> 2367.1649
A8: 45778 | B8: =+Tabla7[[#This Row],[INGRESO MES RECIBIDO]]+Tabla7[[#This Row],[INGRESO PROGRAMADO PEND.]] -> 58656.78 | C8: =IFERROR((Tabla7[[#This Row],[INGRESO TOTAL MES]]/B7)-1,"0") -> -0.032710631 | D8: =SUMIFS(INGRESOS!G:G,INGRESOS!A:A,">="&EOMONTH(Tabla7[[#This Row],[MES]],-1)+1,INGRESOS!A:A,"<="&EOMONTH(Tabla7[[#This Row],[MES]],0)) -> 58656.78 | E8: =COUNTIFS(INGRESOS!$A:$A,">="&Tabla7[[#This Row],[MES]],INGRESOS!$A:$A,"<="&MIN(TODAY(),EOMONTH(Tabla7[[#This Row],[MES]],0))) -> 38 | F8: =SUMIFS('CALENDARIO INGRESOS'!I:I,'CALENDARIO INGRESOS'!G:G,">="&EOMONTH(Tabla7[[#This Row],[MES]],-1)+1,'CALENDARIO INGRESOS'!G:G,"<="&EOMONTH(Tabla7[[#This Row],[MES]],0),'CALENDARIO INGRESOS'!L:L,"PAGADA")/SUMIFS('CALENDARIO INGRESOS'!I:I,'CALENDARIO INGRESOS'!G:G,">="&EOMONTH(Tabla7[[#This Row],[MES]],-1)+1,'CALENDARIO INGRESOS'!G:G,"<="&EOMONTH(Tabla7[[#This Row],[MES]],0)) -> 1 | G8: =SUMIFS('CALENDARIO INGRESOS'!I:I,'CALENDARIO INGRESOS'!G:G,">="&EOMONTH(Tabla7[[#This Row],[MES]],-1)+1,'CALENDARIO INGRESOS'!G:G,"<="&EOMONTH(Tabla7[[#This Row],[MES]],0),'CALENDARIO INGRESOS'!L:L, "<>PAGADA",'CALENDARIO INGRESOS'!D:D,"<>ELIMINADO",'CALENDARIO INGRESOS'!D:D,"<>¡REGULARIZAR!") -> 0 | H8: =SUMIFS('CALENDARIO INGRESOS'!$I:$I, 'CALENDARIO INGRESOS'!$G:$G,">="&EOMONTH(Tabla7[[#This Row],[MES]],-1)+1, 'CALENDARIO INGRESOS'!$G:$G,"<="&EOMONTH(Tabla7[[#This Row],[MES]],0), 'CALENDARIO INGRESOS'!$L:$L,"<>PAGADA", 'CALENDARIO INGRESOS'!$G:$G,"<="&TODAY(),'CALENDARIO INGRESOS'!D:D,"<>¡REGULARIZAR!",'CALENDARIO INGRESOS'!D:D,"<>ELIMINADO") -> 0 | I8: =COUNTIFS('CALENDARIO INGRESOS'!$G:$G,">="&EOMONTH(Tabla7[[#This Row],[MES]],-1)+1,'CALENDARIO INGRESOS'!$G:$G,"<="&EOMONTH(Tabla7[[#This Row],[MES]],0),'CALENDARIO INGRESOS'!$D:$D,"<>ELIMINADO",'CALENDARIO INGRESOS'!$D:$D,"<>¡REGULARIZAR!",'CALENDARIO INGRESOS'!$L:$L,"<>PAGADA",'CALENDARIO INGRESOS'!$G:$G,"<="&TODAY()) -> 0 | J8: =SUMIFS('CALENDARIO INGRESOS'!$I:$I, 'CALENDARIO INGRESOS'!$G:$G,">="&EOMONTH(Tabla7[[#This Row],[MES]],-1)+1, 'CALENDARIO INGRESOS'!$G:$G,"<="&EOMONTH(Tabla7[[#This Row],[MES]],0), 'CALENDARIO INGRESOS'!$L:$L,"<>PAGADA", 'CALENDARIO INGRESOS'!$G:$G,">="&TODAY(),'CALENDARIO INGRESOS'!$D:$D,"<>ELIMINADO",'CALENDARIO INGRESOS'!$D:$D,"<>¡REGULARIZAR!") -> 0 | K8: =COUNTIFS('CALENDARIO INGRESOS'!$G:$G,">="&EOMONTH(Tabla7[[#This Row],[MES]],-1)+1,'CALENDARIO INGRESOS'!$G:$G,"<="&EOMONTH(Tabla7[[#This Row],[MES]],0),'CALENDARIO INGRESOS'!$D:$D,"<>ELIMINADO",'CALENDARIO INGRESOS'!$D:$D,"<>¡REGULARIZAR!",'CALENDARIO INGRESOS'!$L:$L,"<>PAGADA",'CALENDARIO INGRESOS'!$G:$G,">="&TODAY()) -> 0 | L8: =SUMIFS('CALENDARIO INGRESOS'!I:I,'CALENDARIO INGRESOS'!G:G,">="&EOMONTH(Tabla7[[#This Row],[MES]],-1)+1,'CALENDARIO INGRESOS'!G:G,"<="&EOMONTH(Tabla7[[#This Row],[MES]],0),'CALENDARIO INGRESOS'!L:L, "<>PAGADA",'CALENDARIO INGRESOS'!D:D,"¡REGULARIZAR!") -> 0 | M8: =COUNTIFS('CALENDARIO INGRESOS'!$G:$G,">="&EOMONTH(Tabla7[[#This Row],[MES]],-1)+1,'CALENDARIO INGRESOS'!$G:$G,"<="&EOMONTH(Tabla7[[#This Row],[MES]],0),'CALENDARIO INGRESOS'!$D:$D,"¡REGULARIZAR!",'CALENDARIO INGRESOS'!$L:$L,"<>PAGADA") -> 0 | N8: =SUMIFS('CALENDARIO INGRESOS'!I:I,'CALENDARIO INGRESOS'!G:G,">="&EOMONTH(Tabla7[[#This Row],[MES]],-1)+1,'CALENDARIO INGRESOS'!G:G,"<="&EOMONTH(Tabla7[[#This Row],[MES]],0),'CALENDARIO INGRESOS'!L:L, "<>PAGADA",'CALENDARIO INGRESOS'!D:D,"ELIMINADO") -> 0 | O8: =+IFERROR(Tabla7[[#This Row],[INCOBRABLE]]/Tabla7[[#This Row],[INGRESO TOTAL MES]],0) -> 0 | P8: =IFERROR(AVERAGEIFS(INGRESOS!I:I,INGRESOS!A:A,">="&Tabla7[[#This Row],[MES]],INGRESOS!A:A,"<="&MIN(TODAY(),EOMONTH(Tabla7[[#This Row],[MES]],0))),0) -> 0.028309699 | Q8: =SUMIFS(INGRESOS!$J:$J,INGRESOS!$A:$A,">="&Tabla7[[#This Row],[MES]],INGRESOS!$A:$A,"<="&MIN(TODAY(),EOMONTH(Tabla7[[#This Row],[MES]],0))) -> 57208.64 | R8: =SUMIFS(SALIDAS!F:F,SALIDAS!A:A,">="&Tabla7[[#This Row],[MES]],SALIDAS!A:A,"<="&MIN(TODAY(),EOMONTH(Tabla7[[#This Row],[MES]],0))) -> -53876.674 | S8: =SUMIFS(SALIDAS!F:F,SALIDAS!U:U,"COR",SALIDAS!A:A,">="&Tabla7[[#This Row],[MES]],SALIDAS!A:A,"<="&MIN(TODAY(),EOMONTH(Tabla7[[#This Row],[MES]],0))) -> -13057.68 | T8: =Tabla7[[#This Row],[INGRESO MES RECIBIDO NETO]]+Tabla7[[#This Row],[COR]]+Tabla7[[#This Row],[Customer Success]] -> 39264.755 | U8: =+IFERROR(Tabla7[[#This Row],[MARGEN BRUTO]]/Tabla7[[#This Row],[INGRESO MES RECIBIDO NETO]],"null") -> 0.6863431 | V8: =SUMIFS(SALIDAS!F:F,SALIDAS!U:U,"OPEX",SALIDAS!V:V,Tabla7[[#Headers],[Sales & Marketing]],SALIDAS!A:A,">="&Tabla7[[#This Row],[MES]],SALIDAS!A:A,"<="&MIN(TODAY(),EOMONTH(Tabla7[[#This Row],[MES]],0))) -> -25428.314 | W8: =SUMIFS(SALIDAS!F:F,SALIDAS!U:U,"OPEX",SALIDAS!V:V,Tabla7[[#Headers],[Research & Development]],SALIDAS!A:A,">="&Tabla7[[#This Row],[MES]],SALIDAS!A:A,"<="&MIN(TODAY(),EOMONTH(Tabla7[[#This Row],[MES]],0))) -> -441.71 | X8: =SUMIFS(SALIDAS!F:F,SALIDAS!U:U,"OPEX",SALIDAS!V:V,Tabla7[[#Headers],[General & Administrative]],SALIDAS!A:A,">="&Tabla7[[#This Row],[MES]],SALIDAS!A:A,"<="&MIN(TODAY(),EOMONTH(Tabla7[[#This Row],[MES]],0))) -> -10062.765 | Y8: =SUMIFS(SALIDAS!F:F,SALIDAS!U:U,"OPEX",SALIDAS!V:V,Tabla7[[#Headers],[Customer Success]],SALIDAS!A:A,">="&Tabla7[[#This Row],[MES]],SALIDAS!A:A,"<="&MIN(TODAY(),EOMONTH(Tabla7[[#This Row],[MES]],0))) -> -4886.2049 | Z8: =SUMIFS(SALIDAS!F:F,SALIDAS!U:U,"OPEX",SALIDAS!A:A,">="&Tabla7[[#This Row],[MES]],SALIDAS!A:A,"<="&MIN(TODAY(),EOMONTH(Tabla7[[#This Row],[MES]],0))) -> -40818.994 | AA8: =+Tabla7[[#This Row],[MARGEN BRUTO]]+SUM(Tabla7[[#This Row],[Sales & Marketing]:[General & Administrative]]) -> 3331.9657 | AB8: =ABS(SUMIFS(SALIDAS!F:F,SALIDAS!U:U,"CAPEX",SALIDAS!A:A,">="&Tabla7[[#This Row],[MES]],SALIDAS!A:A,"<="&MIN(TODAY(),EOMONTH(Tabla7[[#This Row],[MES]],0)))) -> 0 | AC8: =+Tabla7[[#This Row],[EBITDA]]-Tabla7[[#This Row],[TOTAL CAPEX]] -> 3331.9657 | AD8: =+Tabla7[[#This Row],[FCF]]+AD7 -> -57884.761 | AE8: =IFERROR(SUMIFS(SALIDAS!F:F,SALIDAS!U:U,"OPEX",SALIDAS!V:V,Tabla7[[#Headers],[Sales & Marketing]],SALIDAS!A:A,">="&Tabla7[[#This Row],[MES]],SALIDAS!A:A,"<="&MIN(TODAY(),EOMONTH(Tabla7[[#This Row],[MES]],0)))/_xlfn.XLOOKUP(Tabla7[[#This Row],[MES]],'COHORTES INGRESO'!A:A,'COHORTES INGRESO'!C:C),0) -> -1695.221 | AF8: =+IFERROR(Tabla7[[#This Row],[COR]]/Tabla711[[#This Row],[NUEVOS CLIENTES TOTAL]],0) -> -870.512 | AG8: =Tabla7[[#This Row],[INGRESO MES RECIBIDO NETO]]+SUMIFS(SALIDAS!F:F,SALIDAS!T:T,"Costo variable",SALIDAS!A:A,">="&Tabla7[[#This Row],[MES]],SALIDAS!A:A,"<="&MIN(TODAY(),EOMONTH(Tabla7[[#This Row],[MES]],0))) -> 38756.795 | AH8: =+IFERROR(AVERAGEIFS(INGRESOS!J:J,INGRESOS!$A:$A,">="&Tabla7[[#This Row],[MES]],INGRESOS!$A:$A,"<="&MIN(TODAY(),EOMONTH(Tabla7[[#This Row],[MES]],0))),0) -> 1505.4905
